Workbook
Name Acustica: TB_Caracteristicas!$P$45
Name Danceability: TB_Caracteristicas!$P$46
Name Energia: TB_Caracteristicas!$P$47
Name high_popularity_spotify_data: Dataset!$A$1:$AC$1687
Name Modern: TB_Distribucion!$D$78
Name SegmentaciónDeDatos_Playlist_genre21: #N/A
Name SegmentaciónDeDatos_playlist_name: #N/A
Name SegmentaciónDeDatos_Playlist_subgenre2: #N/A
Name SegmentaciónDeDatos_Popularidad: #N/A
Name Throwback: TB_Distribucion!$G$92:$H$92
Name Throwbackp: TB_Distribucion!$G$92
Name Total_Pop: TB_Distribucion!$A$56
Name Valence: TB_Caracteristicas!$P$48

Sheet Dataset
A1: energy | B1: tempo | C1: danceability | D1: playlist_genre | E1: loudness | F1: liveness | G1: valence | H1: track_artist | I1: time_signature | J1: speechiness | K1: track_popularity | L1: track_href | M1: uri | N1: track_album_name | O1: playlist_name | P1: analysis_url | Q1: track_id | R1: track_name | S1: track_album_release_date | T1: instrumentalness | U1: track_album_id | V1: mode | W1: key | X1: duration_ms | Y1: acousticness | Z1: id | AA1: playlist_subgenre | AB1: type | AC1: playlist_id
A2: 0.592 | B2: 157969 | C2: 0.521 | D2: pop | E2: -7777 | F2: 0.122 | G2: 0.535 | H2: Lady Gaga, Bruno Mars | I2: 3 | J2: 0.0304 | K2: 100 | L2: https://api.spotify.com/v1/tracks/2plbrEY59IikOBgBGLjaoe | M2: spotify:track:2plbrEY59IikOBgBGLjaoe | N2: Die With A Smile | O2: Today's Top Hits | P2: https://api.spotify.com/v1/audio-analysis/2plbrEY59IikOBgBGLjaoe | Q2: 2plbrEY59IikOBgBGLjaoe | R2: Die With A Smile | S2: 45520 | T2: 0 | U2: 10FLjwfpbxLmW8c25Xyc2N | V2: 0 | W2: 6 | X2: 251668 | Y2: 0.308 | Z2: 2plbrEY59IikOBgBGLjaoe | AA2: mainstream | AB2: audio_features | AC2: 37i9dQZF1DXcBWIGoYBM5M
A3: 0.507 | B3: 104978 | C3: 0.747 | D3: pop | E3: -10171 | F3: 0.117 | G3: 0.438 | H3: Billie Eilish | I3: 4 | J3: 0.0358 | K3: 97 | L3: https://api.spotify.com/v1/tracks/6dOtVTDdiauQNBQEDOtlAB | M3: spotify:track:6dOtVTDdiauQNBQEDOtlAB | N3: HIT ME HARD AND SOFT | O3: Today's Top Hits | P3: https://api.spotify.com/v1/audio-analysis/6dOtVTDdiauQNBQEDOtlAB | Q3: 6dOtVTDdiauQNBQEDOtlAB | R3: BIRDS OF A FEATHER | S3: 45429 | T3: 0.0608 | U3: 7aJuG4TFXa2hmE4z1yxc3n | V3: 1 | W3: 2 | X3: 210373 | Y3: 0.2 | Z3: 6dOtVTDdiauQNBQEDOtlAB | AA3: mainstream | AB3: audio_features | AC3: 37i9dQZF1DXcBWIGoYBM5M
A4: 0.808 | B4: 108548 | C4: 0.554 | D4: pop | E4: -4169 | F4: 0.159 | G4: 0.372 | H4: Gracie Abrams | I4: 4 | J4: 0.0368 | K4: 93 | L4: https://api.spotify.com/v1/tracks/7ne4VBA60CxGM75vw0EYad | M4: spotify:track:7ne4VBA60CxGM75vw0EYad | N4: The Secret of Us (Deluxe) | O4: Today's Top Hits | P4: https://api.spotify.com/v1/audio-analysis/7ne4VBA60CxGM75vw0EYad | Q4: 7ne4VBA60CxGM75vw0EYad | R4: That‚Äôs So True | S4: 45583 | T4: 0 | U4: 0hBRqPYPXhr1RkTDG3n4Mk | V4: 1 | W4: 1 | X4: 166300 | Y4: 0.214 | Z4: 7ne4VBA60CxGM75vw0EYad | AA4: mainstream | AB4: audio_features | AC4: 37i9dQZF1DXcBWIGoYBM5M
A5: 0.91 | B5: 112966 | C5: 0.67 | D5: pop | E5: -4.07 | F5: 0.304 | G5: 0.786 | H5: Sabrina Carpenter | I5: 4 | J5: 0.0634 | K5: 81 | L5: https://api.spotify.com/v1/tracks/1d7Ptw3qYcfpdLNL5REhtJ | M5: spotify:track:1d7Ptw3qYcfpdLNL5REhtJ | N5: Short n' Sweet | O5: Today's Top Hits | P5: https://api.spotify.com/v1/audio-analysis/1d7Ptw3qYcfpdLNL5REhtJ | Q5: 1d7Ptw3qYcfpdLNL5REhtJ | R5: Taste | S5: 45527 | T5: 0 | U5: 4B4Elma4nNDUyl6D5PvQkj | V5: 0 | W5: 0 | X5: 157280 | Y5: 0.0939 | Z5: 1d7Ptw3qYcfpdLNL5REhtJ | AA5: mainstream | AB5: audio_features | AC5: 37i9dQZF1DXcBWIGoYBM5M
A6: 0.783 | B6: 149027 | C6: 0.777 | D6: pop | E6: -4477 | F6: 0.355 | G6: 0.939 | H6: ROS√â, Bruno Mars | I6: 4 | J6: 0.26 | K6: 98 | L6: https://api.spotify.com/v1/tracks/5vNRhkKd0yEAg8suGBpjeY | M6: spotify:track:5vNRhkKd0yEAg8suGBpjeY | N6: APT. | O6: Today's Top Hits | P6: https://api.spotify.com/v1/audio-analysis/5vNRhkKd0yEAg8suGBpjeY | Q6: 5vNRhkKd0yEAg8suGBpjeY | R6: APT. | S6: 45583 | T6: 0 | U6: 2IYQwwgxgOIn7t3iF6ufFD | V6: 0 | W6: 0 | X6: 169917 | Y6: 0.0283 | Z6: 5vNRhkKd0yEAg8suGBpjeY | AA6: mainstream | AB6: audio_features | AC6: 37i9dQZF1DXcBWIGoYBM5M
A7: 0.582 | B7: 116712 | C7: 0.7 | D7: pop | E7: -5.96 | F7: 0.0881 | G7: 0.785 | H7: Chappell Roan | I7: 4 | J7: 0.0356 | K7: 94 | L7: https://api.spotify.com/v1/tracks/0WbMK4wrZ1wFSty9F7FCgu | M7: spotify:track:0WbMK4wrZ1wFSty9F7FCgu | N7: Good Luck, Babe! | O7: Today's Top Hits | P7: https://api.spotify.com/v1/audio-analysis/0WbMK4wrZ1wFSty9F7FCgu | Q7: 0WbMK4wrZ1wFSty9F7FCgu | R7: Good Luck, Babe! | S7: 45387 | T7: 0 | U7: 1WAjjRMfZjEXtB0lQrAw6Q | V7: 0 | W7: 11 | X7: 218424 | Y7: 0.0502 | Z7: 0WbMK4wrZ1wFSty9F7FCgu | AA7: mainstream | AB7: audio_features | AC7: 37i9dQZF1DXcBWIGoYBM5M
A8: 0.561 | B8: 150069 | C8: 0.669 | D8: pop | E8: -6538 | F8: 0.0954 | G8: 0.841 | H8: Addison Rae | I8: 4 | J8: 0.0411 | K8: 88 | L8: https://api.spotify.com/v1/tracks/6MzofobZt2dm0Kf1hTThFz | M8: spotify:track:6MzofobZt2dm0Kf1hTThFz | N8: Diet Pepsi | O8: Today's Top Hits | P8: https://api.spotify.com/v1/audio-analysis/6MzofobZt2dm0Kf1hTThFz | Q8: 6MzofobZt2dm0Kf1hTThFz | R8: Diet Pepsi | S8: 45513 | T8: 0.00962 | U8: 0XA403JTounqFh2owquBXu | V8: 1 | W8: 10 | X8: 169698 | Y8: 0.495 | Z8: 6MzofobZt2dm0Kf1hTThFz | AA8: mainstream | AB8: audio_features | AC8: 37i9dQZF1DXcBWIGoYBM5M
A9: 0.247 | B9: 148101 | C9: 0.467 | D9: pop | E9: -12002 | F9: 0.17 | G9: 0.126 | H9: Billie Eilish | I9: 4 | J9: 0.0431 | K9: 93 | L9: https://api.spotify.com/v1/tracks/3QaPy1KgI7nu9FJEQUgn6h | M9: spotify:track:3QaPy1KgI7nu9FJEQUgn6h | N9: HIT ME HARD AND SOFT | O9: Today's Top Hits | P9: https://api.spotify.com/v1/audio-analysis/3QaPy1KgI7nu9FJEQUgn6h | Q9: 3QaPy1KgI7nu9FJEQUgn6h | R9: WILDFLOWER | S9: 45429 | T9: 0.000271 | U9: 7aJuG4TFXa2hmE4z1yxc3n | V9: 0 | W9: 6 | X9: 261467 | Y9: 0.612 | Z9: 3QaPy1KgI7nu9FJEQUgn6h | AA9: mainstream | AB9: audio_features | AC9: 37i9dQZF1DXcBWIGoYBM5M
A10: 0.416 | B10: 94926 | C10: 0.492 | D10: pop | E10: -10439 | F10: 0.203 | G10: 0.297 | H10: Gigi Perez | I10: 4 | J10: 0.0254 | K10: 71 | L10: https://api.spotify.com/v1/tracks/0UYnhUfnUj5adChuAXvLUB | M10: spotify:track:0UYnhUfnUj5adChuAXvLUB | N10: Sailor Song | O10: Today's Top Hits | P10: https://api.spotify.com/v1/audio-analysis/0UYnhUfnUj5adChuAXvLUB | Q10: 0UYnhUfnUj5adChuAXvLUB | R10: Sailor Song | S10: 45499 | T10: 8.61e-05 | U10: 4DWrYvfGXRE8ko5ZxlIpit | V10: 1 | W10: 11 | X10: 211979 | Y10: 0.686 | Z10: 0UYnhUfnUj5adChuAXvLUB | AA10: mainstream | AB10: audio_features | AC10: 37i9dQZF1DXcBWIGoYBM5M
A11: 0.722 | B11: 119973 | C11: 0.769 | D11: pop | E11: -5485 | F11: 0.111 | G11: 0.57 | H11: The Weeknd, Playboi Carti | I11: 4 | J11: 0.0507 | K11: 92 | L11: https://api.spotify.com/v1/tracks/1Es7AUAhQvapIcoh3qMKDL | M11: spotify:track:1Es7AUAhQvapIcoh3qMKDL | N11: Timeless | O11: Today's Top Hits | P11: https://api.spotify.com/v1/audio-analysis/1Es7AUAhQvapIcoh3qMKDL | Q11: 1Es7AUAhQvapIcoh3qMKDL | R11: Timeless (with Playboi Carti) | S11: 45562 | T11: 2.56e-06 | U11: 2IRxVVqbSbqHJo8Zx50LYn | V11: 0 | W11: 11 | X11: 256000 | Y11: 0.0584 | Z11: 1Es7AUAhQvapIcoh3qMKDL | AA11: mainstream | AB11: audio_features | AC11: 37i9dQZF1DXcBWIGoYBM5M
A12: 0.667 | B12: 130019 | C12: 0.776 | D12: pop | E12: -6622 | F12: 0.0761 | G12: 0.618 | H12: Charli xcx, Billie Eilish | I12: 4 | J12: 0.0983 | K12: 85 | L12: https://api.spotify.com/v1/tracks/3WOhcATHxK2SLNeP5W3v1v | M12: spotify:track:3WOhcATHxK2SLNeP5W3v1v | N12: Guess featuring Billie Eilish | O12: Today's Top Hits | P12: https://api.spotify.com/v1/audio-analysis/3WOhcATHxK2SLNeP5W3v1v | Q12: 3WOhcATHxK2SLNeP5W3v1v | R12: Guess featuring billie eilish | S12: 45505 | T12: 0.3 | U12: 3ThlxfLSy4bfKzxWqmC7VN | V12: 1 | W12: 7 | X12: 145219 | Y12: 0.0146 | Z12: 3WOhcATHxK2SLNeP5W3v1v | AA12: mainstream | AB12: audio_features | AC12: 37i9dQZF1DXcBWIGoYBM5M
A13: 0.586 | B13: 107071 | C13: 0.669 | D13: pop | E13: -6073 | F13: 0.104 | G13: 0.579 | H13: Sabrina Carpenter | I13: 4 | J13: 0.054 | K13: 88 | L13: https://api.spotify.com/v1/tracks/5N3hjp1WNayUPZrA8kJmJP | M13: spotify:track:5N3hjp1WNayUPZrA8kJmJP | N13: Please Please Please | O13: Today's Top Hits | P13: https://api.spotify.com/v1/audio-analysis/5N3hjp1WNayUPZrA8kJmJP | Q13: 5N3hjp1WNayUPZrA8kJmJP | R13: Please Please Please | S13: 45449 | T13: 0 | U13: 5bBaoign62r1i7OV8w7mi9 | V13: 1 | W13: 9 | X13: 186365 | Y13: 0.274 | Z13: 5N3hjp1WNayUPZrA8kJmJP | AA13: mainstream | AB13: audio_features | AC13: 37i9dQZF1DXcBWIGoYBM5M
A14: 0.806 | B14: 104032 | C14: 0.608 | D14: pop | E14: -3443 | F14: 0.191 | G14: 0.587 | H14: Tate McRae | I14: 4 | J14: 0.0486 | K14: 79 | L14: https://api.spotify.com/v1/tracks/1f18HzFpegqvH4ibGJyeMJ | M14: spotify:track:1f18HzFpegqvH4ibGJyeMJ | N14: 2 hands | O14: Today's Top Hits | P14: https://api.spotify.com/v1/audio-analysis/1f18HzFpegqvH4ibGJyeMJ | Q14: 1f18HzFpegqvH4ibGJyeMJ | R14: 2 hands | S14: 45610 | T14: 0 | U14: 2BdJwrx2wMJi7x06wWkUFg | V14: 1 | W14: 1 | X14: 181821 | Y14: 0.121 | Z14: 1f18HzFpegqvH4ibGJyeMJ | AA14: mainstream | AB14: audio_features | AC14: 37i9dQZF1DXcBWIGoYBM5M
A15: 0.709 | B15: 81012 | C15: 0.722 | D15: pop | E15: -4.95 | F15: 0.0804 | G15: 0.604 | H15: Shaboozey | I15: 4 | J15: 0.0273 | K15: 86 | L15: https://api.spotify.com/v1/tracks/2FQrifJ1N335Ljm3TjTVVf | M15: spotify:track:2FQrifJ1N335Ljm3TjTVVf | N15: A Bar Song (Tipsy) | O15: Today's Top Hits | P15: https://api.spotify.com/v1/audio-analysis/2FQrifJ1N335Ljm3TjTVVf | Q15: 2FQrifJ1N335Ljm3TjTVVf | R15: A Bar Song (Tipsy) | S15: 45394 | T15: 0 | U15: 6egBeCLeGITzGSo5VyRjwZ | V15: 1 | W15: 9 | X15: 171292 | Y15: 0.0633 | Z15: 2FQrifJ1N335Ljm3TjTVVf | AA15: mainstream | AB15: audio_features | AC15: 37i9dQZF1DXcBWIGoYBM5M
A16: 0.757 | B16: 139982 | C16: 0.742 | D16: pop | E16: -4981 | F16: 0.305 | G16: 0.957 | H16: Chappell Roan | I16: 4 | J16: 0.0421 | K16: 88 | L16: https://api.spotify.com/v1/tracks/4xdBrk0nFZaP54vvZj0yx7 | M16: spotify:track:4xdBrk0nFZaP54vvZj0yx7 | N16: The Rise and Fall of a Midwest Princess | O16: Today's Top Hits | P16: https://api.spotify.com/v1/audio-analysis/4xdBrk0nFZaP54vvZj0yx7 | Q16: 4xdBrk0nFZaP54vvZj0yx7 | R16: HOT TO GO! | S16: 45191 | T16: 0 | U16: 0EiI8ylL0FmWWpgHVTsZjZ | V16: 1 | W16: 6 | X16: 184841 | Y16: 0.0187 | Z16: 4xdBrk0nFZaP54vvZj0yx7 | AA16: mainstream | AB16: audio_features | AC16: 37i9dQZF1DXcBWIGoYBM5M
A17: 0.917 | B17: 100987 | C17: 0.562 | D17: pop | E17: -2768 | F17: 0.488 | G17: 0.501 | H17: Lady Gaga | I17: 4 | J17: 0.117 | K17: 86 | L17: https://api.spotify.com/v1/tracks/19KlZwqlT3fguP2BeHF1Q1 | M17: spotify:track:19KlZwqlT3fguP2BeHF1Q1 | N17: Disease | O17: Today's Top Hits | P17: https://api.spotify.com/v1/audio-analysis/19KlZwqlT3fguP2BeHF1Q1 | Q17: 19KlZwqlT3fguP2BeHF1Q1 | R17: Disease | S17: 45590 | T17: 0 | U17: 52BWvTRMsPqjHzrbQomgwP | V17: 0 | W17: 11 | X17: 229997 | Y17: 0.0513 | Z17: 19KlZwqlT3fguP2BeHF1Q1 | AA17: mainstream | AB17: audio_features | AC17: 37i9dQZF1DXcBWIGoYBM5M
A18: 0.787 | B18: 109939 | C18: 0.734 | D18: pop | E18: -3951 | F18: 0.312 | G18: 0.672 | H18: LISA | I18: 4 | J18: 0.116 | K18: 82 | L18: https://api.spotify.com/v1/tracks/5G345YEhvleYxQLfYUlEFv | M18: spotify:track:5G345YEhvleYxQLfYUlEFv | N18: Moonlit Floor (Kiss Me) | O18: Today's Top Hits | P18: https://api.spotify.com/v1/audio-analysis/5G345YEhvleYxQLfYUlEFv | Q18: 5G345YEhvleYxQLfYUlEFv | R18: Moonlit Floor (Kiss Me) | S18: 45573 | T18: 0 | U18: 1OGxb1Z5KDBVOwDtyKu8wz | V18: 0 | W18: 5 | X18: 155757 | Y18: 0.126 | Z18: 5G345YEhvleYxQLfYUlEFv | AA18: mainstream | AB18: audio_features | AC18: 37i9dQZF1DXcBWIGoYBM5M
A19: 0.843 | B19: 122064 | C19: 0.619 | D19: pop | E19: -5348 | F19: 0.164 | G19: 0.746 | H19: Morgan Wallen | I19: 4 | J19: 0.0284 | K19: 86 | L19: https://api.spotify.com/v1/tracks/7hR22TOX3RorxJPcsz5Wbo | M19: spotify:track:7hR22TOX3RorxJPcsz5Wbo | N19: Love Somebody | O19: Today's Top Hits | P19: https://api.spotify.com/v1/audio-analysis/7hR22TOX3RorxJPcsz5Wbo | Q19: 7hR22TOX3RorxJPcsz5Wbo | R19: Love Somebody | S19: 45583 | T19: 0.000118 | U19: 0TxewlKVKdpP18dGg279ep | V19: 0 | W19: 5 | X19: 204829 | Y19: 0.00948 | Z19: 7hR22TOX3RorxJPcsz5Wbo | AA19: mainstream | AB19: audio_features | AC19: 37i9dQZF1DXcBWIGoYBM5M
A20: 0.406 | B20: 115.94 | C20: 0.53 | D20: pop | E20: -7507 | F20: 0.133 | G20: 0.338 | H20: Gracie Abrams | I20: 3 | J20: 0.033 | K20: 90 | L20: https://api.spotify.com/v1/tracks/51rfRCiUSvxXlCSCfIztBy | M20: spotify:track:51rfRCiUSvxXlCSCfIztBy | N20: The Secret of Us | O20: Today's Top Hits | P20: https://api.spotify.com/v1/audio-analysis/51rfRCiUSvxXlCSCfIztBy | Q20: 51rfRCiUSvxXlCSCfIztBy | R20: I Love You, I'm Sorry | S20: 45464 | T20: 0 | U20: 56bdWeO40o3WfAD2Lja4dl | V20: 1 | W20: 10 | X20: 157147 | Y20: 0.656 | Z20: 51rfRCiUSvxXlCSCfIztBy | AA20: mainstream | AB20: audio_features | AC20: 37i9dQZF1DXcBWIGoYBM5M
A21: 0.782 | B21: 119992 | C21: 0.727 | D21: pop | E21: -8529 | F21: 0.225 | G21: 0.655 | H21: Adam Port, Stryv, Keinemusik, Orso, Malachiii | I21: 4 | J21: 0.042 | K21: 86 | L21: https://api.spotify.com/v1/tracks/1BJJbSX6muJVF2AK7uH1x4 | M21: spotify:track:1BJJbSX6muJVF2AK7uH1x4 | N21: Move | O21: Today's Top Hits | P21: https://api.spotify.com/v1/audio-analysis/1BJJbSX6muJVF2AK7uH1x4 | Q21: 1BJJbSX6muJVF2AK7uH1x4 | R21: Move | S21: 45450 | T21: 0.336 | U21: 4M8ThNHbNjda2cPwL8XZHS | V21: 0 | W21: 8 | X21: 177599 | Y21: 0.0563 | Z21: 1BJJbSX6muJVF2AK7uH1x4 | AA21: mainstream | AB21: audio_features | AC21: 37i9dQZF1DXcBWIGoYBM5M
A22: 0.812 | B22: 80.09 | C22: 0.505 | D22: pop | E22: -3986 | F22: 0.444 | G22: 0.664 | H22: Tyler, The Creator, GloRilla, Sexyy Red, Lil Wayne | I22: 4 | J22: 0.461 | K22: 88 | L22: https://api.spotify.com/v1/tracks/3tFed7YsjGnIfxeLEQwx3R | M22: spotify:track:3tFed7YsjGnIfxeLEQwx3R | N22: CHROMAKOPIA | O22: Today's Top Hits | P22: https://api.spotify.com/v1/audio-analysis/3tFed7YsjGnIfxeLEQwx3R | Q22: 3tFed7YsjGnIfxeLEQwx3R | R22: Sticky (feat. GloRilla, Sexyy Red & Lil Wayne) | S22: 45593 | T22: 0 | U22: 0U28P0QVB1QRxpqp5IHOlH | V22: 1 | W22: 1 | X22: 255916 | Y22: 0.285 | Z22: 3tFed7YsjGnIfxeLEQwx3R | AA22: mainstream | AB22: audio_features | AC22: 37i9dQZF1DXcBWIGoYBM5M
A23: 0.76 | B23: 103969 | C23: 0.701 | D23: pop | E23: -5478 | F23: 0.185 | G23: 0.69 | H23: Sabrina Carpenter | I23: 4 | J23: 0.0285 | K23: 90 | L23: https://api.spotify.com/v1/tracks/2qSkIjg1o9h3YT9RAgYN75 | M23: spotify:track:2qSkIjg1o9h3YT9RAgYN75 | N23: Espresso | O23: Today's Top Hits | P23: https://api.spotify.com/v1/audio-analysis/2qSkIjg1o9h3YT9RAgYN75 | Q23: 2qSkIjg1o9h3YT9RAgYN75 | R23: Espresso | S23: 45394 | T23: 6.54e-05 | U23: 5quMTd5zeI9yW5UDua8wS4 | V23: 1 | W23: 0 | X23: 175459 | Y23: 0.107 | Z23: 2qSkIjg1o9h3YT9RAgYN75 | AA23: mainstream | AB23: audio_features | AC23: 37i9dQZF1DXcBWIGoYBM5M
A24: 0.725 | B24: 116988 | C24: 0.894 | D24: pop | E24: -4984 | F24: 0.0815 | G24: 0.838 | H24: JENNIE | I24: 4 | J24: 0.0432 | K24: 89 | L24: https://api.spotify.com/v1/tracks/2CspwnypzT7rcWI9RfsoSb | M24: spotify:track:2CspwnypzT7rcWI9RfsoSb | N24: Mantra | O24: Today's Top Hits | P24: https://api.spotify.com/v1/audio-analysis/2CspwnypzT7rcWI9RfsoSb | Q24: 2CspwnypzT7rcWI9RfsoSb | R24: Mantra | S24: 45575 | T24: 1.15e-05 | U24: 3e5tDT1kfaAGx10yOjIDgW | V24: 0 | W24: 10 | X24: 136627 | Y24: 0.00434 | Z24: 2CspwnypzT7rcWI9RfsoSb | AA24: mainstream | AB24: audio_features | AC24: 37i9dQZF1DXcBWIGoYBM5M
A25: 0.563 | B25: 105008 | C25: 0.833 | D25: pop | E25: -5593 | F25: 0.139 | G25: 0.343 | H25: Rauw Alejandro, Bad Bunny | I25: 4 | J25: 0.204 | K25: 82 | L25: https://api.spotify.com/v1/tracks/0l0vcZMU7AOeQmUIREoI2U | M25: spotify:track:0l0vcZMU7AOeQmUIREoI2U | N25: Cosa Nuestra | O25: Today's Top Hits | P25: https://api.spotify.com/v1/audio-analysis/0l0vcZMU7AOeQmUIREoI2U | Q25: 0l0vcZMU7AOeQmUIREoI2U | R25: Qu√© Pasar√≠a... | S25: 45611 | T25: 1.27e-05 | U25: 0aX0UXrHG2ceYIxTQcqJdA | V25: 0 | W25: 4 | X25: 182857 | Y25: 0.528 | Z25: 0l0vcZMU7AOeQmUIREoI2U | AA25: mainstream | AB25: audio_features | AC25: 37i9dQZF1DXcBWIGoYBM5M
A26: 0.628 | B26: 119.98 | C26: 0.757 | D26: pop | E26: -6715 | F26: 0.221 | G26: 0.321 | H26: Don Toliver | I26: 4 | J26: 0.101 | K26: 85 | L26: https://api.spotify.com/v1/tracks/2c7z5oRcPBbqRaBY2mLWcf | M26: spotify:track:2c7z5oRcPBbqRaBY2mLWcf | N26: HARDSTONE PSYCHO | O26: Today's Top Hits | P26: https://api.spotify.com/v1/audio-analysis/2c7z5oRcPBbqRaBY2mLWcf | Q26: 2c7z5oRcPBbqRaBY2mLWcf | R26: NEW DROP | S26: 45457 | T26: 0.0209 | U26: 0Kzb3u6kMnOJOZXYFSk33F | V26: 0 | W26: 4 | X26: 217333 | Y26: 0.189 | Z26: 2c7z5oRcPBbqRaBY2mLWcf | AA26: mainstream | AB26: audio_features | AC26: 37i9dQZF1DXcBWIGoYBM5M
A27: 0.855 | B27: 127986 | C27: 0.638 | D27: pop | E27: -4.86 | F27: 0.245 | G27: 0.731 | H27: Post Malone, Morgan Wallen | I27: 4 | J27: 0.0264 | K27: 84 | L27: https://api.spotify.com/v1/tracks/7221xIgOnuakPdLqT0F3nP | M27: spotify:track:7221xIgOnuakPdLqT0F3nP | N27: I Had Some Help | O27: Today's Top Hits | P27: https://api.spotify.com/v1/audio-analysis/7221xIgOnuakPdLqT0F3nP | Q27: 7221xIgOnuakPdLqT0F3nP | R27: I Had Some Help (Feat. Morgan Wallen) | S27: 45422 | T27: 0 | U27: 1woYXxyyxTQJ0E0AhZE6mj | V27: 1 | W27: 7 | X27: 178206 | Y27: 0.00757 | Z27: 7221xIgOnuakPdLqT0F3nP | AA27: mainstream | AB27: audio_features | AC27: 37i9dQZF1DXcBWIGoYBM5M
A28: 0.62 | B28: 117038 | C28: 0.741 | D28: pop | E28: -5505 | F28: 0.0398 | G28: 0.934 | H28: Hozier | I28: 4 | J28: 0.0412 | K28: 77 | L28: https://api.spotify.com/v1/tracks/4IadxL6BUymXlh8RCJJu7T | M28: spotify:track:4IadxL6BUymXlh8RCJJu7T | N28: Unheard | O28: Today's Top Hits | P28: https://api.spotify.com/v1/audio-analysis/4IadxL6BUymXlh8RCJJu7T | Q28: 4IadxL6BUymXlh8RCJJu7T | R28: Too Sweet | S28: 45373 | T28: 0.000809 | U28: 1KZC0cX0qq6hodR9YVgh9F | V28: 1 | W28: 10 | X28: 251424 | Y28: 0.0295 | Z28: 4IadxL6BUymXlh8RCJJu7T | AA28: mainstream | AB28: audio_features | AC28: 37i9dQZF1DXcBWIGoYBM5M
A29: 0.339 | B29: 97989 | C29: 0.705 | D29: pop | E29: -10612 | F29: 0.12 | G29: 0.457 | H29: The Mar√≠as | I29: 4 | J29: 0.0278 | K29: 84 | L29: https://api.spotify.com/v1/tracks/3siwsiaEoU4Kuuc9WKMUy5 | M29: spotify:track:3siwsiaEoU4Kuuc9WKMUy5 | N29: Submarine | O29: Today's Top Hits | P29: https://api.spotify.com/v1/audio-analysis/3siwsiaEoU4Kuuc9WKMUy5 | Q29: 3siwsiaEoU4Kuuc9WKMUy5 | R29: No One Noticed | S29: 45443 | T29: 0.0814 | U29: 03guxdOi12XJbnvxvxbpwG | V29: 1 | W29: 7 | X29: 236907 | Y29: 0.552 | Z29: 3siwsiaEoU4Kuuc9WKMUy5 | AA29: mainstream | AB29: audio_features | AC29: 37i9dQZF1DXcBWIGoYBM5M
A30: 0.651 | B30: 112648 | C30: 0.694 | D30: pop | E30: -6968 | F30: 0.0787 | G30: 0.471 | H30: Oscar Maydon, Fuerza Regida | I30: 3 | J30: 0.0784 | K30: 93 | L30: https://api.spotify.com/v1/tracks/1cOboCuWYI2osTOfolMRS6 | M30: spotify:track:1cOboCuWYI2osTOfolMRS6 | N30: Tu Boda | O30: Today's Top Hits | P30: https://api.spotify.com/v1/audio-analysis/1cOboCuWYI2osTOfolMRS6 | Q30: 1cOboCuWYI2osTOfolMRS6 | R30: Tu Boda | S30: 45561 | T30: 1.36e-05 | U30: 60cQzWfmdg4hyDXrpW6kOA | V30: 1 | W30: 6 | X30: 225881 | Y30: 0.496 | Z30: 1cOboCuWYI2osTOfolMRS6 | AA30: mainstream | AB30: audio_features | AC30: 37i9dQZF1DXcBWIGoYBM5M
A31: 0.601 | B31: 123994 | C31: 0.635 | D31: pop | E31: -6129 | F31: 0.11 | G31: 0.332 | H31: Myles Smith | I31: 4 | J31: 0.0295 | K31: 88 | L31: https://api.spotify.com/v1/tracks/3Vr3zh0r7ALn8VLqCiRR10 | M31: spotify:track:3Vr3zh0r7ALn8VLqCiRR10 | N31: Stargazing | O31: Today's Top Hits | P31: https://api.spotify.com/v1/audio-analysis/3Vr3zh0r7ALn8VLqCiRR10 | Q31: 3Vr3zh0r7ALn8VLqCiRR10 | R31: Stargazing | S31: 45422 | T31: 0 | U31: 3VNxRarx9HUI5w7DHv0TBj | V31: 0 | W31: 1 | X31: 172533 | Y31: 0.246 | Z31: 3Vr3zh0r7ALn8VLqCiRR10 | AA31: mainstream | AB31: audio_features | AC31: 37i9dQZF1DXcBWIGoYBM5M
A32: 0.691 | B32: 167029 | C32: 0.836 | D32: pop | E32: -4222 | F32: 0.282 | G32: 0.703 | H32: GloRilla, Sexyy Red | I32: 4 | J32: 0.363 | K32: 70 | L32: https://api.spotify.com/v1/tracks/4VI2Y5xg4gYynQqNQNQbTN | M32: spotify:track:4VI2Y5xg4gYynQqNQNQbTN | N32: WHATCHU KNO ABOUT ME (with Sexyy Red) | O32: Today's Top Hits | P32: https://api.spotify.com/v1/audio-analysis/4VI2Y5xg4gYynQqNQNQbTN | Q32: 4VI2Y5xg4gYynQqNQNQbTN | R32: WHATCHU KNO ABOUT ME (with Sexyy Red) | S32: 45575 | T32: 0 | U32: 2PzoiaGTcK3NfnMgHFd7QC | V32: 1 | W32: 1 | X32: 149461 | Y32: 0.00586 | Z32: 4VI2Y5xg4gYynQqNQNQbTN | AA32: mainstream | AB32: audio_features | AC32: 37i9dQZF1DXcBWIGoYBM5M
A33: 0.646 | B33: 115842 | C33: 0.645 | D33: pop | E33: -8334 | F33: 0.074 | G33: 0.295 | H33: Ariana Grande | I33: 4 | J33: 0.0427 | K33: 81 | L33: https://api.spotify.com/v1/tracks/46kspZSY3aKmwQe7O77fCC | M33: spotify:track:46kspZSY3aKmwQe7O77fCC | N33: eternal sunshine | O33: Today's Top Hits | P33: https://api.spotify.com/v1/audio-analysis/46kspZSY3aKmwQe7O77fCC | Q33: 46kspZSY3aKmwQe7O77fCC | R33: we can't be friends (wait for your love) | S33: 45359 | T33: 3.04e-05 | U33: 71PfP4E9roOXAudea1aPGw | V33: 1 | W33: 5 | X33: 228639 | Y33: 0.0615 | Z33: 46kspZSY3aKmwQe7O77fCC | AA33: mainstream | AB33: audio_features | AC33: 37i9dQZF1DXcBWIGoYBM5M
A34: 0.471 | B34: 105029 | C34: 0.472 | D34: pop | E34: -5692 | F34: 0.14 | G34: 0.219 | H34: Benson Boone | I34: 3 | J34: 0.0603 | K34: 85 | L34: https://api.spotify.com/v1/tracks/6tNQ70jh4OwmPGpYy6R2o9 | M34: spotify:track:6tNQ70jh4OwmPGpYy6R2o9 | N34: Beautiful Things | O34: Today's Top Hits | P34: https://api.spotify.com/v1/audio-analysis/6tNQ70jh4OwmPGpYy6R2o9 | Q34: 6tNQ70jh4OwmPGpYy6R2o9 | R34: Beautiful Things | S34: 45309 | T34: 0 | U34: 29aSKB1qPEbN0Qf9OPSQpw | V34: 1 | W34: 10 | X34: 180304 | Y34: 0.151 | Z34: 6tNQ70jh4OwmPGpYy6R2o9 | AA34: mainstream | AB34: audio_features | AC34: 37i9dQZF1DXcBWIGoYBM5M
A35: 0.709 | B35: 194055 | C35: 0.744 | D35: pop | E35: -5778 | F35: 0.0847 | G35: 0.712 | H35: Myke Towers, benny blanco | I35: 4 | J35: 0.284 | K35: 84 | L35: https://api.spotify.com/v1/tracks/0qeIFEGRQqHoaJtLCl0U73 | M35: spotify:track:0qeIFEGRQqHoaJtLCl0U73 | N35: LA PANTERA NEGRA (DELUXE) | O35: Today's Top Hits | P35: https://api.spotify.com/v1/audio-analysis/0qeIFEGRQqHoaJtLCl0U73 | Q35: 0qeIFEGRQqHoaJtLCl0U73 | R35: DEGENERE üëë (feat. benny blanco) | S35: 45582 | T35: 0 | U35: 3pkIK8SI5mcUUjb9jNjx4H | V35: 0 | W35: 6 | X35: 130880 | Y35: 0.0501 | Z35: 0qeIFEGRQqHoaJtLCl0U73 | AA35: mainstream | AB35: audio_features | AC35: 37i9dQZF1DXcBWIGoYBM5M
A36: 0.904 | B36: 167033 | C36: 0.739 | D36: pop | E36: -2655 | F36: 0.0948 | G36: 0.788 | H36: KATSEYE | I36: 4 | J36: 0.0442 | K36: 85 | L36: https://api.spotify.com/v1/tracks/6aJn7Cst74cj4lNIiPRgav | M36: spotify:track:6aJn7Cst74cj4lNIiPRgav | N36: Touch | O36: Today's Top Hits | P36: https://api.spotify.com/v1/audio-analysis/6aJn7Cst74cj4lNIiPRgav | Q36: 6aJn7Cst74cj4lNIiPRgav | R36: Touch | S36: 45499 | T36: 1.03e-05 | U36: 1hjqg3TuQ2YqooaPhxHwdv | V36: 0 | W36: 5 | X36: 129883 | Y36: 0.549 | Z36: 6aJn7Cst74cj4lNIiPRgav | AA36: mainstream | AB36: audio_features | AC36: 37i9dQZF1DXcBWIGoYBM5M
A37: 0.604 | B37: 159.92 | C37: 0.561 | D37: pop | E37: -4409 | F37: 0.104 | G37: 0.242 | H37: Teddy Swims | I37: 3 | J37: 0.0337 | K37: 89 | L37: https://api.spotify.com/v1/tracks/17phhZDn6oGtzMe56NuWvj | M37: spotify:track:17phhZDn6oGtzMe56NuWvj | N37: I've Tried Everything But Therapy (Part 1) | O37: Today's Top Hits | P37: https://api.spotify.com/v1/audio-analysis/17phhZDn6oGtzMe56NuWvj | Q37: 17phhZDn6oGtzMe56NuWvj | R37: Lose Control | S37: 45184 | T37: 1.9e-05 | U37: 7nacKlk586eLRBSIsrk9DB | V37: 1 | W37: 9 | X37: 210689 | Y37: 0.199 | Z37: 17phhZDn6oGtzMe56NuWvj | AA37: mainstream | AB37: audio_features | AC37: 37i9dQZF1DXcBWIGoYBM5M
A38: 0.668 | B38: 90969 | C38: 0.646 | D38: pop | E38: -5203 | F38: 0.212 | G38: 0.64 | H38: Mark Ambor | I38: 4 | J38: 0.0282 | K38: 82 | L38: https://api.spotify.com/v1/tracks/5uQ7de4EWjb3rkcFxyEOpu | M38: spotify:track:5uQ7de4EWjb3rkcFxyEOpu | N38: Belong Together | O38: Today's Top Hits | P38: https://api.spotify.com/v1/audio-analysis/5uQ7de4EWjb3rkcFxyEOpu | Q38: 5uQ7de4EWjb3rkcFxyEOpu | R38: Belong Together | S38: 45338 | T38: 0 | U38: 3PlCMwyq6nuQYtoYproV1o | V38: 1 | W38: 2 | X38: 148318 | Y38: 0.491 | Z38: 5uQ7de4EWjb3rkcFxyEOpu | AA38: mainstream | AB38: audio_features | AC38: 37i9dQZF1DXcBWIGoYBM5M
A39: 0.668 | B39: 128027 | C39: 0.924 | D39: pop | E39: -6795 | F39: 0.0678 | G39: 0.787 | H39: KAROL G | I39: 4 | J39: 0.0469 | K39: 93 | L39: https://api.spotify.com/v1/tracks/6WatFBLVB0x077xWeoVc2k | M39: spotify:track:6WatFBLVB0x077xWeoVc2k | N39: Si Antes Te Hubiera Conocido | O39: Today's Top Hits | P39: https://api.spotify.com/v1/audio-analysis/6WatFBLVB0x077xWeoVc2k | Q39: 6WatFBLVB0x077xWeoVc2k | R39: Si Antes Te Hubiera Conocido | S39: 45464 | T39: 0.000594 | U39: 5ylbxH7EqpsmHZCRuiYewS | V39: 1 | W39: 11 | X39: 195824 | Y39: 0.446 | Z39: 6WatFBLVB0x077xWeoVc2k | AA39: mainstream | AB39: audio_features | AC39: 37i9dQZF1DXcBWIGoYBM5M
A40: 0.454 | B40: 159982 | C40: 0.689 | D40: pop | E40: -7643 | F40: 0.0707 | G40: 0.912 | H40: Djo | I40: 4 | J40: 0.0584 | K40: 89 | L40: https://api.spotify.com/v1/tracks/3qhlB30KknSejmIvZZLjOD | M40: spotify:track:3qhlB30KknSejmIvZZLjOD | N40: DECIDE | O40: Today's Top Hits | P40: https://api.spotify.com/v1/audio-analysis/3qhlB30KknSejmIvZZLjOD | Q40: 3qhlB30KknSejmIvZZLjOD | R40: End of Beginning | S40: 44820 | T40: 0.00259 | U40: 4JDXBZdRPId4devseaAOKH | V40: 1 | W40: 2 | X40: 159246 | Y40: 0.0351 | Z40: 3qhlB30KknSejmIvZZLjOD | AA40: mainstream | AB40: audio_features | AC40: 37i9dQZF1DXcBWIGoYBM5M
A41: 0.386 | B41: 192004 | C41: 0.504 | D41: pop | E41: -10976 | F41: 0.0961 | G41: 0.281 | H41: Taylor Swift, Post Malone | I41: 4 | J41: 0.0308 | K41: 84 | L41: https://api.spotify.com/v1/tracks/2OzhQlSqBEmt7hmkYxfT6m | M41: spotify:track:2OzhQlSqBEmt7hmkYxfT6m | N41: THE TORTURED POETS DEPARTMENT | O41: Today's Top Hits | P41: https://api.spotify.com/v1/audio-analysis/2OzhQlSqBEmt7hmkYxfT6m | Q41: 2OzhQlSqBEmt7hmkYxfT6m | R41: Fortnight (feat. Post Malone) | S41: 45400 | T41: 1.53e-05 | U41: 1Mo4aZ8pdj6L1jx8zSwJnt | V41: 1 | W41: 11 | X41: 228965 | Y41: 0.502 | Z41: 2OzhQlSqBEmt7hmkYxfT6m | AA41: mainstream | AB41: audio_features | AC41: 37i9dQZF1DXcBWIGoYBM5M
A42: 0.681 | B42: 155079 | C42: 0.56 | D42: pop | E42: -6304 | F42: 0.106 | G42: 0.388 | H42: Omar Courtz, De La Rose | I42: 4 | J42: 0.244 | K42: 89 | L42: https://api.spotify.com/v1/tracks/0Sr7ssScx54yxdM2ols7nW | M42: spotify:track:0Sr7ssScx54yxdM2ols7nW | N42: PRIMERA MUSA | O42: Today's Top Hits | P42: https://api.spotify.com/v1/audio-analysis/0Sr7ssScx54yxdM2ols7nW | Q42: 0Sr7ssScx54yxdM2ols7nW | R42: Q U E V A S H A C E R H O Y ? | S42: 45555 | T42: 0 | U42: 3C5uwdRE5QRoXSGPPxpDd4 | V42: 0 | W42: 6 | X42: 223320 | Y42: 0.103 | Z42: 0Sr7ssScx54yxdM2ols7nW | AA42: mainstream | AB42: audio_features | AC42: 37i9dQZF1DXcBWIGoYBM5M
A43: 0.472 | B43: 101061 | C43: 0.898 | D43: pop | E43: -7001 | F43: 0.141 | G43: 0.214 | H43: Kendrick Lamar | I43: 4 | J43: 0.0776 | K43: 88 | L43: https://api.spotify.com/v1/tracks/6AI3ezQ4o3HUoP6Dhudph3 | M43: spotify:track:6AI3ezQ4o3HUoP6Dhudph3 | N43: Not Like Us | O43: Today's Top Hits | P43: https://api.spotify.com/v1/audio-analysis/6AI3ezQ4o3HUoP6Dhudph3 | Q43: 6AI3ezQ4o3HUoP6Dhudph3 | R43: Not Like Us | S43: 45416 | T43: 0 | U43: 5JjnoGJyOxfSZUZtk2rRwZ | V43: 1 | W43: 1 | X43: 274192 | Y43: 0.0107 | Z43: 6AI3ezQ4o3HUoP6Dhudph3 | AA43: mainstream | AB43: audio_features | AC43: 37i9dQZF1DXcBWIGoYBM5M
A44: 0.711 | B44: 146921 | C44: 0.487 | D44: pop | E44: -4.22 | F44: 0.152 | G44: 0.317 | H44: Jin | I44: 4 | J44: 0.0322 | K44: 85 | L44: https://api.spotify.com/v1/tracks/4p7DTkyrKqT98xlIwYYfXz | M44: spotify:track:4p7DTkyrKqT98xlIwYYfXz | N44: Happy | O44: Today's Top Hits | P44: https://api.spotify.com/v1/audio-analysis/4p7DTkyrKqT98xlIwYYfXz | Q44: 4p7DTkyrKqT98xlIwYYfXz | R44: Running Wild | S44: 45611 | T44: 0 | U44: 0fKlaQuBMQYFo5aIFoGIXt | V44: 1 | W44: 8 | X44: 151647 | Y44: 0.000175 | Z44: 4p7DTkyrKqT98xlIwYYfXz | AA44: mainstream | AB44: audio_features | AC44: 37i9dQZF1DXcBWIGoYBM5M
A45: 0.712 | B45: 91.98 | C45: 0.848 | D45: pop | E45: -3574 | F45: 0.106 | G45: 0.692 | H45: KAROL G, Feid, DFZM, Ovy On The Drums, J Balvin, Maluma, Ryan Castro, Blessd | I45: 4 | J45: 0.0981 | K45: 84 | L45: https://api.spotify.com/v1/tracks/3mg9jYNC1NihbthlglzrWP | M45: spotify:track:3mg9jYNC1NihbthlglzrWP | N45: 57 | O45: Today's Top Hits | P45: https://api.spotify.com/v1/audio-analysis/3mg9jYNC1NihbthlglzrWP | Q45: 3mg9jYNC1NihbthlglzrWP | R45: 57 | S45: 45604 | T45: 0 | U45: 5TT8KluomuelzsNF7T1U37 | V45: 0 | W45: 1 | X45: 298131 | Y45: 0.221 | Z45: 3mg9jYNC1NihbthlglzrWP | AA45: mainstream | AB45: audio_features | AC45: 37i9dQZF1DXcBWIGoYBM5M
A46: 0.645 | B46: 114933 | C46: 0.882 | D46: pop | E46: -7233 | F46: 0.057 | G46: 0.788 | H46: Ndotz | I46: 4 | J46: 0.0601 | K46: 87 | L46: https://api.spotify.com/v1/tracks/0io16MKpbeDIdYzmGpQaES | M46: spotify:track:0io16MKpbeDIdYzmGpQaES | N46: Embrace It | O46: Today's Top Hits | P46: https://api.spotify.com/v1/audio-analysis/0io16MKpbeDIdYzmGpQaES | Q46: 0io16MKpbeDIdYzmGpQaES | R46: Embrace It | S46: 45527 | T46: 4.13e-05 | U46: 0mV9Pfr1GfoZLkp1EAau9P | V46: 1 | W46: 1 | X46: 104419 | Y46: 0.475 | Z46: 0io16MKpbeDIdYzmGpQaES | AA46: mainstream | AB46: audio_features | AC46: 37i9dQZF1DXcBWIGoYBM5M
A47: 0.872 | B47: 184115 | C47: 0.466 | D47: pop | E47: -3344 | F47: 0.121 | G47: 0.806 | H47: Linkin Park | I47: 4 | J47: 0.0336 | K47: 89 | L47: https://api.spotify.com/v1/tracks/2PnlsTsOTLE5jnBnNe2K0A | M47: spotify:track:2PnlsTsOTLE5jnBnNe2K0A | N47: The Emptiness Machine | O47: Today's Top Hits | P47: https://api.spotify.com/v1/audio-analysis/2PnlsTsOTLE5jnBnNe2K0A | Q47: 2PnlsTsOTLE5jnBnNe2K0A | R47: The Emptiness Machine | S47: 45540 | T47: 0 | U47: 6W0Gabv5f3ugnckc6YgfJQ | V47: 1 | W47: 7 | X47: 190428 | Y47: 0.0156 | Z47: 2PnlsTsOTLE5jnBnNe2K0A | AA47: mainstream | AB47: audio_features | AC47: 37i9dQZF1DXcBWIGoYBM5M
A48: 0.756 | B48: 116034 | C48: 0.66 | D48: pop | E48: -3743 | F48: 0.193 | G48: 0.838 | H48: Jimin | I48: 4 | J48: 0.032 | K48: 92 | L48: https://api.spotify.com/v1/tracks/7tI8dRuH2Yc6RuoTjxo4dU | M48: spotify:track:7tI8dRuH2Yc6RuoTjxo4dU | N48: MUSE | O48: Today's Top Hits | P48: https://api.spotify.com/v1/audio-analysis/7tI8dRuH2Yc6RuoTjxo4dU | Q48: 7tI8dRuH2Yc6RuoTjxo4dU | R48: Who | S48: 45492 | T48: 0 | U48: 15XcLhiVMlSOipUddTNDnr | V48: 0 | W48: 0 | X48: 170888 | Y48: 0.00289 | Z48: 7tI8dRuH2Yc6RuoTjxo4dU | AA48: mainstream | AB48: audio_features | AC48: 37i9dQZF1DXcBWIGoYBM5M
A49: 0.508 | B49: 147125 | C49: 0.579 | D49: rock | E49: -9484 | F49: 0.0575 | G49: 0.609 | H49: Eagles | I49: 4 | J49: 0.027 | K49: 81 | L49: https://api.spotify.com/v1/tracks/40riOy7x9W7GXjyGp4pjAv | M49: spotify:track:40riOy7x9W7GXjyGp4pjAv | N49: Hotel California (2013 Remaster) | O49: Rock Classics | P49: https://api.spotify.com/v1/audio-analysis/40riOy7x9W7GXjyGp4pjAv | Q49: 40riOy7x9W7GXjyGp4pjAv | R49: Hotel California - 2013 Remaster | S49: 28102 | T49: 0.000494 | U49: 2widuo17g5CEC66IbzveRu | V49: 1 | W49: 2 | X49: 391376 | Y49: 0.00574 | Z49: 40riOy7x9W7GXjyGp4pjAv | AA49: classic | AB49: audio_features | AC49: 37i9dQZF1DWXRqgorJj26U
A50: 0.89 | B50: 133.52 | C50: 0.502 | D50: rock | E50: -5175 | F50: 0.217 | G50: 0.259 | H50: AC/DC | I50: 4 | J50: 0.0364 | K50: 83 | L50: https://api.spotify.com/v1/tracks/57bgtoPSgt236HzfBOd8kj | M50: spotify:track:57bgtoPSgt236HzfBOd8kj | N50: The Razors Edge | O50: Rock Classics | P50: https://api.spotify.com/v1/audio-analysis/57bgtoPSgt236HzfBOd8kj | Q50: 57bgtoPSgt236HzfBOd8kj | R50: Thunderstruck | S50: 33140 | T50: 0.0117 | U50: 4vu7F6h90Br1ZtYYaqfITy | V50: 1 | W50: 4 | X50: 292880 | Y50: 0.000147 | Z50: 57bgtoPSgt236HzfBOd8kj | AA50: classic | AB50: audio_features | AC50: 37i9dQZF1DWXRqgorJj26U
A51: 0.446 | B51: 123596 | C51: 0.743 | D51: rock | E51: -7807 | F51: 0.337 | G51: 0.278 | H51: The White Stripes | I51: 4 | J51: 0.0683 | K51: 82 | L51: https://api.spotify.com/v1/tracks/3dPQuX8Gs42Y7b454ybpMR | M51: spotify:track:3dPQuX8Gs42Y7b454ybpMR | N51: Elephant | O51: Rock Classics | P51: https://api.spotify.com/v1/audio-analysis/3dPQuX8Gs42Y7b454ybpMR | Q51: 3dPQuX8Gs42Y7b454ybpMR | R51: Seven Nation Army | S51: 37712 | T51: 0.118 | U51: 6D9urpsOWWKtYvF6PaorGE | V51: 0 | W51: 4 | X51: 232107 | Y51: 0.0039 | Z51: 3dPQuX8Gs42Y7b454ybpMR | AA51: classic | AB51: audio_features | AC51: 37i9dQZF1DWXRqgorJj26U
A52: 0.43 | B52: 91844 | C52: 0.515 | D52: rock | E52: -9935 | F52: 0.129 | G52: 0.104 | H52: Radiohead | I52: 4 | J52: 0.0372 | K52: 86 | L52: https://api.spotify.com/v1/tracks/70LcF31zb1H0PyJoS1Sx1r | M52: spotify:track:70LcF31zb1H0PyJoS1Sx1r | N52: Pablo Honey | O52: Rock Classics | P52: https://api.spotify.com/v1/audio-analysis/70LcF31zb1H0PyJoS1Sx1r | Q52: 70LcF31zb1H0PyJoS1Sx1r | R52: Creep | S52: 34022 | T52: 0.000133 | U52: 3gBVdu4a1MMJVMy6vwPEb8 | V52: 1 | W52: 7 | X52: 238640 | Y52: 0.0097 | Z52: 70LcF31zb1H0PyJoS1Sx1r | AA52: classic | AB52: audio_features | AC52: 37i9dQZF1DWXRqgorJj26U
A53: 0.824 | B53: 120125 | C53: 0.5 | D53: rock | E53: -5846 | F53: 0.0916 | G53: 0.539 | H53: Nirvana | I53: 4 | J53: 0.0388 | K53: 76 | L53: https://api.spotify.com/v1/tracks/4P5KoWXOxwuobLmHXLMobV | M53: spotify:track:4P5KoWXOxwuobLmHXLMobV | N53: Nevermind (Remastered) | O53: Rock Classics | P53: https://api.spotify.com/v1/audio-analysis/4P5KoWXOxwuobLmHXLMobV | Q53: 4P5KoWXOxwuobLmHXLMobV | R53: Come As You Are | S53: 33507 | T53: 0.00161 | U53: 2guirTSEqLizK7j9i1MTTZ | V53: 0 | W53: 4 | X53: 218920 | Y53: 0.00016 | Z53: 4P5KoWXOxwuobLmHXLMobV | AA53: classic | AB53: audio_features | AC53: 37i9dQZF1DWXRqgorJj26U
A54: 0.767 | B54: 96483 | C54: 0.592 | D54: rock | E54: -2788 | F54: 0.127 | G54: 0.328 | H54: Red Hot Chili Peppers | I54: 4 | J54: 0.027 | K54: 81 | L54: https://api.spotify.com/v1/tracks/48UPSzbZjgc449aqz8bxox | M54: spotify:track:48UPSzbZjgc449aqz8bxox | N54: Californication (Deluxe Edition) | O54: Rock Classics | P54: https://api.spotify.com/v1/audio-analysis/48UPSzbZjgc449aqz8bxox | Q54: 48UPSzbZjgc449aqz8bxox | R54: Californication | S54: 36319 | T54: 0.00165 | U54: 2Y9IRtehByVkegoD7TcLfi | V54: 0 | W54: 9 | X54: 329733 | Y54: 0.0021 | Z54: 48UPSzbZjgc449aqz8bxox | AA54: classic | AB54: audio_features | AC54: 37i9dQZF1DWXRqgorJj26U
A55: 0.952 | B55: 125304 | C55: 0.445 | D55: rock | E55: -5321 | F55: 0.112 | G55: 0.624 | H55: Guns N' Roses | I55: 4 | J55: 0.0522 | K55: 84 | L55: https://api.spotify.com/v1/tracks/7snQQk1zcKl8gZ92AnueZW | M55: spotify:track:7snQQk1zcKl8gZ92AnueZW | N55: Appetite For Destruction | O55: Rock Classics | P55: https://api.spotify.com/v1/audio-analysis/7snQQk1zcKl8gZ92AnueZW | Q55: 7snQQk1zcKl8gZ92AnueZW | R55: Sweet Child O' Mine | S55: 31979 | T55: 0.0843 | U55: 28yHV3Gdg30AiB8h8em1eW | V55: 1 | W55: 6 | X55: 356067 | Y55: 0.09 | Z55: 7snQQk1zcKl8gZ92AnueZW | AA55: classic | AB55: audio_features | AC55: 37i9dQZF1DWXRqgorJj26U
A56: 0.795 | B56: 158691 | C56: 0.464 | D56: rock | E56: -9267 | F56: 0.399 | G56: 0.612 | H56: The Rolling Stones | I56: 4 | J56: 0.0926 | K56: 81 | L56: https://api.spotify.com/v1/tracks/63T7DJ1AFDD6Bn8VzG6JE8 | M56: spotify:track:63T7DJ1AFDD6Bn8VzG6JE8 | N56: Aftermath | O56: Rock Classics | P56: https://api.spotify.com/v1/audio-analysis/63T7DJ1AFDD6Bn8VzG6JE8 | Q56: 63T7DJ1AFDD6Bn8VzG6JE8 | R56: Paint It, Black | S56: 24212 | T56: 0.00244 | U56: 72qrnM4yUNMDDlWiqKc8iY | V56: 1 | W56: 1 | X56: 202267 | Y56: 0.0493 | Z56: 63T7DJ1AFDD6Bn8VzG6JE8 | AA56: classic | AB56: audio_features | AC56: 37i9dQZF1DWXRqgorJj26U
A57: 0.492 | B57: 120151 | C57: 0.828 | D57: rock | E57: -9744 | F57: 0.128 | G57: 0.789 | H57: Fleetwood Mac | I57: 4 | J57: 0.0276 | K57: 84 | L57: https://api.spotify.com/v1/tracks/0ofHAoxe9vBkTCp2UQIavz | M57: spotify:track:0ofHAoxe9vBkTCp2UQIavz | N57: Rumours (Super Deluxe) | O57: Rock Classics | P57: https://api.spotify.com/v1/audio-analysis/0ofHAoxe9vBkTCp2UQIavz | Q57: 0ofHAoxe9vBkTCp2UQIavz | R57: Dreams - 2004 Remaster | S57: 28160 | T57: 0.00428 | U57: 0BwWUstDMUbgq2NYONRqlu | V57: 1 | W57: 0 | X57: 257800 | Y57: 0.0644 | Z57: 0ofHAoxe9vBkTCp2UQIavz | AA57: classic | AB57: audio_features | AC57: 37i9dQZF1DWXRqgorJj26U
A58: 0.881 | B58: 158066 | C58: 0.413 | D58: rock | E58: -5541 | F58: 0.0805 | G58: 0.364 | H58: Foo Fighters | I58: 4 | J58: 0.0367 | K58: 81 | L58: https://api.spotify.com/v1/tracks/5UWwZ5lm5PKu6eKsHAGxOk | M58: spotify:track:5UWwZ5lm5PKu6eKsHAGxOk | N58: The Colour And The Shape | O58: Rock Classics | P58: https://api.spotify.com/v1/audio-analysis/5UWwZ5lm5PKu6eKsHAGxOk | Q58: 5UWwZ5lm5PKu6eKsHAGxOk | R58: Everlong | S58: 35570 | T58: 0.000308 | U58: 30ly6F6Xl0TKmyBCU50Khv | V58: 0 | W58: 11 | X58: 250547 | Y58: 5.99e-05 | Z58: 5UWwZ5lm5PKu6eKsHAGxOk | AA58: classic | AB58: audio_features | AC58: 37i9dQZF1DWXRqgorJj26U
A59: 0.716 | B59: 94379 | C59: 0.535 | D59: rock | E59: -5025 | F59: 0.659 | G59: 0.901 | H59: Joan Jett & the Blackhearts | I59: 4 | J59: 0.0431 | K59: 77 | L59: https://api.spotify.com/v1/tracks/2Cdvbe2G4hZsnhNMKyGrie | M59: spotify:track:2Cdvbe2G4hZsnhNMKyGrie | N59: I Love Rock 'N' Roll (Expanded Edition) | O59: Rock Classics | P59: https://api.spotify.com/v1/audio-analysis/2Cdvbe2G4hZsnhNMKyGrie | Q59: 2Cdvbe2G4hZsnhNMKyGrie | R59: I Love Rock 'N Roll | S59: 29908 | T59: 0 | U59: 555qwe1qUgLdee80TZ2CQt | V59: 1 | W59: 4 | X59: 175173 | Y59: 0.326 | Z59: 2Cdvbe2G4hZsnhNMKyGrie | AA59: classic | AB59: audio_features | AC59: 37i9dQZF1DWXRqgorJj26U
A60: 0.322 | B60: 93503 | C60: 0.475 | D60: rock | E60: -10687 | F60: 0.11 | G60: 0.387 | H60: Kansas | I60: 4 | J60: 0.0283 | K60: 79 | L60: https://api.spotify.com/v1/tracks/6zeE5tKyr8Nu882DQhhSQI | M60: spotify:track:6zeE5tKyr8Nu882DQhhSQI | N60: Point Of Know Return (Expanded Edition) | O60: Rock Classics | P60: https://api.spotify.com/v1/audio-analysis/6zeE5tKyr8Nu882DQhhSQI | Q60: 6zeE5tKyr8Nu882DQhhSQI | R60: Dust in the Wind | S60: 1977 | T60: 0.00056 | U60: 6oU298pdPTCQnMx1PYwyUA | V60: 1 | W60: 7 | X60: 206267 | Y60: 0.367 | Z60: 6zeE5tKyr8Nu882DQhhSQI | AA60: classic | AB60: audio_features | AC60: 37i9dQZF1DWXRqgorJj26U
A61: 0.394 | B61: 104114 | C61: 0.693 | D61: rock | E61: -15882 | F61: 0.247 | G61: 0.721 | H61: Pink Floyd | I61: 4 | J61: 0.0428 | K61: 74 | L61: https://api.spotify.com/v1/tracks/4gMgiXfqyzZLMhsksGmbQV | M61: spotify:track:4gMgiXfqyzZLMhsksGmbQV | N61: The Wall | O61: Rock Classics | P61: https://api.spotify.com/v1/audio-analysis/4gMgiXfqyzZLMhsksGmbQV | Q61: 4gMgiXfqyzZLMhsksGmbQV | R61: Another Brick in the Wall, Pt. 2 | S61: 29189 | T61: 0.000694 | U61: 5Dbax7G8SWrP9xyzkOvy2F | V61: 1 | W61: 0 | X61: 238747 | Y61: 0.0782 | Z61: 4gMgiXfqyzZLMhsksGmbQV | AA61: classic | AB61: audio_features | AC61: 37i9dQZF1DWXRqgorJj26U
A62: 0.899 | B62: 152445 | C62: 0.475 | D62: rock | E62: -4321 | F62: 0.14 | G62: 0.603 | H62: Bon Jovi | I62: 4 | J62: 0.0637 | K62: 72 | L62: https://api.spotify.com/v1/tracks/0X1sqQ652p1sceKM2nJlIJ | M62: spotify:track:0X1sqQ652p1sceKM2nJlIJ | N62: Bon Jovi | O62: Rock Classics | P62: https://api.spotify.com/v1/audio-analysis/0X1sqQ652p1sceKM2nJlIJ | Q62: 0X1sqQ652p1sceKM2nJlIJ | R62: Runaway | S62: 30704 | T62: 1.91e-05 | U62: 1UUOBzIHw0noiRGRpbt3sz | V62: 0 | W62: 9 | X62: 230667 | Y62: 0.00375 | Z62: 0X1sqQ652p1sceKM2nJlIJ | AA62: classic | AB62: audio_features | AC62: 37i9dQZF1DWXRqgorJj26U
A63: 0.943 | B63: 85064 | C63: 0.442 | D63: rock | E63: -3205 | F63: 0.091 | G63: 0.781 | H63: Green Day | I63: 4 | J63: 0.0602 | K63: 80 | L63: https://api.spotify.com/v1/tracks/6L89mwZXSOwYl76YXfX13s | M63: spotify:track:6L89mwZXSOwYl76YXfX13s | N63: Dookie | O63: Rock Classics | P63: https://api.spotify.com/v1/audio-analysis/6L89mwZXSOwYl76YXfX13s | Q63: 6L89mwZXSOwYl76YXfX13s | R63: Basket Case | S63: 34366 | T63: 8.71e-06 | U63: 4uG8q3GPuWHQlRbswMIRS6 | V63: 1 | W63: 3 | X63: 181533 | Y63: 0.00293 | Z63: 6L89mwZXSOwYl76YXfX13s | AA63: classic | AB63: audio_features | AC63: 37i9dQZF1DWXRqgorJj26U
A64: 0.345 | B64: 84581 | C64: 0.559 | D64: rock | E64: -13496 | F64: 0.141 | G64: 0.458 | H64: Red Hot Chili Peppers | I64: 4 | J64: 0.0459 | K64: 82 | L64: https://api.spotify.com/v1/tracks/3d9DChrdc6BOeFsbrZ3Is0 | M64: spotify:track:3d9DChrdc6BOeFsbrZ3Is0 | N64: Blood Sugar Sex Magik (Deluxe Edition) | O64: Rock Classics | P64: https://api.spotify.com/v1/audio-analysis/3d9DChrdc6BOeFsbrZ3Is0 | Q64: 3d9DChrdc6BOeFsbrZ3Is0 | R64: Under the Bridge | S64: 33505 | T64: 0.000105 | U64: 30Perjew8HyGkdSmqguYyg | V64: 1 | W64: 4 | X64: 264307 | Y64: 0.0576 | Z64: 3d9DChrdc6BOeFsbrZ3Is0 | AA64: classic | AB64: audio_features | AC64: 37i9dQZF1DWXRqgorJj26U
A65: 0.814 | B65: 147193 | C65: 0.673 | D65: rock | E65: -5411 | F65: 0.343 | G65: 0.728 | H65: Billy Idol | I65: 4 | J65: 0.0367 | K65: 70 | L65: https://api.spotify.com/v1/tracks/1gzIbdFnGJ226LTl0Cn2SX | M65: spotify:track:1gzIbdFnGJ226LTl0Cn2SX | N65: Billy Idol | O65: Rock Classics | P65: https://api.spotify.com/v1/audio-analysis/1gzIbdFnGJ226LTl0Cn2SX | Q65: 1gzIbdFnGJ226LTl0Cn2SX | R65: White Wedding - Pt. 1 | S65: 29952 | T65: 0.00293 | U65: 5ebh0MxkqELmk50xHj2b4k | V65: 1 | W65: 9 | X65: 252200 | Y65: 0.0134 | Z65: 1gzIbdFnGJ226LTl0Cn2SX | AA65: classic | AB65: audio_features | AC65: 37i9dQZF1DWXRqgorJj26U
A66: 0.767 | B66: 127361 | C66: 0.532 | D66: rock | E66: -5509 | F66: 0.39 | G66: 0.755 | H66: AC/DC | I66: 4 | J66: 0.0574 | K66: 81 | L66: https://api.spotify.com/v1/tracks/2SiXAy7TuUkycRVbbWDEpo | M66: spotify:track:2SiXAy7TuUkycRVbbWDEpo | N66: Back In Black | O66: Rock Classics | P66: https://api.spotify.com/v1/audio-analysis/2SiXAy7TuUkycRVbbWDEpo | Q66: 2SiXAy7TuUkycRVbbWDEpo | R66: You Shook Me All Night Long | S66: 29427 | T66: 0.000513 | U66: 6mUdeDZCsExyJLMdAfDuwh | V66: 1 | W66: 7 | X66: 210173 | Y66: 0.00287 | Z66: 2SiXAy7TuUkycRVbbWDEpo | AA66: classic | AB66: audio_features | AC66: 37i9dQZF1DWXRqgorJj26U
A67: 0.863 | B67: 136302 | C67: 0.723 | D67: rock | E67: -7.89 | F67: 0.128 | G67: 0.931 | H67: The Rolling Stones | I67: 4 | J67: 0.0338 | K67: 76 | L67: https://api.spotify.com/v1/tracks/2PzU4IB8Dr6mxV3lHuaG34 | M67: spotify:track:2PzU4IB8Dr6mxV3lHuaG34 | N67: Out Of Our Heads | O67: Rock Classics | P67: https://api.spotify.com/v1/audio-analysis/2PzU4IB8Dr6mxV3lHuaG34 | Q67: 2PzU4IB8Dr6mxV3lHuaG34 | R67: (I Can't Get No) Satisfaction - Mono Version | S67: 23953 | T67: 0.0317 | U67: 2Q5MwpTmtjscaS34mJFXQQ | V67: 1 | W67: 2 | X67: 222813 | Y67: 0.0383 | Z67: 2PzU4IB8Dr6mxV3lHuaG34 | AA67: classic | AB67: audio_features | AC67: 37i9dQZF1DWXRqgorJj26U
A68: 0.449 | B68: 100456 | C68: 0.486 | D68: rock | E68: -10298 | F68: 0.54 | G68: 0.549 | H68: David Bowie | I68: 4 | J68: 0.0267 | K68: 76 | L68: https://api.spotify.com/v1/tracks/0pQskrTITgmCMyr85tb9qq | M68: spotify:track:0pQskrTITgmCMyr85tb9qq | N68: The Rise and Fall of Ziggy Stardust and the Spiders from Mars (2012 Remaster) | O68: Rock Classics | P68: https://api.spotify.com/v1/audio-analysis/0pQskrTITgmCMyr85tb9qq | Q68: 0pQskrTITgmCMyr85tb9qq | R68: Starman - 2012 Remaster | S68: 26456 | T68: 2.23e-06 | U68: 48D1hRORqJq52qsnUYZX56 | V68: 1 | W68: 5 | X68: 254293 | Y68: 0.166 | Z68: 0pQskrTITgmCMyr85tb9qq | AA68: classic | AB68: audio_features | AC68: 37i9dQZF1DWXRqgorJj26U
A69: 0.902 | B69: 89.74 | C69: 0.412 | D69: rock | E69: -11.6 | F69: 0.405 | G69: 0.422 | H69: Led Zeppelin | I69: 4 | J69: 0.405 | K69: 72 | L69: https://api.spotify.com/v1/tracks/0hCB0YR03f6AmQaHbwWDe8 | M69: spotify:track:0hCB0YR03f6AmQaHbwWDe8 | N69: Led Zeppelin II (1994 Remaster) | O69: Rock Classics | P69: https://api.spotify.com/v1/audio-analysis/0hCB0YR03f6AmQaHbwWDe8 | Q69: 0hCB0YR03f6AmQaHbwWDe8 | R69: Whole Lotta Love - 1990 Remaster | S69: 25498 | T69: 0.131 | U69: 70lQYZtypdCALtFVlQAcvx | V69: 1 | W69: 9 | X69: 333893 | Y69: 0.0484 | Z69: 0hCB0YR03f6AmQaHbwWDe8 | AA69: classic | AB69: audio_features | AC69: 37i9dQZF1DWXRqgorJj26U
A70: 0.722 | B70: 103886 | C70: 0.55 | D70: rock | E70: -11729 | F70: 0.11 | G70: 0.716 | H70: The Doors | I70: 4 | J70: 0.0283 | K70: 70 | L70: https://api.spotify.com/v1/tracks/14XWXWv5FoCbFzLksawpEe | M70: spotify:track:14XWXWv5FoCbFzLksawpEe | N70: L.A. Woman | O70: Rock Classics | P70: https://api.spotify.com/v1/audio-analysis/14XWXWv5FoCbFzLksawpEe | Q70: 14XWXWv5FoCbFzLksawpEe | R70: Riders on the Storm | S70: 26042 | T70: 0.0129 | U70: 7IKUTIc9UWuVngyGPtqNHS | V70: 0 | W70: 11 | X70: 434720 | Y70: 0.25 | Z70: 14XWXWv5FoCbFzLksawpEe | AA70: classic | AB70: audio_features | AC70: 37i9dQZF1DWXRqgorJj26U
A71: 0.944 | B71: 105338 | C71: 0.394 | D71: rock | E71: -6506 | F71: 0.298 | G71: 0.265 | H71: Pearl Jam | I71: 4 | J71: 0.0761 | K71: 77 | L71: https://api.spotify.com/v1/tracks/6QewNVIDKdSl8Y3ycuHIei | M71: spotify:track:6QewNVIDKdSl8Y3ycuHIei | N71: Ten | O71: Rock Classics | P71: https://api.spotify.com/v1/audio-analysis/6QewNVIDKdSl8Y3ycuHIei | Q71: 6QewNVIDKdSl8Y3ycuHIei | R71: Even Flow | S71: 33477 | T71: 4.54e-06 | U71: 5B4PYA7wNN4WdEXdIJu58a | V71: 0 | W71: 10 | X71: 292581 | Y71: 0.00178 | Z71: 6QewNVIDKdSl8Y3ycuHIei | AA71: classic | AB71: audio_features | AC71: 37i9dQZF1DWXRqgorJj26U
A72: 0.952 | B72: 122093 | C72: 0.398 | D72: rock | E72: -6042 | F72: 0.1 | G72: 0.584 | H72: Bruce Springsteen | I72: 4 | J72: 0.061 | K72: 72 | L72: https://api.spotify.com/v1/tracks/0dOg1ySSI7NkpAe89Zo0b9 | M72: spotify:track:0dOg1ySSI7NkpAe89Zo0b9 | N72: Born In The U.S.A. | O72: Rock Classics | P72: https://api.spotify.com/v1/audio-analysis/0dOg1ySSI7NkpAe89Zo0b9 | Q72: 0dOg1ySSI7NkpAe89Zo0b9 | R72: Born in the U.S.A. | S72: 30837 | T72: 7.75e-05 | U72: 0PMasrHdpaoIRuHuhHp72O | V72: 1 | W72: 4 | X72: 278680 | Y72: 0.000373 | Z72: 0dOg1ySSI7NkpAe89Zo0b9 | AA72: classic | AB72: audio_features | AC72: 37i9dQZF1DWXRqgorJj26U
A73: 0.917 | B73: 171176 | C73: 0.356 | D73: rock | E73: -6006 | F73: 0.406 | G73: 0.518 | H73: The Verve | I73: 4 | J73: 0.0479 | K73: 79 | L73: https://api.spotify.com/v1/tracks/57iDDD9N9tTWe75x6qhStw | M73: spotify:track:57iDDD9N9tTWe75x6qhStw | N73: Urban Hymns (Remastered 2016) | O73: Rock Classics | P73: https://api.spotify.com/v1/audio-analysis/57iDDD9N9tTWe75x6qhStw | Q73: 57iDDD9N9tTWe75x6qhStw | R73: Bitter Sweet Symphony - Remastered 2016 | S73: 35702 | T73: 0 | U73: 52AeC4gwbxDfFlLHgK1ByD | V73: 1 | W73: 9 | X73: 357267 | Y73: 0.0335 | Z73: 57iDDD9N9tTWe75x6qhStw | AA73: classic | AB73: audio_features | AC73: 37i9dQZF1DWXRqgorJj26U
A74: 0.589 | B74: 124634 | C74: 0.455 | D74: rock | E74: -8.64 | F74: 0.104 | G74: 0.254 | H74: Guns N' Roses | I74: 4 | J74: 0.0328 | K74: 75 | L74: https://api.spotify.com/v1/tracks/2N2yrmodOnVF10mKvItC9P | M74: spotify:track:2N2yrmodOnVF10mKvItC9P | N74: Use Your Illusion I | O74: Rock Classics | P74: https://api.spotify.com/v1/audio-analysis/2N2yrmodOnVF10mKvItC9P | Q74: 2N2yrmodOnVF10mKvItC9P | R74: Don't Cry (Original) | S74: 33498 | T74: 0.00358 | U74: 0CxPbTRARqKUYighiEY9Sz | V74: 1 | W74: 11 | X74: 283733 | Y74: 0.00184 | Z74: 2N2yrmodOnVF10mKvItC9P | AA74: classic | AB74: audio_features | AC74: 37i9dQZF1DWXRqgorJj26U
A75: 0.805 | B75: 113253 | C75: 0.438 | D75: rock | E75: -6237 | F75: 0.0842 | G75: 0.564 | H75: Jimi Hendrix | I75: 4 | J75: 0.0624 | K75: 72 | L75: https://api.spotify.com/v1/tracks/2aoo2jlRnM3A0NyLQqMN2f | M75: spotify:track:2aoo2jlRnM3A0NyLQqMN2f | N75: Electric Ladyland | O75: Rock Classics | P75: https://api.spotify.com/v1/audio-analysis/2aoo2jlRnM3A0NyLQqMN2f | Q75: 2aoo2jlRnM3A0NyLQqMN2f | R75: All Along the Watchtower | S75: 25136 | T75: 5.69e-05 | U75: 5z090LQztiqh13wYspQvKQ | V75: 1 | W75: 8 | X75: 240800 | Y75: 0.00255 | Z75: 2aoo2jlRnM3A0NyLQqMN2f | AA75: classic | AB75: audio_features | AC75: 37i9dQZF1DWXRqgorJj26U
A76: 0.239 | B76: 189507 | C76: 0.446 | D76: rock | E76: -13945 | F76: 0.0697 | G76: 0.298 | H76: Phil Collins | I76: 4 | J76: 0.0316 | K76: 76 | L76: https://api.spotify.com/v1/tracks/18AXbzPzBS8Y3AkgSxzJPb | M76: spotify:track:18AXbzPzBS8Y3AkgSxzJPb | N76: Face Value (Deluxe Editon) | O76: Rock Classics | P76: https://api.spotify.com/v1/audio-analysis/18AXbzPzBS8Y3AkgSxzJPb | Q76: 18AXbzPzBS8Y3AkgSxzJPb | R76: In The Air Tonight - 2015 Remastered | S76: 29587 | T76: 4.1e-06 | U76: 1cM3r0WQZWNkCpEbmFjLln | V76: 1 | W76: 0 | X76: 336453 | Y76: 0.551 | Z76: 18AXbzPzBS8Y3AkgSxzJPb | AA76: classic | AB76: audio_features | AC76: 37i9dQZF1DWXRqgorJj26U
A77: 0.521 | B77: 123118 | C77: 0.721 | D77: rock | E77: -8123 | F77: 0.127 | G77: 0.942 | H77: Talking Heads | I77: 4 | J77: 0.0613 | K77: 76 | L77: https://api.spotify.com/v1/tracks/1i6N76fftMZhijOzFQ5ZtL | M77: spotify:track:1i6N76fftMZhijOzFQ5ZtL | N77: Talking Heads '77 (Deluxe Version) | O77: Rock Classics | P77: https://api.spotify.com/v1/audio-analysis/1i6N76fftMZhijOzFQ5ZtL | Q77: 1i6N76fftMZhijOzFQ5ZtL | R77: Psycho Killer - 2005 Remaster | S77: 28384 | T77: 0.00545 | U77: 5eqcF7pWzHgWpGdEmHgeSN | V77: 1 | W77: 2 | X77: 261413 | Y77: 0.0708 | Z77: 1i6N76fftMZhijOzFQ5ZtL | AA77: classic | AB77: audio_features | AC77: 37i9dQZF1DWXRqgorJj26U
A78: 0.67 | B78: 129269 | C78: 0.619 | D78: rock | E78: -10322 | F78: 0.331 | G78: 0.777 | H78: Lenny Kravitz | I78: 4 | J78: 0.0353 | K78: 71 | L78: https://api.spotify.com/v1/tracks/45Ia1U4KtIjAPPU7Wv1Sea | M78: spotify:track:45Ia1U4KtIjAPPU7Wv1Sea | N78: Are You Gonna Go My Way | O78: Rock Classics | P78: https://api.spotify.com/v1/audio-analysis/45Ia1U4KtIjAPPU7Wv1Sea | Q78: 45Ia1U4KtIjAPPU7Wv1Sea | R78: Are You Gonna Go My Way | S78: 34037 | T78: 0.0109 | U78: 35LzZH7Fgog8lf1hfcdoMQ | V78: 0 | W78: 11 | X78: 211933 | Y78: 0.00165 | Z78: 45Ia1U4KtIjAPPU7Wv1Sea | AA78: classic | AB78: audio_features | AC78: 37i9dQZF1DWXRqgorJj26U
A79: 0.828 | B79: 105.25 | C79: 0.539 | D79: rock | E79: -9108 | F79: 0.154 | G79: 0.562 | H79: Metallica | I79: 4 | J79: 0.035 | K79: 70 | L79: https://api.spotify.com/v1/tracks/54bm2e3tk8cliUz3VSdCPZ | M79: spotify:track:54bm2e3tk8cliUz3VSdCPZ | N79: Master of Puppets (Remastered Deluxe Box Set) | O79: Rock Classics | P79: https://api.spotify.com/v1/audio-analysis/54bm2e3tk8cliUz3VSdCPZ | Q79: 54bm2e3tk8cliUz3VSdCPZ | R79: Master of Puppets (Remastered) | S79: 31474 | T79: 0.421 | U79: 7CGhx630DIjdJqaBDVKc5j | V79: 0 | W79: 4 | X79: 515387 | Y79: 0.00067 | Z79: 54bm2e3tk8cliUz3VSdCPZ | AA79: classic | AB79: audio_features | AC79: 37i9dQZF1DWXRqgorJj26U
A80: 0.487 | B80: 114965 | C80: 0.73 | D80: rock | E80: -10991 | F80: 0.0852 | G80: 0.731 | H80: Fleetwood Mac | I80: 4 | J80: 0.0303 | K80: 79 | L80: https://api.spotify.com/v1/tracks/254bXAqt3zP6P50BdQvEsq | M80: spotify:track:254bXAqt3zP6P50BdQvEsq | N80: Tango In the Night (Deluxe Edition) | O80: Rock Classics | P80: https://api.spotify.com/v1/audio-analysis/254bXAqt3zP6P50BdQvEsq | Q80: 254bXAqt3zP6P50BdQvEsq | R80: Everywhere - 2017 Remaster | S80: 31880 | T80: 0.01 | U80: 4AsXQ17Arq1cUVoa9dKJ3F | V80: 1 | W80: 4 | X80: 226653 | Y80: 0.258 | Z80: 254bXAqt3zP6P50BdQvEsq | AA80: classic | AB80: audio_features | AC80: 37i9dQZF1DWXRqgorJj26U
A81: 0.697 | B81: 116109 | C81: 0.741 | D81: rock | E81: -7028 | F81: 0.133 | G81: 0.774 | H81: Creedence Clearwater Revival | I81: 4 | J81: 0.0277 | K81: 84 | L81: https://api.spotify.com/v1/tracks/2LawezPeJhN4AWuSB0GtAU | M81: spotify:track:2LawezPeJhN4AWuSB0GtAU | N81: Pendulum (Expanded Edition) | O81: Rock Classics | P81: https://api.spotify.com/v1/audio-analysis/2LawezPeJhN4AWuSB0GtAU | Q81: 2LawezPeJhN4AWuSB0GtAU | R81: Have You Ever Seen The Rain | S81: 25909 | T81: 2.28e-05 | U81: 372cMadhAGlNuDnc8TssqF | V81: 1 | W81: 0 | X81: 160133 | Y81: 0.0664 | Z81: 2LawezPeJhN4AWuSB0GtAU | AA81: classic | AB81: audio_features | AC81: 37i9dQZF1DWXRqgorJj26U
A82: 0.579 | B82: 127215 | C82: 0.62 | D82: rock | E82: -9307 | F82: 0.0858 | G82: 0.691 | H82: The Cars | I82: 4 | J82: 0.0473 | K82: 69 | L82: https://api.spotify.com/v1/tracks/4alHo6RGd0D3OUbTPExTHN | M82: spotify:track:4alHo6RGd0D3OUbTPExTHN | N82: The Cars | O82: Rock Classics | P82: https://api.spotify.com/v1/audio-analysis/4alHo6RGd0D3OUbTPExTHN | Q82: 4alHo6RGd0D3OUbTPExTHN | R82: Just What I Needed | S82: 28647 | T82: 6.4e-05 | U82: 4tJPWT4r4FSKwy784Qs1Fq | V82: 1 | W82: 4 | X82: 225627 | Y82: 0.0152 | Z82: 4alHo6RGd0D3OUbTPExTHN | AA82: classic | AB82: audio_features | AC82: 37i9dQZF1DWXRqgorJj26U
A83: 0.912 | B83: 116761 | C83: 0.502 | D83: rock | E83: -4556 | F83: 0.106 | G83: 0.72 | H83: Nirvana | I83: 4 | J83: 0.0564 | K83: 76 | L83: https://api.spotify.com/v1/tracks/5ghIJDpPoe3CfHMGu71E6T | M83: spotify:track:5ghIJDpPoe3CfHMGu71E6T | N83: Nevermind (Remastered) | O83: Rock Classics | P83: https://api.spotify.com/v1/audio-analysis/5ghIJDpPoe3CfHMGu71E6T | Q83: 5ghIJDpPoe3CfHMGu71E6T | R83: Smells Like Teen Spirit | S83: 33507 | T83: 0.000173 | U83: 2guirTSEqLizK7j9i1MTTZ | V83: 1 | W83: 1 | X83: 301920 | Y83: 2.55e-05 | Z83: 5ghIJDpPoe3CfHMGu71E6T | AA83: classic | AB83: audio_features | AC83: 37i9dQZF1DWXRqgorJj26U
A84: 0.833 | B84: 88785 | C84: 0.466 | D84: rock | E84: -4215 | F84: 0.0327 | G84: 0.661 | H84: Rage Against The Machine | I84: 4 | J84: 0.304 | K84: 78 | L84: https://api.spotify.com/v1/tracks/59WN2psjkt1tyaxjspN8fp | M84: spotify:track:59WN2psjkt1tyaxjspN8fp | N84: Rage Against The Machine - XX (20th Anniversary Special Edition) | O84: Rock Classics | P84: https://api.spotify.com/v1/audio-analysis/59WN2psjkt1tyaxjspN8fp | Q84: 59WN2psjkt1tyaxjspN8fp | R84: Killing In The Name | S84: 1992 | T84: 0 | U84: 4Io5vWtmV1rFj4yirKb4y4 | V84: 1 | W84: 7 | X84: 313573 | Y84: 0.0266 | Z84: 59WN2psjkt1tyaxjspN8fp | AA84: classic | AB84: audio_features | AC84: 37i9dQZF1DWXRqgorJj26U
A85: 0.376 | B85: 164775 | C85: 0.53 | D85: rock | E85: -11913 | F85: 0.0926 | G85: 0.188 | H85: The Beatles | I85: 4 | J85: 0.04 | K85: 75 | L85: https://api.spotify.com/v1/tracks/2EqlS6tkEnglzr7tkKAAYD | M85: spotify:track:2EqlS6tkEnglzr7tkKAAYD | N85: Abbey Road (Remastered) | O85: Rock Classics | P85: https://api.spotify.com/v1/audio-analysis/2EqlS6tkEnglzr7tkKAAYD | Q85: 2EqlS6tkEnglzr7tkKAAYD | R85: Come Together - Remastered 2009 | S85: 25472 | T85: 0.247 | U85: 0ETFjACtuP2ADo6LFhL6HN | V85: 0 | W85: 9 | X85: 259947 | Y85: 0.0304 | Z85: 2EqlS6tkEnglzr7tkKAAYD | AA85: classic | AB85: audio_features | AC85: 37i9dQZF1DWXRqgorJj26U
A86: 0.786 | B86: 126755 | C86: 0.482 | D86: rock | E86: -5735 | F86: 0.446 | G86: 0.793 | H86: Kansas | I86: 4 | J86: 0.032 | K86: 73 | L86: https://api.spotify.com/v1/tracks/4DMKwE2E2iYDKY01C335Uw | M86: spotify:track:4DMKwE2E2iYDKY01C335Uw | N86: Leftoverture (Expanded Edition) | O86: Rock Classics | P86: https://api.spotify.com/v1/audio-analysis/4DMKwE2E2iYDKY01C335Uw | Q86: 4DMKwE2E2iYDKY01C335Uw | R86: Carry on Wayward Son | S86: 1976 | T86: 8.88e-05 | U86: 7MejfRSNnrpcLZIxkeZDqR | V86: 1 | W86: 7 | X86: 323000 | Y86: 0.00321 | Z86: 4DMKwE2E2iYDKY01C335Uw | AA86: classic | AB86: audio_features | AC86: 37i9dQZF1DWXRqgorJj26U
A87: 0.789 | B87: 129802 | C87: 0.674 | D87: rock | E87: -6903 | F87: 0.0753 | G87: 0.918 | H87: Blur | I87: 4 | J87: 0.0676 | K87: 78 | L87: https://api.spotify.com/v1/tracks/1FTSo4v6BOZH9QxKc3MbVM | M87: spotify:track:1FTSo4v6BOZH9QxKc3MbVM | N87: Blur (Special Edition) | O87: Rock Classics | P87: https://api.spotify.com/v1/audio-analysis/1FTSo4v6BOZH9QxKc3MbVM | Q87: 1FTSo4v6BOZH9QxKc3MbVM | R87: Song 2 - 2012 Remaster | S87: 35471 | T87: 0.00708 | U87: 7HvIrSkKGJCzd8AKyjTJ6Q | V87: 1 | W87: 8 | X87: 121160 | Y87: 0.00178 | Z87: 1FTSo4v6BOZH9QxKc3MbVM | AA87: classic | AB87: audio_features | AC87: 37i9dQZF1DWXRqgorJj26U
A88: 0.441 | B88: 81334 | C88: 0.519 | D88: rock | E88: -14178 | F88: 0.076 | G88: 0.25 | H88: Pixies | I88: 4 | J88: 0.0353 | K88: 76 | L88: https://api.spotify.com/v1/tracks/7wCmS9TTVUcIhRalDYFgPy | M88: spotify:track:7wCmS9TTVUcIhRalDYFgPy | N88: Surfer Rosa (2007 Remaster) | O88: Rock Classics | P88: https://api.spotify.com/v1/audio-analysis/7wCmS9TTVUcIhRalDYFgPy | Q88: 7wCmS9TTVUcIhRalDYFgPy | R88: Where Is My Mind? - 2007 Remaster | S88: 32223 | T88: 0.000453 | U88: 50j4Wm1b9hLpSpPIA39Vp9 | V88: 1 | W88: 4 | X88: 234973 | Y88: 0.0204 | Z88: 7wCmS9TTVUcIhRalDYFgPy | AA88: classic | AB88: audio_features | AC88: 37i9dQZF1DWXRqgorJj26U
A89: 0.836 | B89: 113375 | C89: 0.743 | D89: rock | E89: -6465 | F89: 0.384 | G89: 0.82 | H89: The Clash | I89: 4 | J89: 0.116 | K89: 80 | L89: https://api.spotify.com/v1/tracks/39shmbIHICJ2Wxnk1fPSdz | M89: spotify:track:39shmbIHICJ2Wxnk1fPSdz | N89: Combat Rock (Remastered) | O89: Rock Classics | P89: https://api.spotify.com/v1/audio-analysis/39shmbIHICJ2Wxnk1fPSdz | Q89: 39shmbIHICJ2Wxnk1fPSdz | R89: Should I Stay or Should I Go - Remastered | S89: 1982 | T89: 0 | U89: 1ZH5g1RDq3GY1OvyD0w0s2 | V89: 1 | W89: 2 | X89: 188987 | Y89: 0.0804 | Z89: 39shmbIHICJ2Wxnk1fPSdz | AA89: classic | AB89: audio_features | AC89: 37i9dQZF1DWXRqgorJj26U
A90: 0.528 | B90: 109975 | C90: 0.932 | D90: rock | E90: -6472 | F90: 0.163 | G90: 0.757 | H90: Queen | I90: 4 | J90: 0.161 | K90: 71 | L90: https://api.spotify.com/v1/tracks/57JVGBtBLCfHw2muk5416J | M90: spotify:track:57JVGBtBLCfHw2muk5416J | N90: The Game (Deluxe Remastered Version) | O90: Rock Classics | P90: https://api.spotify.com/v1/audio-analysis/57JVGBtBLCfHw2muk5416J | Q90: 57JVGBtBLCfHw2muk5416J | R90: Another One Bites The Dust - Remastered 2011 | S90: 29399 | T90: 0.329 | U90: 6wPXUmYJ9mOWrKlLzZ5cCa | V90: 0 | W90: 5 | X90: 214653 | Y90: 0.115 | Z90: 57JVGBtBLCfHw2muk5416J | AA90: classic | AB90: audio_features | AC90: 37i9dQZF1DWXRqgorJj26U
A91: 0.905 | B91: 128019 | C91: 0.602 | D91: rock | E91: -4046 | F91: 0.117 | G91: 0.411 | H91: Muse | I91: 4 | J91: 0.0775 | K91: 75 | L91: https://api.spotify.com/v1/tracks/4VqPOruhp5EdPBeR92t6lQ | M91: spotify:track:4VqPOruhp5EdPBeR92t6lQ | N91: The Resistance | O91: Rock Classics | P91: https://api.spotify.com/v1/audio-analysis/4VqPOruhp5EdPBeR92t6lQ | Q91: 4VqPOruhp5EdPBeR92t6lQ | R91: Uprising | S91: 40066 | T91: 0.064 | U91: 0eFHYz8NmK75zSplL5qlfM | V91: 1 | W91: 2 | X91: 304840 | Y91: 0.000202 | Z91: 4VqPOruhp5EdPBeR92t6lQ | AA91: classic | AB91: audio_features | AC91: 37i9dQZF1DWXRqgorJj26U
A92: 0.519 | B92: 98883 | C92: 0.653 | D92: rock | E92: -10164 | F92: 0.101 | G92: 0.822 | H92: Buffalo Springfield | I92: 4 | J92: 0.0497 | K92: 76 | L92: https://api.spotify.com/v1/tracks/1qRA5BS78u3gME0loMl9AA | M92: spotify:track:1qRA5BS78u3gME0loMl9AA | N92: Buffalo Springfield | O92: Rock Classics | P92: https://api.spotify.com/v1/audio-analysis/1qRA5BS78u3gME0loMl9AA | Q92: 1qRA5BS78u3gME0loMl9AA | R92: For What It's Worth | S92: 24446 | T92: 0.0209 | U92: 3PkdGRruLnJ9zCtANiDrpB | V92: 1 | W92: 2 | X92: 153693 | Y92: 0.406 | Z92: 1qRA5BS78u3gME0loMl9AA | AA92: classic | AB92: audio_features | AC92: 37i9dQZF1DWXRqgorJj26U
A93: 0.946 | B93: 138.18 | C93: 0.454 | D93: rock | E93: -5978 | F93: 0.173 | G93: 0.647 | H93: Van Halen | I93: 4 | J93: 0.13 | K93: 68 | L93: https://api.spotify.com/v1/tracks/0upLyFR8Rr52ZpMp5esQoq | M93: spotify:track:0upLyFR8Rr52ZpMp5esQoq | N93: Van Halen (Remastered) | O93: Rock Classics | P93: https://api.spotify.com/v1/audio-analysis/0upLyFR8Rr52ZpMp5esQoq | Q93: 0upLyFR8Rr52ZpMp5esQoq | R93: You Really Got Me - 2015 Remaster | S93: 28531 | T93: 0 | U93: 7DdEbYFPKTZ8KB4z6L4UnQ | V93: 0 | W93: 1 | X93: 156147 | Y93: 0.0223 | Z93: 0upLyFR8Rr52ZpMp5esQoq | AA93: classic | AB93: audio_features | AC93: 37i9dQZF1DWXRqgorJj26U
A94: 0.828 | B94: 105435 | C94: 0.35 | D94: rock | E94: -5373 | F94: 0.0774 | G94: 0.147 | H94: Soundgarden | I94: 4 | J94: 0.041 | K94: 76 | L94: https://api.spotify.com/v1/tracks/2EoOZnxNgtmZaD8uUmz2nD | M94: spotify:track:2EoOZnxNgtmZaD8uUmz2nD | N94: Superunknown (Deluxe Edition) | O94: Rock Classics | P94: https://api.spotify.com/v1/audio-analysis/2EoOZnxNgtmZaD8uUmz2nD | Q94: 2EoOZnxNgtmZaD8uUmz2nD | R94: Black Hole Sun | S94: 34402 | T94: 0.000161 | U94: 29sTacnS0qA9xri6YS8xLA | V94: 1 | W94: 6 | X94: 318587 | Y94: 0.000217 | Z94: 2EoOZnxNgtmZaD8uUmz2nD | AA94: classic | AB94: audio_features | AC94: 37i9dQZF1DWXRqgorJj26U
A95: 0.349 | B95: 124348 | C95: 0.489 | D95: rock | E95: -14295 | F95: 0.0866 | G95: 0.622 | H95: Santana | I95: 4 | J95: 0.0323 | K95: 70 | L95: https://api.spotify.com/v1/tracks/4YMQXzscifAREG0a7KNGhB | M95: spotify:track:4YMQXzscifAREG0a7KNGhB | N95: Santana's Greatest Hits | O95: Rock Classics | P95: https://api.spotify.com/v1/audio-analysis/4YMQXzscifAREG0a7KNGhB | Q95: 4YMQXzscifAREG0a7KNGhB | R95: Black Magic Woman - Single Version | S95: 34516 | T95: 0.0789 | U95: 1YrdGK2y2Edq2R5gFja2ai | V95: 0 | W95: 2 | X95: 196467 | Y95: 0.676 | Z95: 4YMQXzscifAREG0a7KNGhB | AA95: classic | AB95: audio_features | AC95: 37i9dQZF1DWXRqgorJj26U
A96: 0.872 | B96: 159925 | C96: 0.587 | D96: rock | E96: -5066 | F96: 0.622 | G96: 0.735 | H96: Lenny Kravitz | I96: 4 | J96: 0.0484 | K96: 73 | L96: https://api.spotify.com/v1/tracks/1OxcIUqVmVYxT6427tbhDW | M96: spotify:track:1OxcIUqVmVYxT6427tbhDW | N96: 5 | O96: Rock Classics | P96: https://api.spotify.com/v1/audio-analysis/1OxcIUqVmVYxT6427tbhDW | Q96: 1OxcIUqVmVYxT6427tbhDW | R96: Fly Away | S96: 35927 | T96: 0 | U96: 6MCNMOCRsh6nxs7PNzc0zN | V96: 1 | W96: 7 | X96: 221333 | Y96: 0.018 | Z96: 1OxcIUqVmVYxT6427tbhDW | AA96: classic | AB96: audio_features | AC96: 37i9dQZF1DWXRqgorJj26U
A97: 0.808 | B97: 151008 | C97: 0.577 | D97: rock | E97: -7.04 | F97: 0.221 | G97: 0.869 | H97: The Police | I97: 4 | J97: 0.039 | K97: 75 | L97: https://api.spotify.com/v1/tracks/1oYYd2gnWZYrt89EBXdFiO | M97: spotify:track:1oYYd2gnWZYrt89EBXdFiO | N97: Reggatta De Blanc (Remastered 2003) | O97: Rock Classics | P97: https://api.spotify.com/v1/audio-analysis/1oYYd2gnWZYrt89EBXdFiO | Q97: 1oYYd2gnWZYrt89EBXdFiO | R97: Message In A Bottle | S97: 29130 | T97: 1.33e-05 | U97: 2EpuND32cO7CX0gXZl2NB6 | V97: 0 | W97: 1 | X97: 290280 | Y97: 0.0338 | Z97: 1oYYd2gnWZYrt89EBXdFiO | AA97: classic | AB97: audio_features | AC97: 37i9dQZF1DWXRqgorJj26U
A98: 0.758 | B98: 112113 | C98: 0.489 | D98: rock | E98: -6491 | F98: 0.092 | G98: 0.435 | H98: David Bowie | I98: 4 | J98: 0.0297 | K98: 72 | L98: https://api.spotify.com/v1/tracks/7Jh1bpe76CNTCgdgAdBw4Z | M98: spotify:track:7Jh1bpe76CNTCgdgAdBw4Z | N98: "Heroes" (2017 Remaster) | O98: Rock Classics | P98: https://api.spotify.com/v1/audio-analysis/7Jh1bpe76CNTCgdgAdBw4Z | Q98: 7Jh1bpe76CNTCgdgAdBw4Z | R98: Heroes - 2017 Remaster | S98: 1977 | T98: 0.49 | U98: 4I5zzKYd2SKDgZ9DRf5LVk | V98: 1 | W98: 7 | X98: 371413 | Y98: 0.000678 | Z98: 7Jh1bpe76CNTCgdgAdBw4Z | AA98: classic | AB98: audio_features | AC98: 37i9dQZF1DWXRqgorJj26U
A99: 0.932 | B99: 112937 | C99: 0.564 | D99: rock | E99: -10068 | F99: 0.349 | G99: 0.619 | H99: Led Zeppelin | I99: 4 | J99: 0.0554 | K99: 75 | L99: https://api.spotify.com/v1/tracks/78lgmZwycJ3nzsdgmPPGNx | M99: spotify:track:78lgmZwycJ3nzsdgmPPGNx | N99: Led Zeppelin III (Remaster) | O99: Rock Classics | P99: https://api.spotify.com/v1/audio-analysis/78lgmZwycJ3nzsdgmPPGNx | Q99: 78lgmZwycJ3nzsdgmPPGNx | R99: Immigrant Song - Remaster | S99: 1970 | T99: 0.169 | U99: 6P5QHz4XtxOmS5EuiGIPut | V99: 1 | W99: 11 | X99: 146250 | Y99: 0.013 | Z99: 78lgmZwycJ3nzsdgmPPGNx | AA99: classic | AB99: audio_features | AC99: 37i9dQZF1DWXRqgorJj26U
A100: 0.338 | B100: 177765 | C100: 0.388 | D100: rock | E100: -10054 | F100: 0.248 | G100: 0.478 | H100: Electric Light Orchestra | I100: 4 | J100: 0.0329 | K100: 76 | L100: https://api.spotify.com/v1/tracks/2RlgNHKcydI9sayD2Df2xp | M100: spotify:track:2RlgNHKcydI9sayD2Df2xp | N100: Out of the Blue | O100: Rock Classics | P100: https://api.spotify.com/v1/audio-analysis/2RlgNHKcydI9sayD2Df2xp | Q100: 2RlgNHKcydI9sayD2Df2xp | R100: Mr. Blue Sky | S100: 1977 | T100: 3.73e-06 | U100: 3usnShwygMXVZB4IV5dwnU | V100: 1 | W100: 10 | X100: 303373 | Y100: 0.652 | Z100: 2RlgNHKcydI9sayD2Df2xp | AA100: classic | AB100: audio_features | AC100: 37i9dQZF1DWXRqgorJj26U
...

Sheet TB_Music_Data
A1: Energy | B1: Tempo en BPM | C1: Danceability | D1: Playlist_genre2 | E1: Valence | F1: Track_artist | G1: Track_popularity | H1: Playlist_name | I1: Track_name | J1: Track_album_release_date | K1: Mode | L1: Key | M1: Duration_minutes | N1: Acousticness | O1: Playlist_subgenre2
A2: 0.814 | B2: 93 | C2: 0.683 | D2: =PROPER(Music_Data[[#This Row],[Playlist_genre2]]) -> Afrobeats | E2: 0.758 | F2: Tyla | G2: 78 | H2: Afro Hits | I2: PUSH 2 START | J2: 45576 | K2: 1 | L2: 2 | M2: =LEFT(Music_Data[[#This Row],[Duration_minutes]],3)/60 -> 2.6 | N2: 0.277 | O2: =PROPER(Music_Data[[#This Row],[Playlist_subgenre2]]) -> Nigerian
A3: 0.648 | B3: 93 | C3: 0.737 | D3: =PROPER(Music_Data[[#This Row],[Playlist_genre2]]) -> Afrobeats | E3: 0.746 | F3: Wizkid, Brent Faiyaz | G3: 77 | H3: African Heat | I3: Piece of My Heart (feat. Brent Faiyaz) | J3: 45583 | K3: 1 | L3: 1 | M3: =LEFT(Music_Data[[#This Row],[Duration_minutes]],3)/60 -> 4.3166667 | N3: 0.252 | O3: =PROPER(Music_Data[[#This Row],[Playlist_subgenre2]]) -> African
A4: 0.792 | B4: 113 | C4: 0.749 | D4: =PROPER(Music_Data[[#This Row],[Playlist_genre2]]) -> Afrobeats | E4: 0.903 | F4: Davido, YG Marley | G4: 76 | H4: African Heat | I4: Awuke | J4: 45596 | K4: 1 | L4: 5 | M4: =LEFT(Music_Data[[#This Row],[Duration_minutes]],3)/60 -> 2.8666667 | N4: 0.308 | O4: =PROPER(Music_Data[[#This Row],[Playlist_subgenre2]]) -> African
A5: 0.874 | B5: 118 | C5: 0.774 | D5: =PROPER(Music_Data[[#This Row],[Playlist_genre2]]) -> Afrobeats | E5: 0.927 | F5: Wizkid | G5: 75 | H5: Afro Hits | I5: Kese (Dance) | J5: 45611 | K5: 0 | L5: 5 | M5: =LEFT(Music_Data[[#This Row],[Duration_minutes]],3)/60 -> 2.9 | N5: 0.142 | O5: =PROPER(Music_Data[[#This Row],[Playlist_subgenre2]]) -> Nigerian
A6: 0.634 | B6: 101 | C6: 0.502 | D6: =PROPER(Music_Data[[#This Row],[Playlist_genre2]]) -> Afrobeats | E6: 0.645 | F6: Asake, Wizkid | G6: 72 | H6: African Heat | I6: MMS | J6: 45512 | K6: 0 | L6: 8 | M6: =LEFT(Music_Data[[#This Row],[Duration_minutes]],3)/60 -> 3.65 | N6: 0.677 | O6: =PROPER(Music_Data[[#This Row],[Playlist_subgenre2]]) -> African
A7: 0.683 | B7: 145 | C7: 0.501 | D7: =PROPER(Music_Data[[#This Row],[Playlist_genre2]]) -> Afrobeats | E7: 0.623 | F7: Bnxn, Rema | G7: 71 | H7: Afro Hits | I7: Fi Kan We Kan | J7: 45580 | K7: 0 | L7: 6 | M7: =LEFT(Music_Data[[#This Row],[Duration_minutes]],3)/60 -> 2.6833333 | N7: 0.109 | O7: =PROPER(Music_Data[[#This Row],[Playlist_subgenre2]]) -> Nigerian
A8: 0.719 | B8: 113 | C8: 0.897 | D8: =PROPER(Music_Data[[#This Row],[Playlist_genre2]]) -> Afrobeats | E8: 0.546 | F8: Smur Lee, ODUMODUBLVCK, Shallipopi | G8: 71 | H8: African Heat | I8: JUJU (feat. Shallipopi) | J8: 45526 | K8: 0 | L8: 6 | M8: =LEFT(Music_Data[[#This Row],[Duration_minutes]],3)/60 -> 2.6166667 | N8: 0.116 | O8: =PROPER(Music_Data[[#This Row],[Playlist_subgenre2]]) -> African
A9: 0.819 | B9: 110 | C9: 0.726 | D9: =PROPER(Music_Data[[#This Row],[Playlist_genre2]]) -> Afrobeats | E9: 0.636 | F9: Young Jonn | G9: 70 | H9: African Heat | I9: Stronger | J9: 45394 | K9: 1 | L9: 8 | M9: =LEFT(Music_Data[[#This Row],[Duration_minutes]],3)/60 -> 2.35 | N9: 0.477 | O9: =PROPER(Music_Data[[#This Row],[Playlist_subgenre2]]) -> African
A10: 0.529 | B10: 112 | C10: 0.782 | D10: =PROPER(Music_Data[[#This Row],[Playlist_genre2]]) -> Afrobeats | E10: 0.44 | F10: Ayo Maff | G10: 69 | H10: African Heat | I10: Are you there? | J10: 45519 | K10: 1 | L10: 0 | M10: =LEFT(Music_Data[[#This Row],[Duration_minutes]],3)/60 -> 2.6 | N10: 0.509 | O10: =PROPER(Music_Data[[#This Row],[Playlist_subgenre2]]) -> African
A11: 0.651 | B11: 67 | C11: 0.49 | D11: =PROPER(Music_Data[[#This Row],[Playlist_genre2]]) -> Afrobeats | E11: 0.567 | F11: Ayo Maff, Fireboy DML | G11: 68 | H11: African Heat | I11: Dealer | J11: 45398 | K11: 1 | L11: 11 | M11: =LEFT(Music_Data[[#This Row],[Duration_minutes]],3)/60 -> 3 | N11: 0.714 | O11: =PROPER(Music_Data[[#This Row],[Playlist_subgenre2]]) -> African
A12: 0.812 | B12: 100 | C12: 0.455 | D12: =PROPER(Music_Data[[#This Row],[Playlist_genre2]]) -> Afrobeats | E12: 0.823 | F12: Darkoo, Rema | G12: 68 | H12: Afro Hits | I12: Favourite Girl (with Rema) | J12: 45512 | K12: 1 | L12: 8 | M12: =LEFT(Music_Data[[#This Row],[Duration_minutes]],3)/60 -> 3.0666667 | N12: 0.372 | O12: =PROPER(Music_Data[[#This Row],[Playlist_subgenre2]]) -> Nigerian
A13: 0.52 | B13: 958 | C13: 0.578 | D13: =PROPER(Music_Data[[#This Row],[Playlist_genre2]]) -> Afrobeats | E13: 0.425 | F13: FOLA, Bnxn | G13: 68 | H13: African Heat | I13: alone - Remix | J13: 45569 | K13: 0 | L13: 11 | M13: =LEFT(Music_Data[[#This Row],[Duration_minutes]],3)/60 -> 2.5666667 | N13: 0.554 | O13: =PROPER(Music_Data[[#This Row],[Playlist_subgenre2]]) -> African
... A420: 0.764 | B420: 140 | C420: 0.882 | D420: =PROPER(Music_Data[[#This Row],[Playlist_genre2]]) -> Gaming | E420: 0.886 | F420: Central Cee, Lil Baby | G420: 81 | H420: Top Gaming Tracks | I420: BAND4BAND (feat. Lil Baby) | J420: 45435 | K420: 1 | L420: 11 | M420: =LEFT(Music_Data[[#This Row],[Duration_minutes]],3)/60 -> 2.3333333 | N420: 0.359 | O420: =PROPER(Music_Data[[#This Row],[Playlist_subgenre2]]) -> Modern
A421: 0.62 | B421: 120 | C421: 0.857 | D421: =PROPER(Music_Data[[#This Row],[Playlist_genre2]]) -> Gaming | E421: 0.796 | F421: Charli xcx | G421: 81 | H421: Top Gaming Tracks | I421: 360 | J421: 45450 | K421: 1 | L421: 0 | M421: =LEFT(Music_Data[[#This Row],[Duration_minutes]],3)/60 -> 2.2166667 | N421: 0.646 | O421: =PROPER(Music_Data[[#This Row],[Playlist_subgenre2]]) -> Modern
A422: 0.95 | B422: 150 | C422: 0.673 | D422: =PROPER(Music_Data[[#This Row],[Playlist_genre2]]) -> Gaming | E422: 0.563 | F422: Dimitri Vegas & Like Mike, Tii´sto, Dido, W&W, Dimitri Vegas, Like Mike | G422: 81 | H422: Top Gaming Tracks | I422: Thank You (Not So Bad) | J422: 45261 | K422: 1 | L422: 11 | M422: =LEFT(Music_Data[[#This Row],[Duration_minutes]],3)/60 -> 2.3333333 | N422: 0.0229 | O422: =PROPER(Music_Data[[#This Row],[Playlist_subgenre2]]) -> Modern
A423: 0.887 | B423: 127 | C423: 0.936 | D423: =PROPER(Music_Data[[#This Row],[Playlist_genre2]]) -> Gaming | E423: 0.889 | F423: Eminem | G423: 81 | H423: Top Gaming Tracks | I423: Houdini | J423: 45443 | K423: 0 | L423: 9 | M423: =LEFT(Music_Data[[#This Row],[Duration_minutes]],3)/60 -> 3.7833333 | N423: 0.0292 | O423: =PROPER(Music_Data[[#This Row],[Playlist_subgenre2]]) -> Modern
A424: 0.745 | B424: 165 | C424: 0.808 | D424: =PROPER(Music_Data[[#This Row],[Playlist_genre2]]) -> Gaming | E424: 0.829 | F424: Eminem, Juice WRLD | G424: 81 | H424: Top Gaming Tracks | I424: Godzilla (feat. Juice WRLD) | J424: 43847 | K424: 0 | L424: 10 | M424: =LEFT(Music_Data[[#This Row],[Duration_minutes]],3)/60 -> 3.5 | N424: 0.145 | O424: =PROPER(Music_Data[[#This Row],[Playlist_subgenre2]]) -> Modern
A425: 0.558 | B425: 104 | C425: 0.943 | D425: =PROPER(Music_Data[[#This Row],[Playlist_genre2]]) -> Gaming | E425: 0.606 | F425: Jack Harlow | G425: 81 | H425: Top Gaming Tracks | I425: Lovin On Me | J425: 45240 | K425: 1 | L425: 2 | M425: =LEFT(Music_Data[[#This Row],[Duration_minutes]],3)/60 -> 2.3 | N425: 0.0026 | O425: =PROPER(Music_Data[[#This Row],[Playlist_subgenre2]]) -> Modern
A426: 0.75 | B426: 155 | C426: 0.732 | D426: =PROPER(Music_Data[[#This Row],[Playlist_genre2]]) -> Gaming | E426: 0.401 | F426: Lil Uzi Vert | G426: 81 | H426: Top Gaming Tracks | I426: XO Tour Llif3 | J426: 42972 | K426: 0 | L426: 11 | M426: =LEFT(Music_Data[[#This Row],[Duration_minutes]],3)/60 -> 3.0333333 | N426: 0.00264 | O426: =PROPER(Music_Data[[#This Row],[Playlist_subgenre2]]) -> Modern
A427: 0.632 | B427: 121 | C427: 0.762 | D427: =PROPER(Music_Data[[#This Row],[Playlist_genre2]]) -> Gaming | E427: 0.282 | F427: Lost Frequencies, Calum Scott | G427: 81 | H427: Top Gaming Tracks | I427: Where Are You Now | J427: 45240 | K427: 0 | L427: 6 | M427: =LEFT(Music_Data[[#This Row],[Duration_minutes]],3)/60 -> 2.4833333 | N427: 0.51 | O427: =PROPER(Music_Data[[#This Row],[Playlist_subgenre2]]) -> Modern
A428: 0.761 | B428: 129 | C428: 0.634 | D428: =PROPER(Music_Data[[#This Row],[Playlist_genre2]]) -> Gaming | E428: 0.785 | F428: Marshmello, Kane Brown | G428: 81 | H428: Top Gaming Tracks | I428: Miles On It | J428: 45415 | K428: 1 | L428: 5 | M428: =LEFT(Music_Data[[#This Row],[Duration_minutes]],3)/60 -> 2.8 | N428: 0.00537 | O428: =PROPER(Music_Data[[#This Row],[Playlist_subgenre2]]) -> Modern
A429: 0.586 | B429: 116 | C429: 0.896 | D429: =PROPER(Music_Data[[#This Row],[Playlist_genre2]]) -> Gaming | E429: 0.642 | F429: Roddy Ricch | G429: 81 | H429: Top Gaming Tracks | I429: The Box | J429: 43805 | K429: 0 | L429: 10 | M429: =LEFT(Music_Data[[#This Row],[Duration_minutes]],3)/60 -> 3.2666667 | N429: 0.104 | O429: =PROPER(Music_Data[[#This Row],[Playlist_subgenre2]]) -> Modern
A430: 0.537 | B430: 128 | C430: 0.921 | D430: =PROPER(Music_Data[[#This Row],[Playlist_genre2]]) -> Gaming | E430: 0.711 | F430: XXXTENTACION | G430: 81 | H430: Top Gaming Tracks | I430: Moonlight | J430: 43175 | K430: 0 | L430: 9 | M430: =LEFT(Music_Data[[#This Row],[Duration_minutes]],3)/60 -> 2.25 | N430: 0.556 | O430: =PROPER(Music_Data[[#This Row],[Playlist_subgenre2]]) -> Modern
A431: 0.741 | B431: 120 | C431: 0.771 | D431: =PROPER(Music_Data[[#This Row],[Playlist_genre2]]) -> Gaming | E431: 0.19 | F431: Zerb, The Chainsmokers, Ink | G431: 81 | H431: Top Gaming Tracks | I431: Addicted | J431: 45380 | K431: 0 | L431: 5 | M431: =LEFT(Music_Data[[#This Row],[Duration_minutes]],3)/60 -> 2.5333333 | N431: 0.0245 | O431: =PROPER(Music_Data[[#This Row],[Playlist_subgenre2]]) -> Modern
A432: 0.716 | B432: 910 | C432: 0.701 | D432: =PROPER(Music_Data[[#This Row],[Playlist_genre2]]) -> Gaming | E432: 0.732 | F432: 24kGoldn, iann dior | G432: 80 | H432: Top Gaming Tracks | I432: Mood (feat. iann dior) | J432: 44281 | K432: 0 | L432: 7 | M432: =LEFT(Music_Data[[#This Row],[Duration_minutes]],3)/60 -> 2.3333333 | N432: 0.174 | O432: =PROPER(Music_Data[[#This Row],[Playlist_subgenre2]]) -> Modern
A433: 0.673 | B433: 165 | C433: 0.529 | D433: =PROPER(Music_Data[[#This Row],[Playlist_genre2]]) -> Gaming | E433: 0.366 | F433: Drake, 21 Savage | G433: 80 | H433: Top Gaming Tracks | I433: Jimmy Cooks (feat. 21 Savage) | J433: 44729 | K433: 1 | L433: 0 | M433: =LEFT(Music_Data[[#This Row],[Duration_minutes]],3)/60 -> 3.6333333 | N433: 0.000307 | O433: =PROPER(Music_Data[[#This Row],[Playlist_subgenre2]]) -> Modern
A434: 0.773 | B434: 129 | C434: 0.681 | D434: =PROPER(Music_Data[[#This Row],[Playlist_genre2]]) -> Gaming | E434: 0.504 | F434: Eternxlkz | G434: 80 | H434: Top Gaming Tracks | I434: SLAY! | J434: 45366 | K434: 1 | L434: 1 | M434: =LEFT(Music_Data[[#This Row],[Duration_minutes]],3)/60 -> 1.7833333 | N434: 0.0863 | O434: =PROPER(Music_Data[[#This Row],[Playlist_subgenre2]]) -> Modern
A435: 0.512 | B435: 805 | C435: 0.829 | D435: =PROPER(Music_Data[[#This Row],[Playlist_genre2]]) -> Gaming | E435: 0.638 | F435: Sleepy Hallow | G435: 80 | H435: Top Gaming Tracks | I435: 2055 | J435: 44349 | K435: 0 | L435: 6 | M435: =LEFT(Music_Data[[#This Row],[Duration_minutes]],3)/60 -> 2.05 | N435: 0.492 | O435: =PROPER(Music_Data[[#This Row],[Playlist_subgenre2]]) -> Modern
A436: 0.681 | B436: 139 | C436: 0.918 | D436: =PROPER(Music_Data[[#This Row],[Playlist_genre2]]) -> Gaming | E436: 0.706 | F436: Dave, Central Cee | G436: 79 | H436: Top Gaming Tracks | I436: Sprinter | J436: 45078 | K436: 1 | L436: 1 | M436: =LEFT(Music_Data[[#This Row],[Duration_minutes]],3)/60 -> 3.8166667 | N436: 0.263 | O436: =PROPER(Music_Data[[#This Row],[Playlist_subgenre2]]) -> Modern
A437: 0.797 | B437: 122 | C437: 0.702 | D437: =PROPER(Music_Data[[#This Row],[Playlist_genre2]]) -> Gaming | E437: 0.0356 | F437: Disclosure, Eliza Doolittle, Rivo | G437: 79 | H437: Top Gaming Tracks | I437: You & Me - Rivo Remix | J437: 45282 | K437: 0 | L437: 10 | M437: =LEFT(Music_Data[[#This Row],[Duration_minutes]],3)/60 -> 3.4666667 | N437: 0.583 | O437: =PROPER(Music_Data[[#This Row],[Playlist_subgenre2]]) -> Modern
A438: 0.761 | B438: 146 | C438: 0.62 | D438: =PROPER(Music_Data[[#This Row],[Playlist_genre2]]) -> Gaming | E438: 0.194 | F438: Jungle | G438: 79 | H438: Top Gaming Tracks | I438: Back On 74 | J438: 45149 | K438: 0 | L438: 10 | M438: =LEFT(Music_Data[[#This Row],[Duration_minutes]],3)/60 -> 3.4833333 | N438: 0.207 | O438: =PROPER(Music_Data[[#This Row],[Playlist_subgenre2]]) -> Modern
A439: 0.583 | B439: 116 | C439: 0.709 | D439: =PROPER(Music_Data[[#This Row],[Playlist_genre2]]) -> Gaming | E439: 0.533 | F439: Metro Boomin, Future, Chris Brown | G439: 79 | H439: Top Gaming Tracks | I439: Superhero (Heroes & Villains) [with Future & Chris Brown] | J439: 44897 | K439: 0 | L439: 5 | M439: =LEFT(Music_Data[[#This Row],[Duration_minutes]],3)/60 -> 3.0333333 | N439: 0.138 | O439: =PROPER(Music_Data[[#This Row],[Playlist_subgenre2]]) -> Modern
A440: 0.753 | B440: 127 | C440: 0.671 | D440: =PROPER(Music_Data[[#This Row],[Playlist_genre2]]) -> Gaming | E440: 0.543 | F440: Sonny Fodera, Jazzy, D.O.D | G440: 79 | H440: Top Gaming Tracks | I440: Somedays | J440: 45499 | K440: 0 | L440: 4 | M440: =LEFT(Music_Data[[#This Row],[Duration_minutes]],3)/60 -> 3.45 | N440: 0.019 | O440: =PROPER(Music_Data[[#This Row],[Playlist_subgenre2]]) -> Modern
A441: 0.512 | B441: 960 | C441: 0.803 | D441: =PROPER(Music_Data[[#This Row],[Playlist_genre2]]) -> Gaming | E441: 0.435 | F441: Bryson Tiller | G441: 78 | H441: Top Gaming Tracks | I441: Whatever She Wants | J441: 45335 | K441: 0 | L441: 9 | M441: =LEFT(Music_Data[[#This Row],[Duration_minutes]],3)/60 -> 2.6833333 | N441: 0.128 | O441: =PROPER(Music_Data[[#This Row],[Playlist_subgenre2]]) -> Modern
A442: 0.593 | B442: 120 | C442: 0.565 | D442: =PROPER(Music_Data[[#This Row],[Playlist_genre2]]) -> Gaming | E442: 0.429 | F442: d4vd | G442: 78 | H442: Top Gaming Tracks | I442: Feel It - From The Original Series ‚ÄúInvincible‚Äù | J442: 45379 | K442: 1 | L442: 8 | M442: =LEFT(Music_Data[[#This Row],[Duration_minutes]],3)/60 -> 2.6166667 | N442: 0.0288 | O442: =PROPER(Music_Data[[#This Row],[Playlist_subgenre2]]) -> Modern
A443: 0.567 | B443: 759 | C443: 0.574 | D443: =PROPER(Music_Data[[#This Row],[Playlist_genre2]]) -> Gaming | E443: 0.526 | F443: JID, 21 Savage, Baby Tate | G443: 78 | H443: Top Gaming Tracks | I443: Surround Sound (feat. 21 Savage & Baby Tate) | J443: 44865 | K443: 0 | L443: 7 | M443: =LEFT(Music_Data[[#This Row],[Duration_minutes]],3)/60 -> 3.8166667 | N443: 0.164 | O443: =PROPER(Music_Data[[#This Row],[Playlist_subgenre2]]) -> Modern
A444: 0.643 | B444: 139 | C444: 0.831 | D444: =PROPER(Music_Data[[#This Row],[Playlist_genre2]]) -> Gaming | E444: 0.142 | F444: Kendrick Lamar | G444: 78 | H444: Top Gaming Tracks | I444: euphoria | J444: 45412 | K444: 1 | L444: 1 | M444: =LEFT(Music_Data[[#This Row],[Duration_minutes]],3)/60 -> 6.3833333 | N444: 0.046 | O444: =PROPER(Music_Data[[#This Row],[Playlist_subgenre2]]) -> Modern
A445: 0.452 | B445: 900 | C445: 0.904 | D445: =PROPER(Music_Data[[#This Row],[Playlist_genre2]]) -> Gaming | E445: 0.613 | F445: Tommy Richman | G445: 78 | H445: Top Gaming Tracks | I445: DEVIL IS A LIE | J445: 45457 | K445: 1 | L445: 9 | M445: =LEFT(Music_Data[[#This Row],[Duration_minutes]],3)/60 -> 2.1666667 | N445: 0.174 | O445: =PROPER(Music_Data[[#This Row],[Playlist_subgenre2]]) -> Modern
A446: 0.573 | B446: 140 | C446: 0.911 | D446: =PROPER(Music_Data[[#This Row],[Playlist_genre2]]) -> Gaming | E446: 0.972 | F446: Central Cee | G446: 77 | H446: Top Gaming Tracks | I446: Doja | J446: 44763 | K446: 1 | L446: 6 | M446: =LEFT(Music_Data[[#This Row],[Duration_minutes]],3)/60 -> 16.216667 | N446: 0.38 | O446: =PROPER(Music_Data[[#This Row],[Playlist_subgenre2]]) -> Modern
A447: 0.934 | B447: 880 | C447: 0.777 | D447: =PROPER(Music_Data[[#This Row],[Playlist_genre2]]) -> Gaming | E447: 0.637 | F447: Chase & Status, Stormzy | G447: 77 | H447: Top Gaming Tracks | I447: BACKBONE | J447: 45512 | K447: 1 | L447: 2 | M447: =LEFT(Music_Data[[#This Row],[Duration_minutes]],3)/60 -> 2.7666667 | N447: 0.285 | O447: =PROPER(Music_Data[[#This Row],[Playlist_subgenre2]]) -> Modern
... A532: 0.636 | B532: 145 | C532: 0.837 | D532: =PROPER(Music_Data[[#This Row],[Playlist_genre2]]) -> Hip-Hop | E532: 0.274 | F532: 21 Savage | G532: 77 | H532: Chill Hop | I532: a lot | J532: 43455 | K532: 1 | L532: 1 | M532: =LEFT(Music_Data[[#This Row],[Duration_minutes]],3)/60 -> 4.8 | N532: 0.0395 | O532: =PROPER(Music_Data[[#This Row],[Playlist_subgenre2]]) -> Chill
A533: 0.782 | B533: 940 | C533: 0.701 | D533: =PROPER(Music_Data[[#This Row],[Playlist_genre2]]) -> Hip-Hop | E533: 0.57 | F533: Baby Keem | G533: 77 | H533: Melodic Rap | I533: 16 | J533: 44449 | K533: 1 | L533: 1 | M533: =LEFT(Music_Data[[#This Row],[Duration_minutes]],3)/60 -> 2.6 | N533: 0.0918 | O533: =PROPER(Music_Data[[#This Row],[Playlist_subgenre2]]) -> Melodic
A534: 0.573 | B534: 140 | C534: 0.911 | D534: =PROPER(Music_Data[[#This Row],[Playlist_genre2]]) -> Hip-Hop | E534: 0.972 | F534: Central Cee | G534: 77 | H534: UK Drill | I534: Doja | J534: 44763 | K534: 1 | L534: 6 | M534: =LEFT(Music_Data[[#This Row],[Duration_minutes]],3)/60 -> 16.216667 | N534: 0.38 | O534: =PROPER(Music_Data[[#This Row],[Playlist_subgenre2]]) -> Drill
A535: 0.413 | B535: 131 | C535: 0.772 | D535: =PROPER(Music_Data[[#This Row],[Playlist_genre2]]) -> Hip-Hop | E535: 0.211 | F535: Chief Keef | G535: 77 | H535: Gangster Rap | I535: Love Sosa | J535: 40909 | K535: 0 | L535: 0 | M535: =LEFT(Music_Data[[#This Row],[Duration_minutes]],3)/60 -> 4.1 | N535: 0.0361 | O535: =PROPER(Music_Data[[#This Row],[Playlist_subgenre2]]) -> Gangster
A536: 0.413 | B536: 131 | C536: 0.772 | D536: =PROPER(Music_Data[[#This Row],[Playlist_genre2]]) -> Hip-Hop | E536: 0.211 | F536: Chief Keef | G536: 77 | H536: Trap | I536: Love Sosa | J536: 40909 | K536: 0 | L536: 0 | M536: =LEFT(Music_Data[[#This Row],[Duration_minutes]],3)/60 -> 4.1 | N536: 0.0361 | O536: =PROPER(Music_Data[[#This Row],[Playlist_subgenre2]]) -> Trap
A537: 0.283 | B537: 970 | C537: 0.766 | D537: =PROPER(Music_Data[[#This Row],[Playlist_genre2]]) -> Hip-Hop | E537: 0.144 | F537: Drake | G537: 77 | H537: Chill Hop | I537: Teenage Fever | J537: 42812 | K537: 0 | L537: 8 | M537: =LEFT(Music_Data[[#This Row],[Duration_minutes]],3)/60 -> 3.65 | N537: 0.111 | O537: =PROPER(Music_Data[[#This Row],[Playlist_subgenre2]]) -> Chill
A538: 0.754 | B538: 131 | C538: 0.863 | D538: =PROPER(Music_Data[[#This Row],[Playlist_genre2]]) -> Hip-Hop | E538: 0.301 | F538: Future | G538: 77 | H538: RapCaviar | I538: LIL DEMON | J538: 45555 | K538: 1 | L538: 11 | M538: =LEFT(Music_Data[[#This Row],[Duration_minutes]],3)/60 -> 2.3166667 | N538: 0.00125 | O538: =PROPER(Music_Data[[#This Row],[Playlist_subgenre2]]) -> Modern
A539: 0.657 | B539: 124 | C539: 0.883 | D539: =PROPER(Music_Data[[#This Row],[Playlist_genre2]]) -> Hip-Hop | E539: 0.284 | F539: Future | G539: 77 | H539: Trap | I539: PUFFIN ON ZOOTIEZ | J539: 44680 | K539: 1 | L539: 8 | M539: =LEFT(Music_Data[[#This Row],[Duration_minutes]],3)/60 -> 2.8666667 | N539: 0.0603 | O539: =PROPER(Music_Data[[#This Row],[Playlist_subgenre2]]) -> Trap
A540: 0.651 | B540: 163 | C540: 0.665 | D540: =PROPER(Music_Data[[#This Row],[Playlist_genre2]]) -> Hip-Hop | E540: 0.237 | F540: Juice WRLD | G540: 77 | H540: Melodic Rap | I540: Lean Wit Me | J540: 43444 | K540: 1 | L540: 1 | M540: =LEFT(Music_Data[[#This Row],[Duration_minutes]],3)/60 -> 2.9166667 | N540: 0.0414 | O540: =PROPER(Music_Data[[#This Row],[Playlist_subgenre2]]) -> Melodic
A541: 0.487 | B541: 127 | C541: 0.964 | D541: =PROPER(Music_Data[[#This Row],[Playlist_genre2]]) -> Hip-Hop | E541: 0.108 | F541: Lil Baby | G541: 77 | H541: Gangster Rap | I541: Pure Cocaine | J541: 43434 | K541: 0 | L541: 10 | M541: =LEFT(Music_Data[[#This Row],[Duration_minutes]],3)/60 -> 2.5666667 | N541: 0.00127 | O541: =PROPER(Music_Data[[#This Row],[Playlist_subgenre2]]) -> Gangster
A542: 0.586 | B542: 125 | C542: 0.731 | D542: =PROPER(Music_Data[[#This Row],[Playlist_genre2]]) -> Hip-Hop | E542: 0.147 | F542: NLE Choppa, 41, Kyle Richh | G542: 77 | H542: RapCaviar | I542: Or What | J542: 45541 | K542: 0 | L542: 1 | M542: =LEFT(Music_Data[[#This Row],[Duration_minutes]],3)/60 -> 3.3166667 | N542: 0.116 | O542: =PROPER(Music_Data[[#This Row],[Playlist_subgenre2]]) -> Modern
A543: 0.538 | B543: 999 | C543: 0.829 | D543: =PROPER(Music_Data[[#This Row],[Playlist_genre2]]) -> Hip-Hop | E543: 0.389 | F543: Post Malone | G543: 77 | H543: Melodic Rap | I543: Wow. | J543: 43714 | K543: 0 | L543: 11 | M543: =LEFT(Music_Data[[#This Row],[Duration_minutes]],3)/60 -> 2.4833333 | N543: 0.137 | O543: =PROPER(Music_Data[[#This Row],[Playlist_subgenre2]]) -> Melodic
A544: 0.821 | B544: 948 | C544: 0.669 | D544: =PROPER(Music_Data[[#This Row],[Playlist_genre2]]) -> Hip-Hop | E544: 0.684 | F544: Dr. Dre, Snoop Dogg | G544: 76 | H544: Hip-Hop Drive | I544: Nuthin' But A "G" Thang | J544: 33953 | K544: 0 | L544: 11 | M544: =LEFT(Music_Data[[#This Row],[Duration_minutes]],3)/60 -> 3.95 | N544: 0.00182 | O544: =PROPER(Music_Data[[#This Row],[Playlist_subgenre2]]) -> Modern
A545: 0.821 | B545: 948 | C545: 0.669 | D545: =PROPER(Music_Data[[#This Row],[Playlist_genre2]]) -> Hip-Hop | E545: 0.684 | F545: Dr. Dre, Snoop Dogg | G545: 76 | H545: 90s Hip-Hop | I545: Nuthin' But A "G" Thang | J545: 33953 | K545: 0 | L545: 11 | M545: =LEFT(Music_Data[[#This Row],[Duration_minutes]],3)/60 -> 3.95 | N545: 0.00182 | O545: =PROPER(Music_Data[[#This Row],[Playlist_subgenre2]]) -> 90S
... A553: 0.805 | B553: 142 | C553: 0.548 | D553: =PROPER(Music_Data[[#This Row],[Playlist_genre2]]) -> Hip-Hop | E553: 0.649 | F553: Pop Smoke | G553: 76 | H553: Gangster Rap | I553: Dior | J553: 43672 | K553: 1 | L553: 7 | M553: =LEFT(Music_Data[[#This Row],[Duration_minutes]],3)/60 -> 3.6 | N553: 0.212 | O553: =PROPER(Music_Data[[#This Row],[Playlist_subgenre2]]) -> Gangster
A554: 0.5 | B554: 639 | C554: 0.427 | D554: =PROPER(Music_Data[[#This Row],[Playlist_genre2]]) -> Hip-Hop | E554: 0.269 | F554: Rod Wave | G554: 76 | H554: RapCaviar | I554: 25 | J554: 45576 | K554: 1 | L554: 0 | M554: =LEFT(Music_Data[[#This Row],[Duration_minutes]],3)/60 -> 3 | N554: 0.286 | O554: =PROPER(Music_Data[[#This Row],[Playlist_subgenre2]]) -> Modern
A555: 0.733 | B555: 979 | C555: 0.825 | D555: =PROPER(Music_Data[[#This Row],[Playlist_genre2]]) -> Hip-Hop | E555: 0.62 | F555: 21 Savage, Metro Boomin, Young Thug | G555: 75 | H555: Gangster Rap | I555: Rich Nigga Shit (feat. Young Thug) | J555: 44106 | K555: 0 | L555: 1 | M555: =LEFT(Music_Data[[#This Row],[Duration_minutes]],3)/60 -> 3.1666667 | N555: 0.349 | O555: =PROPER(Music_Data[[#This Row],[Playlist_subgenre2]]) -> Gangster
A556: 0.586 | B556: 130 | C556: 0.891 | D556: =PROPER(Music_Data[[#This Row],[Playlist_genre2]]) -> Hip-Hop | E556: 0.954 | F556: Aaron May | G556: 75 | H556: Chill Hop | I556: I'm Good Luv, Enjoy. | J556: 43524 | K556: 1 | L556: 11 | M556: =LEFT(Music_Data[[#This Row],[Duration_minutes]],3)/60 -> 2.2333333 | N556: 0.0833 | O556: =PROPER(Music_Data[[#This Row],[Playlist_subgenre2]]) -> Chill
A557: 0.356 | B557: 836 | C557: 0.708 | D557: =PROPER(Music_Data[[#This Row],[Playlist_genre2]]) -> Hip-Hop | E557: 0.569 | F557: AUR | G557: 75 | H557: Desi Hip-Hop | I557: Tu hai kahan | J557: 45215 | K557: 1 | L557: 1 | M557: =LEFT(Music_Data[[#This Row],[Duration_minutes]],3)/60 -> 4.3833333 | N557: 0.437 | O557: =PROPER(Music_Data[[#This Row],[Playlist_subgenre2]]) -> Desi
A558: 0.814 | B558: 144 | C558: 0.625 | D558: =PROPER(Music_Data[[#This Row],[Playlist_genre2]]) -> Hip-Hop | E558: 0.535 | F558: Juice WRLD, Marshmello | G558: 75 | H558: Melodic Rap | I558: Come & Go (with Marshmello) | J558: 44022 | K558: 1 | L558: 0 | M558: =LEFT(Music_Data[[#This Row],[Duration_minutes]],3)/60 -> 3.4166667 | N558: 0.0172 | O558: =PROPER(Music_Data[[#This Row],[Playlist_subgenre2]]) -> Melodic
A559: 0.78 | B559: 171 | C559: 0.461 | D559: =PROPER(Music_Data[[#This Row],[Playlist_genre2]]) -> Hip-Hop | E559: 0.448 | F559: Karan Aujla, Mxrci | G559: 75 | H559: Desi Hip-Hop | I559: Winning Speech | J559: 45428 | K559: 0 | L559: 11 | M559: =LEFT(Music_Data[[#This Row],[Duration_minutes]],3)/60 -> 3.7833333 | N559: 0.128 | O559: =PROPER(Music_Data[[#This Row],[Playlist_subgenre2]]) -> Desi
A560: 0.67 | B560: 139 | C560: 0.79 | D560: =PROPER(Music_Data[[#This Row],[Playlist_genre2]]) -> Hip-Hop | E560: 0.408 | F560: Kendrick Lamar | G560: 75 | H560: Gangster Rap | I560: N95 | J560: 44694 | K560: 1 | L560: 1 | M560: =LEFT(Music_Data[[#This Row],[Duration_minutes]],3)/60 -> 3.25 | N560: 0.377 | O560: =PROPER(Music_Data[[#This Row],[Playlist_subgenre2]]) -> Gangster
A561: 0.73 | B561: 156 | C561: 0.729 | D561: =PROPER(Music_Data[[#This Row],[Playlist_genre2]]) -> Hip-Hop | E561: 0.41 | F561: King Von | G561: 75 | H561: Gangster Rap | I561: Crazy Story, Pt. 3 | J561: 43728 | K561: 0 | L561: 11 | M561: =LEFT(Music_Data[[#This Row],[Duration_minutes]],3)/60 -> 3.1833333 | N561: 0.00165 | O561: =PROPER(Music_Data[[#This Row],[Playlist_subgenre2]]) -> Gangster
A562: 0.346 | B562: 119 | C562: 0.963 | D562: =PROPER(Music_Data[[#This Row],[Playlist_genre2]]) -> Hip-Hop | E562: 0.562 | F562: Lil Baby, Drake | G562: 75 | H562: Trap | I562: Yes Indeed | J562: 43238 | K562: 0 | L562: 5 | M562: =LEFT(Music_Data[[#This Row],[Duration_minutes]],3)/60 -> 2.3666667 | N562: 0.0355 | O562: =PROPER(Music_Data[[#This Row],[Playlist_subgenre2]]) -> Trap
A563: 0.665 | B563: 943 | C563: 0.583 | D563: =PROPER(Music_Data[[#This Row],[Playlist_genre2]]) -> Hip-Hop | E563: 0.463 | F563: Matu, Veigh | G563: 75 | H563: Trap | I563: Imagina esse Cen√°rio | J563: 45544 | K563: 1 | L563: 1 | M563: =LEFT(Music_Data[[#This Row],[Duration_minutes]],3)/60 -> 2.5833333 | N563: 0.314 | O563: =PROPER(Music_Data[[#This Row],[Playlist_subgenre2]]) -> Trap
A564: 0.88 | B564: 169 | C564: 0.49 | D564: =PROPER(Music_Data[[#This Row],[Playlist_genre2]]) -> Hip-Hop | E564: 0.392 | F564: Post Malone | G564: 75 | H564: Melodic Rap | I564: Chemical | J564: 45030 | K564: 1 | L564: 2 | M564: =LEFT(Music_Data[[#This Row],[Duration_minutes]],3)/60 -> 3.0666667 | N564: 0.00154 | O564: =PROPER(Music_Data[[#This Row],[Playlist_subgenre2]]) -> Melodic
A565: 0.627 | B565: 899 | C565: 0.742 | D565: =PROPER(Music_Data[[#This Row],[Playlist_genre2]]) -> Hip-Hop | E565: 0.356 | F565: Shubh | G565: 75 | H565: Desi Hip-Hop | I565: Cheques | J565: 45065 | K565: 0 | L565: 4 | M565: =LEFT(Music_Data[[#This Row],[Duration_minutes]],3)/60 -> 3.05 | N565: 0.262 | O565: =PROPER(Music_Data[[#This Row],[Playlist_subgenre2]]) -> Desi
A566: 0.512 | B566: 144 | C566: 0.848 | D566: =PROPER(Music_Data[[#This Row],[Playlist_genre2]]) -> Hip-Hop | E566: 0.881 | F566: Shubh | G566: 75 | H566: Desi Hip-Hop | I566: One Love | J566: 45156 | K566: 1 | L566: 7 | M566: =LEFT(Music_Data[[#This Row],[Duration_minutes]],3)/60 -> 2.65 | N566: 0.284 | O566: =PROPER(Music_Data[[#This Row],[Playlist_subgenre2]]) -> Desi
... A592: 0.538 | B592: 141 | C592: 0.52 | D592: =PROPER(Music_Data[[#This Row],[Playlist_genre2]]) -> Hip-Hop | E592: 0.177 | F592: Mac Miller | G592: 73 | H592: Chill Hop | I592: Self Care | J592: 43315 | K592: 1 | L592: 1 | M592: =LEFT(Music_Data[[#This Row],[Duration_minutes]],3)/60 -> 5.75 | N592: 0.367 | O592: =PROPER(Music_Data[[#This Row],[Playlist_subgenre2]]) -> Chill
A593: 0.88 | B593: 920 | C593: 0.753 | D593: =PROPER(Music_Data[[#This Row],[Playlist_genre2]]) -> Hip-Hop | E593: 0.582 | F593: Matu | G593: 73 | H593: Trap | I593: 1993 | J593: 45544 | K593: 1 | L593: 11 | M593: =LEFT(Music_Data[[#This Row],[Duration_minutes]],3)/60 -> 2.1166667 | N593: 0.455 | O593: =PROPER(Music_Data[[#This Row],[Playlist_subgenre2]]) -> Trap
A594: 0.545 | B594: 970 | C594: 0.809 | D594: =PROPER(Music_Data[[#This Row],[Playlist_genre2]]) -> Hip-Hop | E594: 0.244 | F594: Mustard, Roddy Ricch | G594: 73 | H594: Melodic Rap | I594: Ballin' (with Roddy Ricch) | J594: 43644 | K594: 1 | L594: 7 | M594: =LEFT(Music_Data[[#This Row],[Duration_minutes]],3)/60 -> 3 | N594: 0.392 | O594: =PROPER(Music_Data[[#This Row],[Playlist_subgenre2]]) -> Melodic
A595: 0.531 | B595: 118 | C595: 0.566 | D595: =PROPER(Music_Data[[#This Row],[Playlist_genre2]]) -> Hip-Hop | E595: 0.367 | F595: Paulo Londra, Lenny Tavi°rez | G595: 73 | H595: Trap | I595: Nena Maldici√≥n (feat. Lenny Tav√°rez) | J595: 43608 | K595: 1 | L595: 6 | M595: =LEFT(Music_Data[[#This Row],[Duration_minutes]],3)/60 -> 3.7833333 | N595: 0.192 | O595: =PROPER(Music_Data[[#This Row],[Playlist_subgenre2]]) -> Trap
A596: 0.8 | B596: 139 | C596: 0.498 | D596: =PROPER(Music_Data[[#This Row],[Playlist_genre2]]) -> Hip-Hop | E596: 0.272 | F596: Post Malone, Ozzy Osbourne, Travis Scott | G596: 73 | H596: Melodic Rap | I596: Take What You Want (feat. Ozzy Osbourne & Travis Scott) | J596: 43714 | K596: 0 | L596: 1 | M596: =LEFT(Music_Data[[#This Row],[Duration_minutes]],3)/60 -> 3.8166667 | N596: 0.0903 | O596: =PROPER(Music_Data[[#This Row],[Playlist_subgenre2]]) -> Melodic
A597: 0.709 | B597: 785 | C597: 0.749 | D597: =PROPER(Music_Data[[#This Row],[Playlist_genre2]]) -> Hip-Hop | E597: 0.564 | F597: Real Boston Richey | G597: 73 | H597: RapCaviar | I597: Help Me | J597: 45443 | K597: 1 | L597: 6 | M597: =LEFT(Music_Data[[#This Row],[Duration_minutes]],3)/60 -> 3.0166667 | N597: 0.155 | O597: =PROPER(Music_Data[[#This Row],[Playlist_subgenre2]]) -> Modern
A598: 0.718 | B598: 899 | C598: 0.716 | D598: =PROPER(Music_Data[[#This Row],[Playlist_genre2]]) -> Hip-Hop | E598: 0.91 | F598: Shubh | G598: 73 | H598: Desi Hip-Hop | I598: Bandana | J598: 45380 | K598: 0 | L598: 6 | M598: =LEFT(Music_Data[[#This Row],[Duration_minutes]],3)/60 -> 2.5666667 | N598: 0.0452 | O598: =PROPER(Music_Data[[#This Row],[Playlist_subgenre2]]) -> Desi
A599: 0.818 | B599: 960 | C599: 0.889 | D599: =PROPER(Music_Data[[#This Row],[Playlist_genre2]]) -> Hip-Hop | E599: 0.782 | F599: The Notorious B.I.G. | G599: 73 | H599: 90s Hip-Hop | I599: Juicy - 2005 Remaster | J599: 34590 | K599: 1 | L599: 9 | M599: =LEFT(Music_Data[[#This Row],[Duration_minutes]],3)/60 -> 5.0333333 | N599: 0.47 | O599: =PROPER(Music_Data[[#This Row],[Playlist_subgenre2]]) -> 90S
A600: 0.653 | B600: 142 | C600: 0.493 | D600: =PROPER(Music_Data[[#This Row],[Playlist_genre2]]) -> Hip-Hop | E600: 0.852 | F600: Tyler, The Creator, YoungBoy Never Broke Again, Ty Dolla $ign | G600: 73 | H600: Chill Hop | I600: WUSYANAME (feat. Youngboy Never Broke Again & Ty Dolla $ign) | J600: 44372 | K600: 0 | L600: 0 | M600: =LEFT(Music_Data[[#This Row],[Duration_minutes]],3)/60 -> 2.0166667 | N600: 0.269 | O600: =PROPER(Music_Data[[#This Row],[Playlist_subgenre2]]) -> Chill
A601: 0.369 | B601: 140 | C601: 0.735 | D601: =PROPER(Music_Data[[#This Row],[Playlist_genre2]]) -> Hip-Hop | E601: 0.235 | F601: YNW Melly | G601: 73 | H601: Melodic Rap | I601: Suicidal | J601: 43791 | K601: 0 | L601: 9 | M601: =LEFT(Music_Data[[#This Row],[Duration_minutes]],3)/60 -> 3.7 | N601: 0.334 | O601: =PROPER(Music_Data[[#This Row],[Playlist_subgenre2]]) -> Melodic
A602: 0.803 | B602: 675 | C602: 0.284 | D602: =PROPER(Music_Data[[#This Row],[Playlist_genre2]]) -> Hip-Hop | E602: 0.553 | F602: A$AP Rocky, Joe Fox, Kanye West | G602: 72 | H602: Chill Hop | I602: Jukebox Joints (feat. Joe Fox & Kanye West) | J602: 42150 | K602: 0 | L602: 2 | M602: =LEFT(Music_Data[[#This Row],[Duration_minutes]],3)/60 -> 5.3833333 | N602: 0.302 | O602: =PROPER(Music_Data[[#This Row],[Playlist_subgenre2]]) -> Chill
A603: 0.6 | B603: 113 | C603: 0.883 | D603: =PROPER(Music_Data[[#This Row],[Playlist_genre2]]) -> Hip-Hop | E603: 0.691 | F603: Bad Bunny | G603: 72 | H603: Trap | I603: BOOKER T | J603: 44162 | K603: 1 | L603: 7 | M603: =LEFT(Music_Data[[#This Row],[Duration_minutes]],3)/60 -> 2.6 | N603: 0.114 | O603: =PROPER(Music_Data[[#This Row],[Playlist_subgenre2]]) -> Trap
A604: 0.718 | B604: 128 | C604: 0.76 | D604: =PROPER(Music_Data[[#This Row],[Playlist_genre2]]) -> Hip-Hop | E604: 0.557 | F604: Bad Bunny, Bryant Myers | G604: 72 | H604: Trap | I604: Pa Ti | J604: 42737 | K604: 1 | L604: 1 | M604: =LEFT(Music_Data[[#This Row],[Duration_minutes]],3)/60 -> 3.1833333 | N604: 0.348 | O604: =PROPER(Music_Data[[#This Row],[Playlist_subgenre2]]) -> Trap
A605: 0.62 | B605: 941 | C605: 0.9 | D605: =PROPER(Music_Data[[#This Row],[Playlist_genre2]]) -> Hip-Hop | E605: 0.867 | F605: Big Pun, Joe | G605: 72 | H605: 90s Hip-Hop | I605: Still Not a Player (feat. Joe) - Radio Version | J605: 35913 | K605: 0 | L605: 4 | M605: =LEFT(Music_Data[[#This Row],[Duration_minutes]],3)/60 -> 3.9333333 | N605: 0.2 | O605: =PROPER(Music_Data[[#This Row],[Playlist_subgenre2]]) -> 90S
... A764: 0.536 | B764: 975 | C764: 0.716 | D764: =PROPER(Music_Data[[#This Row],[Playlist_genre2]]) -> Latin | E764: 0.359 | F764: Junior H | G764: 84 | H764: Viva Latino | I764: PI√âNSALO | J764: 45204 | K764: 0 | L764: 2 | M764: =LEFT(Music_Data[[#This Row],[Duration_minutes]],3)/60 -> 4 | N764: 0.452 | O764: =PROPER(Music_Data[[#This Row],[Playlist_subgenre2]]) -> Modern
A765: 0.712 | B765: 919 | C765: 0.848 | D765: =PROPER(Music_Data[[#This Row],[Playlist_genre2]]) -> Latin | E765: 0.692 | F765: KAROL G, Feid, DFZM, Ovy On The Drums, J Balvin, Maluma, Ryan Castro, Blessd | G765: 84 | H765: Viva Latino | I765: 57 | J765: 45604 | K765: 0 | L765: 1 | M765: =LEFT(Music_Data[[#This Row],[Duration_minutes]],3)/60 -> 4.9666667 | N765: 0.221 | O765: =PROPER(Music_Data[[#This Row],[Playlist_subgenre2]]) -> Modern
A766: 0.712 | B766: 919 | C766: 0.848 | D766: =PROPER(Music_Data[[#This Row],[Playlist_genre2]]) -> Latin | E766: 0.692 | F766: KAROL G, Feid, DFZM, Ovy On The Drums, J Balvin, Maluma, Ryan Castro, Blessd | G766: 84 | H766: Reggaeton Hits | I766: 57 | J766: 45604 | K766: 0 | L766: 1 | M766: =LEFT(Music_Data[[#This Row],[Duration_minutes]],3)/60 -> 4.9666667 | N766: 0.221 | O766: =PROPER(Music_Data[[#This Row],[Playlist_subgenre2]]) -> Reggaeton
A767: 0.707 | B767: 820 | C767: 0.786 | D767: =PROPER(Music_Data[[#This Row],[Playlist_genre2]]) -> Latin | E767: 0.691 | F767: Maisak, Feid | G767: 84 | H767: Viva Latino | I767: SE ME OLVIDA | J767: 45527 | K767: 0 | L767: 7 | M767: =LEFT(Music_Data[[#This Row],[Duration_minutes]],3)/60 -> 3.75 | N767: 0.0399 | O767: =PROPER(Music_Data[[#This Row],[Playlist_subgenre2]]) -> Modern
A768: 0.519 | B768: 100 | C768: 0.763 | D768: =PROPER(Music_Data[[#This Row],[Playlist_genre2]]) -> Latin | E768: 0.804 | F768: FloyyMenor | G768: 83 | H768: Reggaeton Hits | I768: PELIGROSA | J768: 45513 | K768: 0 | L768: 6 | M768: =LEFT(Music_Data[[#This Row],[Duration_minutes]],3)/60 -> 2.2333333 | N768: 0.22 | O768: =PROPER(Music_Data[[#This Row],[Playlist_subgenre2]]) -> Reggaeton
A769: 0.738 | B769: 169 | C769: 0.841 | D769: =PROPER(Music_Data[[#This Row],[Playlist_genre2]]) -> Latin | E769: 0.484 | F769: KAROL G, Peso Pluma | G769: 83 | H769: Reggaeton Hits | I769: QLONA | J769: 45148 | K769: 0 | L769: 7 | M769: =LEFT(Music_Data[[#This Row],[Duration_minutes]],3)/60 -> 2.8666667 | N769: 0.52 | O769: =PROPER(Music_Data[[#This Row],[Playlist_subgenre2]]) -> Reggaeton
A770: 0.583 | B770: 115 | C770: 0.669 | D770: =PROPER(Music_Data[[#This Row],[Playlist_genre2]]) -> Latin | E770: 0.271 | F770: Victor Mendivil, Oscar Maydon | G770: 83 | H770: Reggaeton Hits | I770: Mejores Jordans | J770: 45503 | K770: 1 | L770: 1 | M770: =LEFT(Music_Data[[#This Row],[Duration_minutes]],3)/60 -> 3.9 | N770: 0.603 | O770: =PROPER(Music_Data[[#This Row],[Playlist_subgenre2]]) -> Reggaeton
A771: 0.724 | B771: 101 | C771: 0.556 | D771: =PROPER(Music_Data[[#This Row],[Playlist_genre2]]) -> Latin | E771: 0.681 | F771: Duki, Myke Towers | G771: 82 | H771: Viva Latino | I771: Nueva Era | J771: 45596 | K771: 1 | L771: 0 | M771: =LEFT(Music_Data[[#This Row],[Duration_minutes]],3)/60 -> 4.1 | N771: 0.267 | O771: =PROPER(Music_Data[[#This Row],[Playlist_subgenre2]]) -> Modern
A772: 0.642 | B772: 833 | C772: 0.463 | D772: =PROPER(Music_Data[[#This Row],[Playlist_genre2]]) -> Latin | E772: 0.339 | F772: Future, Drake, Tems | G772: 82 | H772: Afro-Latin Party | I772: WAIT FOR U (feat. Drake & Tems) | J772: 44680 | K772: 1 | L772: 1 | M772: =LEFT(Music_Data[[#This Row],[Duration_minutes]],3)/60 -> 3.15 | N772: 0.314 | O772: =PROPER(Music_Data[[#This Row],[Playlist_subgenre2]]) -> Afro-Latin
A773: 0.832 | B773: 985 | C773: 0.742 | D773: =PROPER(Music_Data[[#This Row],[Playlist_genre2]]) -> Latin | E773: 0.716 | F773: Grupo Frontera | G773: 82 | H773: Viva Latino | I773: Hecha Pa' M√≠ | J773: 45568 | K773: 1 | L773: 8 | M773: =LEFT(Music_Data[[#This Row],[Duration_minutes]],3)/60 -> 3.25 | N773: 0.0857 | O773: =PROPER(Music_Data[[#This Row],[Playlist_subgenre2]]) -> Modern
A774: 0.646 | B774: 176 | C774: 0.756 | D774: =PROPER(Music_Data[[#This Row],[Playlist_genre2]]) -> Latin | E774: 0.429 | F774: J Balvin, Bad Bunny | G774: 82 | H774: Reggaeton Hits | I774: LA CANCI√ìN | J774: 43644 | K774: 1 | L774: 7 | M774: =LEFT(Music_Data[[#This Row],[Duration_minutes]],3)/60 -> 4.0333333 | N774: 0.152 | O774: =PROPER(Music_Data[[#This Row],[Playlist_subgenre2]]) -> Reggaeton
A775: 0.701 | B775: 175 | C775: 0.73 | D775: =PROPER(Music_Data[[#This Row],[Playlist_genre2]]) -> Latin | E775: 0.785 | F775: Maluma | G775: 82 | H775: Reggaeton Hits | I775: Borro Cassette | J775: 42307 | K775: 0 | L775: 5 | M775: =LEFT(Music_Data[[#This Row],[Duration_minutes]],3)/60 -> 3.45 | N775: 0.132 | O775: =PROPER(Music_Data[[#This Row],[Playlist_subgenre2]]) -> Reggaeton
A776: 0.737 | B776: 919 | C776: 0.708 | D776: =PROPER(Music_Data[[#This Row],[Playlist_genre2]]) -> Latin | E776: 0.607 | F776: Myke Towers | G776: 82 | H776: Reggaeton Hits | I776: LALA | J776: 45008 | K776: 1 | L776: 1 | M776: =LEFT(Music_Data[[#This Row],[Duration_minutes]],3)/60 -> 3.2833333 | N776: 0.0739 | O776: =PROPER(Music_Data[[#This Row],[Playlist_subgenre2]]) -> Reggaeton
A777: 0.563 | B777: 105 | C777: 0.833 | D777: =PROPER(Music_Data[[#This Row],[Playlist_genre2]]) -> Latin | E777: 0.343 | F777: Rauw Alejandro, Bad Bunny | G777: 82 | H777: Viva Latino | I777: Qu√© Pasar√≠a... | J777: 45611 | K777: 0 | L777: 4 | M777: =LEFT(Music_Data[[#This Row],[Duration_minutes]],3)/60 -> 3.0333333 | N777: 0.528 | O777: =PROPER(Music_Data[[#This Row],[Playlist_subgenre2]]) -> Modern
A778: 0.578 | B778: 199 | C778: 0.734 | D778: =PROPER(Music_Data[[#This Row],[Playlist_genre2]]) -> Latin | E778: 0.88 | F778: W Sound, Blessd, Ovy On The Drums | G778: 82 | H778: Viva Latino | I778: Soltera - W Sound 01 | J778: 45510 | K778: 1 | L778: 1 | M778: =LEFT(Music_Data[[#This Row],[Duration_minutes]],3)/60 -> 2.3666667 | N778: 0.155 | O778: =PROPER(Music_Data[[#This Row],[Playlist_subgenre2]]) -> Modern
... A840: 0.718 | B840: 105 | C840: 0.848 | D840: =PROPER(Music_Data[[#This Row],[Playlist_genre2]]) -> Latin | E840: 0.564 | F840: Maria Becerra, Yandel | G840: 74 | H840: Viva Latino | I840: SEXO ES LA MODA | J840: 45596 | K840: 0 | L840: 9 | M840: =LEFT(Music_Data[[#This Row],[Duration_minutes]],3)/60 -> 2.75 | N840: 0.183 | O840: =PROPER(Music_Data[[#This Row],[Playlist_subgenre2]]) -> Modern
A841: 0.673 | B841: 879 | C841: 0.818 | D841: =PROPER(Music_Data[[#This Row],[Playlist_genre2]]) -> Latin | E841: 0.695 | F841: Mora, JHAYCO | G841: 74 | H841: Reggaeton Hits | I841: 512 | J841: 44232 | K841: 0 | L841: 4 | M841: =LEFT(Music_Data[[#This Row],[Duration_minutes]],3)/60 -> 3.2166667 | N841: 0.348 | O841: =PROPER(Music_Data[[#This Row],[Playlist_subgenre2]]) -> Reggaeton
...

Sheet Dashboard
A1: Analisis de las Caracteristicas y la Distribucion de las canciones mas escuchadas de Spotify
A2: Si Spotify prioriza canciones con alta energía, ritmo bailable y producción digital en sus playlists mas escuchadas, aumentará el engagement de los usuarios, ya que en sus algoritmos y listas editoriales estas características coinciden con las preferencias predominantes de las canciones más escuchadas. | T2: Siguiente Pag
S7: Valence
S9: Acusticness
S12: Danceablilty
S14: Energy
S20: Total Canciones Pop
S22: Total Canciones Modern
S25: Total Canciones Throwback Party

Sheet TB_Caracteristicas
A1: Caracteristicas de las canciones mas escuchadas | J1: SI.ANIDADA
A3: Energy | B3: Tempo | C3: Danceability | D3: Valence | E3: Track_popularity | F3: Mode | G3: Key | H3: Duration_minutes | I3: Acousticness | J3: Popularidad | K3: Track_album_release_date | L3: Variables | M3: Promedios de todas las canciones
A4: 0.592 | B4: 93 | C4: 0.521 | D4: 0.535 | E4: 100 | F4: 0 | G4: 6 | H4: =LEFT(Music_Data[[#This Row],[Duration_minutes]],3)/60 -> 2.6 | I4: 0.308 | J4: =IF(E4>=94,"Muy Popular",IF(E4>=86,"Popular",IF(E4>=78,"No muy popular","Casi nada popular"))) -> Muy Popular | K4: 45576 | L4: Energy | M4: =AVERAGE(TB_Caracteristicas!$A$4:$A$1675) -> 0.6671802 | Q4: Siguiente Pag
A5: 0.592 | B5: 93 | C5: 0.521 | D5: 0.535 | E5: 100 | F5: 0 | G5: 6 | H5: =LEFT(Music_Data[[#This Row],[Duration_minutes]],3)/60 -> 4.3166667 | I5: 0.308 | J5: =IF(E5>=94,"Muy Popular",IF(E5>=86,"Popular",IF(E5>=78,"No muy popular","Casi nada popular"))) -> Muy Popular | K5: 45583 | L5: Danceability | M5: =AVERAGE(TB_Caracteristicas!$C$4:$C$1675) -> 0.65009629
A6: 0.592 | B6: 113 | C6: 0.521 | D6: 0.535 | E6: 100 | F6: 0 | G6: 6 | H6: =LEFT(Music_Data[[#This Row],[Duration_minutes]],3)/60 -> 2.8666667 | I6: 0.308 | J6: =IF(E6>=94,"Muy Popular",IF(E6>=86,"Popular",IF(E6>=78,"No muy popular","Casi nada popular"))) -> Muy Popular | K6: 45596 | L6: Acousticness | M6: =AVERAGE(TB_Caracteristicas!$I$4:$I$1675) -> 0.22162031
A7: 0.783 | B7: 118 | C7: 0.777 | D7: 0.939 | E7: 98 | F7: 0 | G7: 0 | H7: =LEFT(Music_Data[[#This Row],[Duration_minutes]],3)/60 -> 2.9 | I7: 0.0283 | J7: =IF(E7>=94,"Muy Popular",IF(E7>=86,"Popular",IF(E7>=78,"No muy popular","Casi nada popular"))) -> Muy Popular | K7: 45611 | L7: Valence | M7: =AVERAGE(TB_Caracteristicas!$D$4:$D$1675) -> 0.52491316
A8: 0.783 | B8: 101 | C8: 0.777 | D8: 0.939 | E8: 98 | F8: 0 | G8: 0 | H8: =LEFT(Music_Data[[#This Row],[Duration_minutes]],3)/60 -> 3.65 | I8: 0.0283 | J8: =IF(E8>=94,"Muy Popular",IF(E8>=86,"Popular",IF(E8>=78,"No muy popular","Casi nada popular"))) -> Muy Popular | K8: 45512
A9: 0.507 | B9: 145 | C9: 0.747 | D9: 0.438 | E9: 97 | F9: 1 | G9: 2 | H9: =LEFT(Music_Data[[#This Row],[Duration_minutes]],3)/60 -> 2.6833333 | I9: 0.2 | J9: =IF(E9>=94,"Muy Popular",IF(E9>=86,"Popular",IF(E9>=78,"No muy popular","Casi nada popular"))) -> Muy Popular | K9: 45580 | L9: Tonalidad | M9: Suma de Track_popularity
A10: 0.507 | B10: 113 | C10: 0.747 | D10: 0.438 | E10: 97 | F10: 1 | G10: 2 | H10: =LEFT(Music_Data[[#This Row],[Duration_minutes]],3)/60 -> 2.6166667 | I10: 0.2 | J10: =IF(E10>=94,"Muy Popular",IF(E10>=86,"Popular",IF(E10>=78,"No muy popular","Casi nada popular"))) -> Muy Popular | K10: 45526 | L10: 0 | M10: 11598
A11: 0.507 | B11: 110 | C11: 0.747 | D11: 0.438 | E11: 97 | F11: 1 | G11: 2 | H11: =LEFT(Music_Data[[#This Row],[Duration_minutes]],3)/60 -> 2.35 | I11: 0.2 | J11: =IF(E11>=94,"Muy Popular",IF(E11>=86,"Popular",IF(E11>=78,"No muy popular","Casi nada popular"))) -> Muy Popular | K11: 45394 | L11: 1 | M11: 17104
A12: 0.582 | B12: 112 | C12: 0.7 | D12: 0.785 | E12: 94 | F12: 0 | G12: 11 | H12: =LEFT(Music_Data[[#This Row],[Duration_minutes]],3)/60 -> 2.6 | I12: 0.0502 | J12: =IF(E12>=94,"Muy Popular",IF(E12>=86,"Popular",IF(E12>=78,"No muy popular","Casi nada popular"))) -> Muy Popular | K12: 45519 | L12: 2 | M12: 11572
A13: 0.582 | B13: 67 | C13: 0.7 | D13: 0.785 | E13: 94 | F13: 0 | G13: 11 | H13: =LEFT(Music_Data[[#This Row],[Duration_minutes]],3)/60 -> 3 | I13: 0.0502 | J13: =IF(E13>=94,"Muy Popular",IF(E13>=86,"Popular",IF(E13>=78,"No muy popular","Casi nada popular"))) -> Muy Popular | K13: 45398 | L13: 3 | M13: 4062
A14: 0.582 | B14: 100 | C14: 0.7 | D14: 0.785 | E14: 94 | F14: 0 | G14: 11 | H14: =LEFT(Music_Data[[#This Row],[Duration_minutes]],3)/60 -> 3.0666667 | I14: 0.0502 | J14: =IF(E14>=94,"Muy Popular",IF(E14>=86,"Popular",IF(E14>=78,"No muy popular","Casi nada popular"))) -> Muy Popular | K14: 45512 | L14: 4 | M14: 9262
A15: 0.808 | B15: 958 | C15: 0.554 | D15: 0.372 | E15: 93 | F15: 1 | G15: 1 | H15: =LEFT(Music_Data[[#This Row],[Duration_minutes]],3)/60 -> 2.5666667 | I15: 0.214 | J15: =IF(E15>=94,"Muy Popular",IF(E15>=86,"Popular",IF(E15>=78,"No muy popular","Casi nada popular"))) -> Popular | K15: 45569 | L15: 5 | M15: 11538
A16: 0.247 | B16: 197 | C16: 0.467 | D16: 0.126 | E16: 93 | F16: 0 | G16: 6 | H16: =LEFT(Music_Data[[#This Row],[Duration_minutes]],3)/60 -> 3.2166667 | I16: 0.612 | J16: =IF(E16>=94,"Muy Popular",IF(E16>=86,"Popular",IF(E16>=78,"No muy popular","Casi nada popular"))) -> Popular | K16: 45532 | L16: 6 | M16: 10263
A17: 0.651 | B17: 147 | C17: 0.694 | D17: 0.471 | E17: 93 | F17: 1 | G17: 6 | H17: =LEFT(Music_Data[[#This Row],[Duration_minutes]],3)/60 -> 2.2833333 | I17: 0.496 | J17: =IF(E17>=94,"Muy Popular",IF(E17>=86,"Popular",IF(E17>=78,"No muy popular","Casi nada popular"))) -> Popular | K17: 45483 | L17: 7 | M17: 11475
A18: 0.668 | B18: 171 | C18: 0.924 | D18: 0.787 | E18: 93 | F18: 1 | G18: 11 | H18: =LEFT(Music_Data[[#This Row],[Duration_minutes]],3)/60 -> 2.1833333 | I18: 0.446 | J18: =IF(E18>=94,"Muy Popular",IF(E18>=86,"Popular",IF(E18>=78,"No muy popular","Casi nada popular"))) -> Popular | K18: 45478 | L18: 8 | M18: 8831
A19: 0.651 | B19: 113 | C19: 0.694 | D19: 0.471 | E19: 93 | F19: 1 | G19: 6 | H19: =LEFT(Music_Data[[#This Row],[Duration_minutes]],3)/60 -> 2.2833333 | I19: 0.496 | J19: =IF(E19>=94,"Muy Popular",IF(E19>=86,"Popular",IF(E19>=78,"No muy popular","Casi nada popular"))) -> Popular | K19: 45184 | L19: 9 | M19: 10210
A20: 0.668 | B20: 944 | C20: 0.924 | D20: 0.787 | E20: 93 | F20: 1 | G20: 11 | H20: =LEFT(Music_Data[[#This Row],[Duration_minutes]],3)/60 -> 4.8333333 | I20: 0.446 | J20: =IF(E20>=94,"Muy Popular",IF(E20>=86,"Popular",IF(E20>=78,"No muy popular","Casi nada popular"))) -> Popular | K20: 42895 | L20: 10 | M20: 8425
A21: 0.808 | B21: 102 | C21: 0.554 | D21: 0.372 | E21: 93 | F21: 1 | G21: 1 | H21: =LEFT(Music_Data[[#This Row],[Duration_minutes]],3)/60 -> 3.7833333 | I21: 0.214 | J21: =IF(E21>=94,"Muy Popular",IF(E21>=86,"Popular",IF(E21>=78,"No muy popular","Casi nada popular"))) -> Popular | K21: 36717 | L21: 11 | M21: 13124
A22: 0.413 | B22: 102 | C22: 0.494 | D22: 0.273 | E22: 93 | F22: 1 | G22: 11 | H22: =LEFT(Music_Data[[#This Row],[Duration_minutes]],3)/60 -> 3.3 | I22: 0.682 | J22: =IF(E22>=94,"Muy Popular",IF(E22>=86,"Popular",IF(E22>=78,"No muy popular","Casi nada popular"))) -> Popular | K22: 43910 | L22: Total general | M22: 127464
A23: 0.907 | B23: 113 | C23: 0.674 | D23: 0.721 | E23: 93 | F23: 1 | G23: 3 | H23: =LEFT(Music_Data[[#This Row],[Duration_minutes]],3)/60 -> 3.9333333 | I23: 0.101 | J23: =IF(E23>=94,"Muy Popular",IF(E23>=86,"Popular",IF(E23>=78,"No muy popular","Casi nada popular"))) -> Popular | K23: 41275
A24: 0.651 | B24: 130 | C24: 0.694 | D24: 0.471 | E24: 93 | F24: 1 | G24: 6 | H24: =LEFT(Music_Data[[#This Row],[Duration_minutes]],3)/60 -> 3.9833333 | I24: 0.496 | J24: =IF(E24>=94,"Muy Popular",IF(E24>=86,"Popular",IF(E24>=78,"No muy popular","Casi nada popular"))) -> Popular | K24: 44036 | L24: *Teniendo en cuenta que los valores del 0 al 11 corresponden a la tonalidad de la canacion , 0 siendo Do y 11 Si
A25: 0.247 | B25: 833 | C25: 0.467 | D25: 0.126 | E25: 93 | F25: 0 | G25: 6 | H25: =LEFT(Music_Data[[#This Row],[Duration_minutes]],3)/60 -> 3.15 | I25: 0.612 | J25: =IF(E25>=94,"Muy Popular",IF(E25>=86,"Popular",IF(E25>=78,"No muy popular","Casi nada popular"))) -> Popular | K25: 44680
A26: 0.668 | B26: 129 | C26: 0.924 | D26: 0.787 | E26: 93 | F26: 1 | G26: 11 | H26: =LEFT(Music_Data[[#This Row],[Duration_minutes]],3)/60 -> 4.0166667 | I26: 0.446 | J26: =IF(E26>=94,"Muy Popular",IF(E26>=86,"Popular",IF(E26>=78,"No muy popular","Casi nada popular"))) -> Popular | K26: 41901
A27: 0.413 | B27: 137 | C27: 0.494 | D27: 0.273 | E27: 93 | F27: 1 | G27: 11 | H27: =LEFT(Music_Data[[#This Row],[Duration_minutes]],3)/60 -> 2.6833333 | I27: 0.682 | J27: =IF(E27>=94,"Muy Popular",IF(E27>=86,"Popular",IF(E27>=78,"No muy popular","Casi nada popular"))) -> Popular | K27: 43565 | L27: Modos | M27: Suma de Track_popularity
A28: 0.668 | B28: 107 | C28: 0.924 | D28: 0.787 | E28: 93 | F28: 1 | G28: 11 | H28: =LEFT(Music_Data[[#This Row],[Duration_minutes]],3)/60 -> 5.85 | I28: 0.446 | J28: =IF(E28>=94,"Muy Popular",IF(E28>=86,"Popular",IF(E28>=78,"No muy popular","Casi nada popular"))) -> Popular | K28: 41640 | L28: 0 | M28: 53620
A29: 0.722 | B29: 148 | C29: 0.769 | D29: 0.57 | E29: 92 | F29: 0 | G29: 11 | H29: =LEFT(Music_Data[[#This Row],[Duration_minutes]],3)/60 -> 3.0333333 | I29: 0.0584 | J29: =IF(E29>=94,"Muy Popular",IF(E29>=86,"Popular",IF(E29>=78,"No muy popular","Casi nada popular"))) -> Popular | K29: 44659 | L29: 1 | M29: 73844
A30: 0.756 | B30: 139 | C30: 0.66 | D30: 0.838 | E30: 92 | F30: 0 | G30: 0 | H30: =LEFT(Music_Data[[#This Row],[Duration_minutes]],3)/60 -> 3.8166667 | I30: 0.00289 | J30: =IF(E30>=94,"Muy Popular",IF(E30>=86,"Popular",IF(E30>=78,"No muy popular","Casi nada popular"))) -> Popular | K30: 45078 | L30: Total general | M30: 127464
A31: 0.722 | B31: 201 | C31: 0.769 | D31: 0.57 | E31: 92 | F31: 0 | G31: 11 | H31: =LEFT(Music_Data[[#This Row],[Duration_minutes]],3)/60 -> 4.5166667 | I31: 0.0584 | J31: =IF(E31>=94,"Muy Popular",IF(E31>=86,"Popular",IF(E31>=78,"No muy popular","Casi nada popular"))) -> Popular | K31: 44274
A32: 0.756 | B32: 103 | C32: 0.66 | D32: 0.838 | E32: 92 | F32: 0 | G32: 0 | H32: =LEFT(Music_Data[[#This Row],[Duration_minutes]],3)/60 -> 5.65 | I32: 0.00289 | J32: =IF(E32>=94,"Muy Popular",IF(E32>=86,"Popular",IF(E32>=78,"No muy popular","Casi nada popular"))) -> Popular | K32: 45009
A33: 0.722 | B33: 117 | C33: 0.769 | D33: 0.57 | E33: 92 | F33: 0 | G33: 11 | H33: =LEFT(Music_Data[[#This Row],[Duration_minutes]],3)/60 -> 4.2833333 | I33: 0.0584 | J33: =IF(E33>=94,"Muy Popular",IF(E33>=86,"Popular",IF(E33>=78,"No muy popular","Casi nada popular"))) -> Popular | K33: 42881
A34: 0.722 | B34: 961 | C34: 0.769 | D34: 0.57 | E34: 92 | F34: 0 | G34: 11 | H34: =LEFT(Music_Data[[#This Row],[Duration_minutes]],3)/60 -> 3.5166667 | I34: 0.0584 | J34: =IF(E34>=94,"Muy Popular",IF(E34>=86,"Popular",IF(E34>=78,"No muy popular","Casi nada popular"))) -> Popular | K34: 44827
A35: 0.406 | B35: 121 | C35: 0.53 | D35: 0.338 | E35: 90 | F35: 1 | G35: 10 | H35: =LEFT(Music_Data[[#This Row],[Duration_minutes]],3)/60 -> 3.8166667 | I35: 0.656 | J35: =IF(E35>=94,"Muy Popular",IF(E35>=86,"Popular",IF(E35>=78,"No muy popular","Casi nada popular"))) -> Popular | K35: 41901
A36: 0.76 | B36: 135 | C36: 0.701 | D36: 0.69 | E36: 90 | F36: 1 | G36: 0 | H36: =LEFT(Music_Data[[#This Row],[Duration_minutes]],3)/60 -> 3.2166667 | I36: 0.107 | J36: =IF(E36>=94,"Muy Popular",IF(E36>=86,"Popular",IF(E36>=78,"No muy popular","Casi nada popular"))) -> Popular | K36: 43399
A37: 0.76 | B37: 932 | C37: 0.701 | D37: 0.69 | E37: 90 | F37: 1 | G37: 0 | H37: =LEFT(Music_Data[[#This Row],[Duration_minutes]],3)/60 -> 4.3166667 | I37: 0.107 | J37: =IF(E37>=94,"Muy Popular",IF(E37>=86,"Popular",IF(E37>=78,"No muy popular","Casi nada popular"))) -> Popular | K37: 45583
A38: 0.406 | B38: 133 | C38: 0.53 | D38: 0.338 | E38: 90 | F38: 1 | G38: 10 | H38: =LEFT(Music_Data[[#This Row],[Duration_minutes]],3)/60 -> 2.95 | I38: 0.656 | J38: =IF(E38>=94,"Muy Popular",IF(E38>=86,"Popular",IF(E38>=78,"No muy popular","Casi nada popular"))) -> Popular | K38: 44687
A39: 0.807 | B39: 723 | C39: 0.612 | D39: 0.398 | E39: 90 | F39: 1 | G39: 10 | H39: =LEFT(Music_Data[[#This Row],[Duration_minutes]],3)/60 -> 3.9 | I39: 0.0495 | J39: =IF(E39>=94,"Muy Popular",IF(E39>=86,"Popular",IF(E39>=78,"No muy popular","Casi nada popular"))) -> Popular | K39: 44407
A40: 0.417 | B40: 159 | C40: 0.464 | D40: 0.479 | E40: 90 | F40: 0 | G40: 0 | H40: =LEFT(Music_Data[[#This Row],[Duration_minutes]],3)/60 -> 4.8166667 | I40: 0.136 | J40: =IF(E40>=94,"Muy Popular",IF(E40>=86,"Popular",IF(E40>=78,"No muy popular","Casi nada popular"))) -> Popular | K40: 40102
A41: 0.559 | B41: 779 | C41: 0.558 | D41: 0.62 | E41: 90 | F41: 1 | G41: 6 | H41: =LEFT(Music_Data[[#This Row],[Duration_minutes]],3)/60 -> 2.95 | I41: 0.371 | J41: =IF(E41>=94,"Muy Popular",IF(E41>=86,"Popular",IF(E41>=78,"No muy popular","Casi nada popular"))) -> Popular | K41: 45177
A42: 0.727 | B42: 129 | C42: 0.739 | D42: 0.676 | E42: 90 | F42: 0 | G42: 11 | H42: =LEFT(Music_Data[[#This Row],[Duration_minutes]],3)/60 -> 6.55 | I42: 0.0678 | J42: =IF(E42>=94,"Muy Popular",IF(E42>=86,"Popular",IF(E42>=78,"No muy popular","Casi nada popular"))) -> Popular | K42: 42594 | L42: *Hay que tomar el 0 como Modo Menor y el 1 como Modo Mayor
A43: 0.559 | B43: 797 | C43: 0.558 | D43: 0.62 | E43: 90 | F43: 1 | G43: 6 | H43: =LEFT(Music_Data[[#This Row],[Duration_minutes]],3)/60 -> 4.0333333 | I43: 0.371 | J43: =IF(E43>=94,"Muy Popular",IF(E43>=86,"Popular",IF(E43>=78,"No muy popular","Casi nada popular"))) -> Popular | K43: 43553
A44: 0.725 | B44: 130 | C44: 0.894 | D44: 0.838 | E44: 89 | F44: 0 | G44: 10 | H44: =LEFT(Music_Data[[#This Row],[Duration_minutes]],3)/60 -> 4.4666667 | I44: 0.00434 | J44: =IF(E44>=94,"Muy Popular",IF(E44>=86,"Popular",IF(E44>=78,"No muy popular","Casi nada popular"))) -> Popular | K44: 43525 | L44: Variables | M44: Promedios Generales
A45: 0.604 | B45: 109 | C45: 0.561 | D45: 0.242 | E45: 89 | F45: 1 | G45: 9 | H45: =LEFT(Music_Data[[#This Row],[Duration_minutes]],3)/60 -> 4.0166667 | I45: 0.199 | J45: =IF(E45>=94,"Muy Popular",IF(E45>=86,"Popular",IF(E45>=78,"No muy popular","Casi nada popular"))) -> Popular | K45: 43532 | L45: Acousticness | M45: 0.22162031 | P45: =GETPIVOTDATA("Promedios de todas las canciones",$L$44,"Variables","Acousticness") -> 0.22162031
A46: 0.454 | B46: 144 | C46: 0.689 | D46: 0.912 | E46: 89 | F46: 1 | G46: 2 | H46: =LEFT(Music_Data[[#This Row],[Duration_minutes]],3)/60 -> 2.5333333 | I46: 0.0351 | J46: =IF(E46>=94,"Muy Popular",IF(E46>=86,"Popular",IF(E46>=78,"No muy popular","Casi nada popular"))) -> Popular | K46: 44512 | L46: Danceability | M46: 0.65009629 | P46: =GETPIVOTDATA("Promedios de todas las canciones",$L$44,"Variables","Danceability") -> 0.65009629
A47: 0.681 | B47: 704 | C47: 0.56 | D47: 0.388 | E47: 89 | F47: 0 | G47: 6 | H47: =LEFT(Music_Data[[#This Row],[Duration_minutes]],3)/60 -> 4.5333333 | I47: 0.103 | J47: =IF(E47>=94,"Muy Popular",IF(E47>=86,"Popular",IF(E47>=78,"No muy popular","Casi nada popular"))) -> Popular | K47: 43707 | L47: Energy | M47: 0.6671802 | P47: =GETPIVOTDATA("Promedios de todas las canciones",$L$44,"Variables","Energy") -> 0.6671802
A48: 0.872 | B48: 137 | C48: 0.466 | D48: 0.806 | E48: 89 | F48: 1 | G48: 7 | H48: =LEFT(Music_Data[[#This Row],[Duration_minutes]],3)/60 -> 3.4666667 | I48: 0.0156 | J48: =IF(E48>=94,"Muy Popular",IF(E48>=86,"Popular",IF(E48>=78,"No muy popular","Casi nada popular"))) -> Popular | K48: 43392 | L48: Valence | M48: 0.52491316 | P48: =GETPIVOTDATA("Promedios de todas las canciones",$L$44,"Variables","Valence") -> 0.52491316
A49: 0.681 | B49: 101 | C49: 0.56 | D49: 0.388 | E49: 89 | F49: 0 | G49: 6 | H49: =LEFT(Music_Data[[#This Row],[Duration_minutes]],3)/60 -> 3.65 | I49: 0.103 | J49: =IF(E49>=94,"Muy Popular",IF(E49>=86,"Popular",IF(E49>=78,"No muy popular","Casi nada popular"))) -> Popular | K49: 45512
A50: 0.689 | B50: 829 | C50: 0.724 | D50: 0.936 | E50: 89 | F50: 0 | G50: 7 | H50: =LEFT(Music_Data[[#This Row],[Duration_minutes]],3)/60 -> 3.6 | I50: 0.573 | J50: =IF(E50>=94,"Muy Popular",IF(E50>=86,"Popular",IF(E50>=78,"No muy popular","Casi nada popular"))) -> Popular | K50: 44763
A51: 0.604 | B51: 145 | C51: 0.561 | D51: 0.242 | E51: 89 | F51: 1 | G51: 9 | H51: =LEFT(Music_Data[[#This Row],[Duration_minutes]],3)/60 -> 4.05 | I51: 0.199 | J51: =IF(E51>=94,"Muy Popular",IF(E51>=86,"Popular",IF(E51>=78,"No muy popular","Casi nada popular"))) -> Popular | K51: 44736
A52: 0.471 | B52: 140 | C52: 0.472 | D52: 0.219 | E52: 89 | F52: 1 | G52: 10 | H52: =LEFT(Music_Data[[#This Row],[Duration_minutes]],3)/60 -> 3.3 | I52: 0.151 | J52: =IF(E52>=94,"Muy Popular",IF(E52>=86,"Popular",IF(E52>=78,"No muy popular","Casi nada popular"))) -> Popular | K52: 41901
A53: 0.604 | B53: 141 | C53: 0.561 | D53: 0.242 | E53: 89 | F53: 1 | G53: 9 | H53: =LEFT(Music_Data[[#This Row],[Duration_minutes]],3)/60 -> 3.4166667 | I53: 0.199 | J53: =IF(E53>=94,"Muy Popular",IF(E53>=86,"Popular",IF(E53>=78,"No muy popular","Casi nada popular"))) -> Popular | K53: 45247
A54: 0.661 | B54: 140 | C54: 0.429 | D54: 0.285 | E54: 89 | F54: 1 | G54: 11 | H54: =LEFT(Music_Data[[#This Row],[Duration_minutes]],3)/60 -> 2.4 | I54: 0.00239 | J54: =IF(E54>=94,"Muy Popular",IF(E54>=86,"Popular",IF(E54>=78,"No muy popular","Casi nada popular"))) -> Popular | K54: 45310
A55: 0.698 | B55: 104 | C55: 0.726 | D55: 0.867 | E55: 89 | F55: 1 | G55: 5 | H55: =LEFT(Music_Data[[#This Row],[Duration_minutes]],3)/60 -> 3.9833333 | I55: 0.049 | J55: =IF(E55>=94,"Muy Popular",IF(E55>=86,"Popular",IF(E55>=78,"No muy popular","Casi nada popular"))) -> Popular | K55: 42923
A56: 0.52 | B56: 125 | C56: 0.672 | D56: 0.37 | E56: 89 | F56: 1 | G56: 8 | H56: =LEFT(Music_Data[[#This Row],[Duration_minutes]],3)/60 -> 4.1166667 | I56: 0.859 | J56: =IF(E56>=94,"Muy Popular",IF(E56>=86,"Popular",IF(E56>=78,"No muy popular","Casi nada popular"))) -> Popular | K56: 44099
A57: 0.64 | B57: 102 | C57: 0.264 | D57: 0.19 | E57: 89 | F57: 1 | G57: 8 | H57: =LEFT(Music_Data[[#This Row],[Duration_minutes]],3)/60 -> 3.2666667 | I57: 0.0393 | J57: =IF(E57>=94,"Muy Popular",IF(E57>=86,"Popular",IF(E57>=78,"No muy popular","Casi nada popular"))) -> Popular | K57: 44099
A58: 0.689 | B58: 105 | C58: 0.724 | D58: 0.936 | E58: 89 | F58: 0 | G58: 7 | H58: =LEFT(Music_Data[[#This Row],[Duration_minutes]],3)/60 -> 3.65 | I58: 0.573 | J58: =IF(E58>=94,"Muy Popular",IF(E58>=86,"Popular",IF(E58>=78,"No muy popular","Casi nada popular"))) -> Popular | K58: 45007
A59: 0.52 | B59: 144 | C59: 0.672 | D59: 0.37 | E59: 89 | F59: 1 | G59: 8 | H59: =LEFT(Music_Data[[#This Row],[Duration_minutes]],3)/60 -> 3.45 | I59: 0.859 | J59: =IF(E59>=94,"Muy Popular",IF(E59>=86,"Popular",IF(E59>=78,"No muy popular","Casi nada popular"))) -> Popular | K59: 42157
A60: 0.661 | B60: 106 | C60: 0.429 | D60: 0.285 | E60: 89 | F60: 1 | G60: 11 | H60: =LEFT(Music_Data[[#This Row],[Duration_minutes]],3)/60 -> 2.25 | I60: 0.00239 | J60: =IF(E60>=94,"Muy Popular",IF(E60>=86,"Popular",IF(E60>=78,"No muy popular","Casi nada popular"))) -> Popular | K60: 45511
... A1675: 0.358 | B1675: 204 | C1675: 0.715 | D1675: 0.742 | E1675: 68 | F1675: 1 | G1675: 5 | H1675: =LEFT(Music_Data[[#This Row],[Duration_minutes]],3)/60 -> 3.2666667 | I1675: 0.743 | J1675: =IF(E1675>=94,"Muy Popular",IF(E1675>=86,"Popular",IF(E1675>=78,"No muy popular","Casi nada popular"))) -> Casi nada popular | K1675: 45359

Sheet TB_Distribucion
A1: Criterios de Distribucion | I1: Siguiente Pag
A2: Como se buscan las canciones mas escuchadas en Spotify ?
A3: Por Genero, Subgenero y Playlists
A4: Cuantos Generos musicales hay ? | C4: =COUNT(Anexas!$N7:$N34) -> 28 | D4: Cuantos Subgeneros musicales hay ? | F4: =COUNT(Anexas!$A2:$A54) -> 53 | G4: Cuantas Playlists de musica hay ? | I4: =COUNT(Playlists[ID_playlist_name]) -> 73
A5: Cual es el Genero mas escuchado ? | C5: =_xlfn.XLOOKUP(357,Generos[Cantidad de Canciones por genero],Generos[playlist_genre]) -> #N/A | D5: Cual es el Subgenero mas escuchado? | F5: =_xlfn.XLOOKUP(356,Subgenero[Canciones por subgenero],Subgenero[playlist_subgenre]) -> Modern | G5: Cual es la Playlist mas escuchada? | I5: =_xlfn.XLOOKUP(150,Playlists[Canciones por Playlist],Playlists[playlist_name]) -> Throwback Party
A6: Cuantas canciones son del el Genero mas escuchado? | C6: =MAX(Generos[Cantidad de Canciones por genero]) -> #REF! | D6: Cuantas canciones son del Subgenero mas escuchado? | F6: =MAX(Subgenero[Canciones por subgenero]) -> 356 | G6: Cuantas canciones son de la Playlist mas escuchada ? | I6: =MAX(Playlists[Canciones por Playlist]) -> 150
A7: Generos | B7: Suma de Canciones por Genero | D7: Subgenero | E7: Suma de Canciones por Subgenero | G7: Playlists | H7: Suma Canciones por Playlist
A8: Electronic | B8: 148 | D8: Classic | E8: 162 | G8: EDM Hits | H8: 60
A9: Gaming | B9: 100 | D9: Modern | E9: 356 | G9: Reggaeton Hits | H9: 101
A10: Hip-Hop | B10: 227 | D10: Reggaeton | E10: 101 | G10: Rock Classics | H10: 91
A11: Latin | B11: 184 | D11: Throwback | E11: 150 | G11: Throwback Party | H11: 150
A12: Pop | B12: 357 | D12: Total general | E12: 769 | G12: Top Gaming Tracks | H12: 100
A13: Rock | B13: 235 | G13: Total general | H13: 502
A14: Total general | B14: 1251
A56: =GETPIVOTDATA("Playlist_genre2",$A$7,"Playlist_genre2","Pop") -> 357
D78: =GETPIVOTDATA("Playlist_subgenre2",$D$7,"Playlist_subgenre2","Modern") -> 356
G92: =GETPIVOTDATA("Canciones por Playlist",$G$7,"playlist_name","Throwback Party") -> 150

Sheet Respuestas Descriptivas
A1: Caracteristicas de las canciones mas escuchadas | L1: Criterios de Distribucion | V1: Volver
A4: El analisis de estos datos sobre las caracterizticas de las canciones mas escuchadas de spotify , nos permiten visulaizar tendencias en las tecnicas de produccion y composicion para poder entender mejor cuales son las variables que hacen mas popular una cancion que otra. En el caso de cuan energicas son las canciones el promedio dio relativamente alto con un 67% . Esto quiere decir que las canciones mas esuchadas son mas energeticas y dinamicas y esto hace la cancion mas bailable lo cual queda reflejado en el alto porcentaje del promedio de 65%. | L4: Despues del analisis de los criterios de distribucion de las canciones mas escuchadas , se llega a la conclusion que el Genero mas escuchado es el Pop , el Subgenero mas escuchado es el Modern y la playlist mas escuchada es Throwback Party
L7: En base al análisis de los criterios de distribución de las canciones más escuchadas, Spotify debería enfocar su estrategia en potenciar el contenido relacionado con el género Pop, especialmente su subgénero Modern, como tambien a través de playlists temáticas que evocan nostalgia como Throwback Party. Una estrategia efectiva sería crear y promocionar más listas de reproducción que combinen éxitos modernos del pop con clásicos que conecten emocionalmente con la audiencia, apuntando a públicos jóvenes adultos. Además, se recomienda utilizar campañas de marketing y colaboraciones con artistas pop contemporáneos para reforzar el posicionamiento de estas playlists.
A10: La variable Acusticness refiere a cuantos instrumentos acusticos se usaron para grabar la cancion vs cuantos instrumentos sinteticos o digitales . El promedio del procentaje de Acustica dio bastante bajo y quiere decir que hoy la tendencia es grabar canciones con sonidos digitales y sinteticos . Por Ultimo la variable valencia de una cancion nos dice cuan alegre o triste es la narrativa de una cancion . En este caso el promedio del porcentaje dio 53% que nos dice que no hay una tendencia marcada es casi la misma cantidad de canciones tristes que alegres
A17: En el caso de la variable Mode que corresponde al Modo Menor o Mayor de una cancion hay una leve tendencia a las tonalidades menores . En cuanto a las tonalidades Re bemol y Si son las tonalidades que muestran una leve ventaja en popularidad frente a las otras pero no muy significativa
C24: Conclusion Estrategica: en base al análisis de las características de las canciones más escuchadas en Spotify, se observa una clara tendencia hacia producciones energéticas, bailables y con un predominio de sonidos digitales y sintetizados. Por lo tanto, una estrategia efectiva para Spotify sería potenciar la visibilidad de canciones con alta energía y ritmo bailable dentro de sus algoritmos de recomendación y curaduría editorial, priorizando temas con producción digital. Además, al no haber una tendencia clara en cuanto a la narrativa emocional (alegre vs. triste) ni en las tonalidades, se recomienda mantener una oferta variada en estos aspectos para captar distintos perfiles emocionales de oyentes, sin enfocarse exclusivamente en un solo tono o estado de ánimo.

Sheet Anexas
A1: ID_playlist_subgenre | B1: playlist_subgenre | C1: Canciones por subgenero | I1: ID_playlist_name | J1: playlist_name | K1: Canciones por Playlist
A2: 1 | B2: 80s | C2: =COUNTIF(G30:G1687,"80s") -> 44 | I2: 1 | J2: 80s Rock Anthems | K2: =COUNTIF(TB_Music_Data!H1629:H1675,"80s Rock Anthems") -> 9
A3: 2 | B3: 90s | C3: =COUNTIF(G30:G1687,"90s") -> 19 | I3: 2 | J3: 90s Hip-Hop | K3: =COUNTIF(Music_Data[Playlist_name],"90s hip-hop") -> 19
A4: 3 | B4: =PROPER(Subgenero[[#This Row],[playlist_subgenre]]) -> Academic | C4: =COUNTIF(G30:G1687,"academic") -> 42 | I4: 3 | J4: African Heat | K4: =COUNTIF(Music_Data[Playlist_name],"African Heat") -> 10
A5: 4 | B5: =PROPER(Subgenero[[#This Row],[playlist_subgenre]]) -> African | C5: =COUNTIF(G30:G1687,"african") -> 12 | I5: 4 | J5: Afro Hits | K5: =COUNTIF(Music_Data[Playlist_name],"Afro Hits") -> 5
A6: 5 | B6: =PROPER(Subgenero[[#This Row],[playlist_subgenre]]) -> Afro House | C6: =COUNTIF(G30:G1687,"afro house") -> 11 | I6: 5 | J6: Afro House | K6: =COUNTIF(Music_Data[Playlist_name],"Afro House") -> 11 | N6: Playlist_Genre_ID | O6: playlist_genre | P6: Cantidad de Canciones por genero
A7: 6 | B7: =PROPER(Subgenero[[#This Row],[playlist_subgenre]]) -> Afro-Latin | C7: =COUNTIF(G30:G1687,"afro-latin") -> 11 | I7: 6 | J7: Afro-Latin Party | K7: =COUNTIF(Music_Data[Playlist_name],"Afro-Latin Party") -> 11 | N7: 1 | O7: Afrobeats | P7: =COUNTIF(Music_Data[Playlist_genre2],"afrobeats") -> 0
A8: 7 | B8: =PROPER(Subgenero[[#This Row],[playlist_subgenre]]) -> Alternative | C8: =COUNTIF(G30:G1687,"alternative") -> 46 | I8: 7 | J8: Alternative Rock | K8: =COUNTIF(Music_Data[Playlist_name],"Alternative Rock") -> 46 | N8: 2 | O8: Ambient | P8: =COUNTIF(#REF!,"ambient") -> #REF!
A9: 8 | B9: =PROPER(Subgenero[[#This Row],[playlist_subgenre]]) -> American | C9: =COUNTIF(G30:G1687,"american") -> 7 | I9: 8 | J9: Ambient Chill | K9: =COUNTIF(Music_Data[Playlist_name],"Ambient Chill") -> 1 | N9: 3 | O9: Arabic | P9: =COUNTIF(#REF!,"arabic") -> #REF!
A10: 9 | B10: =PROPER(Subgenero[[#This Row],[playlist_subgenre]]) -> Anime | C10: =COUNTIF(G30:G1687,"anime") -> 11 | I10: 9 | J10: American Folk | K10: =COUNTIF(Music_Data[Playlist_name],"American Folk") -> 7 | N10: 4 | O10: Blues | P10: =COUNTIF(#REF!,"blues") -> #REF!
A11: 10 | B11: =PROPER(Subgenero[[#This Row],[playlist_subgenre]]) -> Australian | C11: =COUNTIF(G30:G1687,"australian") -> 4 | I11: 10 | J11: Anime Hits | K11: =COUNTIF(Music_Data[Playlist_name],"Anime Hits") -> 7 | N11: 5 | O11: Brazilian | P11: =COUNTIF(#REF!,"brazilian") -> #REF!
A12: 11 | B12: =PROPER(Subgenero[[#This Row],[playlist_subgenre]]) -> Bedroom | C12: =COUNTIF(G30:G1687,"bedroom") -> 11 | I12: 11 | J12: Arab X | K12: =COUNTIF(Music_Data[Playlist_name],"Arab X") -> 50 | N12: 6 | O12: Classical | P12: =COUNTIF(#REF!,"classical") -> #REF!
A13: 12 | B13: =PROPER(Subgenero[[#This Row],[playlist_subgenre]]) -> Bhangra | C13: =COUNTIF(G30:G1687,"bhangra") -> 2 | I13: 12 | J13: Australian Indie | K13: =COUNTIF(Music_Data[Playlist_name],"Australian Indie") -> 4 | N13: 7 | O13: Country | P13: =COUNTIF(#REF!,"country") -> #REF!
A14: 13 | B14: =PROPER(Subgenero[[#This Row],[playlist_subgenre]]) -> Bollywood | C14: =COUNTIF(G30:G1687,"bollywood") -> 5 | I14: 13 | J14: Bedroom Pop | K14: =COUNTIF(Music_Data[Playlist_name],"Bedroom Pop") -> 11 | N14: 8 | O14: Electronic | P14: =COUNTIF(#REF!,"electronic") -> #REF!
A15: 14 | B15: =PROPER(Subgenero[[#This Row],[playlist_subgenre]]) -> Chill | C15: =COUNTIF(G30:G1687,"chill") -> 66 | I15: 14 | J15: Bhangra Bangers | K15: =COUNTIF(Music_Data[Playlist_name],"Bhangra Bangers") -> 2 | N15: 9 | O15: Folk | P15: =COUNTIF(#REF!,"folk") -> #REF!
A16: 15 | B16: =PROPER(Subgenero[[#This Row],[playlist_subgenre]]) -> Classic | C16: =COUNTIF(G30:G1687,"classic") -> 162 | I16: 15 | J16: Bollywood Butter | K16: =COUNTIF(Music_Data[Playlist_name],"Bollywood Butter") -> 5 | N16: 10 | O16: Gaming | P16: =COUNTIF(#REF!,"gaming") -> #REF!
A17: 16 | B17: =PROPER(Subgenero[[#This Row],[playlist_subgenre]]) -> Cumbia | C17: =COUNTIF(G30:G1687,"cumbia") -> 3 | I17: 16 | J17: Bollywood Workout | K17: =COUNTIF(Music_Data[Playlist_name],"Bollywood Workout") -> 2 | N17: 11 | O17: Hip-Hop | P17: =COUNTIF(#REF!,"hip-hop") -> #REF!
A18: 17 | B18: =PROPER(Subgenero[[#This Row],[playlist_subgenre]]) -> Death | C18: =COUNTIF(G30:G1687,"death") -> 16 | I18: 17 | J18: Brazilian Funk | K18: =COUNTIF(Music_Data[Playlist_name],"Brazilian Funk") -> 14 | N18: 12 | O18: Indian | P18: =COUNTIF(#REF!,"indian") -> #REF!
A19: 18 | B19: =PROPER(Subgenero[[#This Row],[playlist_subgenre]]) -> Deep House | C19: =COUNTIF(G30:G1687,"deep house") -> 1 | I19: 18 | J19: Chill Hop | K19: =COUNTIF(Music_Data[Playlist_name],"Chill Hop") -> 40 | N19: 13 | O19: Indie | P19: =COUNTIF(#REF!,"indie") -> #REF!
A20: 19 | B20: =PROPER(Subgenero[[#This Row],[playlist_subgenre]]) -> Desi | C20: =COUNTIF(G30:G1687,"desi") -> 18 | I20: 19 | J20: Chill Spanish Vibes | K20: =COUNTIF(Music_Data[Playlist_name],"Chill Spanish Vibes") -> 25 | N20: 14 | O20: J-Pop | P20: =COUNTIF(#REF!,"j-pop") -> #REF!
A21: 20 | B21: =PROPER(Subgenero[[#This Row],[playlist_subgenre]]) -> Drama | C21: =COUNTIF(G30:G1687,"drama") -> 8 | I21: 20 | J21: Classic Blues | K21: =COUNTIF(Music_Data[Playlist_name],"Classic Blues") -> 45 | N21: 15 | O21: Jazz | P21: =COUNTIF(#REF!,"jazz") -> #REF!
A22: 21 | B22: =PROPER(Subgenero[[#This Row],[playlist_subgenre]]) -> Drill | C22: =COUNTIF(G30:G1687,"drill") -> 4 | I22: 21 | J22: Classic Country | K22: =COUNTIF(Music_Data[Playlist_name],"Classic Country") -> 3 | N22: 16 | O22: K-Pop | P22: =COUNTIF(#REF!,"k-pop") -> #REF!
A23: 22 | B23: =PROPER(Subgenero[[#This Row],[playlist_subgenre]]) -> Essential | C23: =COUNTIF(G30:G1687,"essential") -> 3 | I23: 22 | J23: Classical Essentials | K23: =COUNTIF(Music_Data[Playlist_name],"Classical Essentials") -> 3 | N23: 17 | O23: Korean | P23: =COUNTIF(#REF!,"korean") -> #REF!
A24: 23 | B24: =PROPER(Subgenero[[#This Row],[playlist_subgenre]]) -> Feel-Good | C24: =COUNTIF(G30:G1687,"feel-good") -> 22 | I24: 23 | J24: Cumbia Classics | K24: =COUNTIF(Music_Data[Playlist_name],"Cumbia Classics") -> 3 | N24: 18 | O24: Latin | P24: =COUNTIF(#REF!,"latin") -> #REF!
A25: 24 | B25: =PROPER(Subgenero[[#This Row],[playlist_subgenre]]) -> French | C25: =COUNTIF(G30:G1687,"french") -> 21 | I25: 24 | J25: Dark Academia | K25: =COUNTIF(Music_Data[Playlist_name],"Dark Academia") -> 42 | N25: 19 | O25: Lofi | P25: =COUNTIF(#REF!,"lofi") -> #REF!
A26: 25 | B26: =PROPER(Subgenero[[#This Row],[playlist_subgenre]]) -> Funk | C26: =COUNTIF(G30:G1687,"funk") -> 14 | I26: 25 | J26: Death Metal Essentials | K26: =COUNTIF(Music_Data[Playlist_name],"Death Metal Essentials") -> 16 | N26: 20 | O26: Metal | P26: =COUNTIF(#REF!,"metal") -> #REF!
A27: 26 | B27: =PROPER(Subgenero[[#This Row],[playlist_subgenre]]) -> Fusion | C27: =COUNTIF(G30:G1687,"fusion") -> 1 | I27: 26 | J27: Deep House Relax | K27: =COUNTIF(Music_Data[Playlist_name],"Deep House Relax") -> 1 | N27: 21 | O27: Pop | P27: =COUNTIF(#REF!,"pop") -> #REF!
A28: 27 | B28: =PROPER(Subgenero[[#This Row],[playlist_subgenre]]) -> Future Bass | C28: =COUNTIF(G30:G1687,"future bass") -> 3 | I28: 27 | J28: Desi Hip-Hop | K28: =COUNTIF(Music_Data[Playlist_name],"Desi Hip-Hop") -> 17 | N28: 22 | O28: Punk | P28: =COUNTIF(#REF!,"punk") -> #REF!
A29: 28 | B29: =PROPER(Subgenero[[#This Row],[playlist_subgenre]]) -> Gangster | C29: =COUNTIF(G30:G1687,"gangster") -> 41 | I29: 28 | J29: EDM Hits | K29: =COUNTIF(Music_Data[Playlist_name],"EDM Hits") -> 60 | N29: 23 | O29: R&B | P29: =COUNTIF(#REF!,"r&b") -> #REF!
A30: 29 | B30: =PROPER(Subgenero[[#This Row],[playlist_subgenre]]) -> Global | C30: =COUNTIF(G30:G1687,"global") -> 50 | G30: mainstream | I30: 29 | J30: Feel Good Indie Rock | K30: =COUNTIF(Music_Data[Playlist_name],"Feel Good Indie Rock") -> 22 | N30: 24 | O30: Reggae | P30: =COUNTIF(#REF!,"reggae") -> #REF!
A31: 30 | B31: =PROPER(Subgenero[[#This Row],[playlist_subgenre]]) -> Heavy | C31: =COUNTIF(G30:G1687,"heavy") -> 3 | G31: mainstream | I31: 30 | J31: French Rap Classics | K31: =COUNTIF(Music_Data[Playlist_name],"French Rap Classics") -> 3 | N31: 25 | O31: Rock | P31: =COUNTIF(#REF!,"rock") -> #REF!
A32: 31 | B32: =PROPER(Subgenero[[#This Row],[playlist_subgenre]]) -> Hip-Hop | C32: =COUNTIF(G30:G1687,"hip-hop") -> 4 | G32: mainstream | I32: 31 | J32: French Touch | K32: =COUNTIF(Music_Data[Playlist_name],"French Touch") -> 18 | N32: 26 | O32: Soul | P32: =COUNTIF(#REF!,"soul") -> #REF!
A33: 32 | B33: =PROPER(Subgenero[[#This Row],[playlist_subgenre]]) -> Indie | C33: =COUNTIF(G30:G1687,"indie") -> 30 | G33: mainstream | I33: 32 | J33: Future Bass | K33: =COUNTIF(Music_Data[Playlist_name],"Future Bass") -> 3 | N33: 27 | O33: Turkish | P33: =COUNTIF(#REF!,"turkish") -> #REF!
A34: 33 | B34: =PROPER(Subgenero[[#This Row],[playlist_subgenre]]) -> Mainstream | C34: =COUNTIF(G30:G1687,"mainstream") -> 19 | G34: mainstream | I34: 33 | J34: Gangster Rap | K34: =COUNTIF(Music_Data[Playlist_name],"Gangster Rap") -> 41 | N34: 28 | O34: World | P34: =COUNTIF(#REF!,"world") -> #REF!
A35: 34 | B35: =PROPER(Subgenero[[#This Row],[playlist_subgenre]]) -> Meditative | C35: =COUNTIF(G30:G1687,"meditative") -> 18 | G35: mainstream | I35: 34 | J35: Global Top 50 | K35: =COUNTIF(Music_Data[Playlist_name],"Global Top 50") -> 50
A36: 35 | B36: =PROPER(Subgenero[[#This Row],[playlist_subgenre]]) -> Melodic | C36: =COUNTIF(G30:G1687,"mainstream") -> 19 | G36: mainstream | I36: 35 | J36: Heavy Metal Classics | K36: =COUNTIF(Music_Data[Playlist_name],"Heavy Metal Classics") -> 3
A37: 36 | B37: =PROPER(Subgenero[[#This Row],[playlist_subgenre]]) -> Modern | C37: =COUNTIF(G30:G1687,"modern") -> 356 | G37: mainstream | I37: 36 | J37: Hip-Hop Drive | K37: =COUNTIF(Music_Data[Playlist_name],"Hip-Hop Drive") -> 1
A38: 37 | B38: =PROPER(Subgenero[[#This Row],[playlist_subgenre]]) -> Neo-Classical | C38: =COUNTIF(G30:G1687,"neo-classical") -> 6 | G38: mainstream | I38: 37 | J38: Indie Folk | K38: =COUNTIF(Music_Data[Playlist_name],"Indie Folk") -> 25
A39: 38 | B39: =PROPER(Subgenero[[#This Row],[playlist_subgenre]]) -> Nigerian | C39: =COUNTIF(G30:G1687,"nigerian") -> 8 | G39: mainstream | I39: 38 | J39: Indie Rock Roadtrip | K39: =COUNTIF(Music_Data[Playlist_name],"Indie Rock Roadtrip") -> 5
A40: 39 | B40: =PROPER(Subgenero[[#This Row],[playlist_subgenre]]) -> Nordic | C40: =COUNTIF(G30:G1687,"nordic") -> 1 | G40: mainstream | I40: 39 | J40: Jazz Classics | K40: =COUNTIF(Music_Data[Playlist_name],"Jazz Classics") -> 1
A41: 40 | B41: =PROPER(Subgenero[[#This Row],[playlist_subgenre]]) -> Pop | C41: =COUNTIF(G30:G1687,"pop") -> 7 | G41: mainstream | I41: 40 | J41: K-Drama OSTs | K41: =COUNTIF(Music_Data[Playlist_name],"K-Drama OSTs") -> 8
A42: 41 | B42: =PROPER(Subgenero[[#This Row],[playlist_subgenre]]) -> Pop Punk | C42: =COUNTIF(G30:G1687,"pop punk") -> 50 | G42: mainstream | I42: 41 | J42: K-Pop Daebak | K42: =COUNTIF(Music_Data[Playlist_name],"K-Pop Daebak") -> 11
A43: 42 | B43: =PROPER(Subgenero[[#This Row],[playlist_subgenre]]) -> Reggaeton | C43: =COUNTIF(G30:G1687,"reggaeton") -> 101 | G43: mainstream | I43: 42 | J43: Latino Hip-Hop | K43: =COUNTIF(Music_Data[Playlist_name],"Latino Hip-Hop") -> 2
A44: 43 | B44: =PROPER(Subgenero[[#This Row],[playlist_subgenre]]) -> Scandi | C44: =COUNTIF(G30:G1687,"scandi") -> 1 | G44: mainstream | I44: 43 | J44: Lofi Hip Hop | K44: =COUNTIF(Music_Data[Playlist_name],"Lofi Hip Hop") -> 2
A45: 44 | B45: =PROPER(Subgenero[[#This Row],[playlist_subgenre]]) -> Soft | C45: =COUNTIF(G30:G1687,"soft") -> 98 | G45: mainstream | I45: 44 | J45: Meditative Vibes | K45: =COUNTIF(Music_Data[Playlist_name],"Meditative Vibes") -> 18
A46: 45 | B46: =PROPER(Subgenero[[#This Row],[playlist_subgenre]]) -> Southern | C46: =COUNTIF(G30:G1687,"southern") -> 3 | G46: mainstream | I46: 45 | J46: Melodic Rap | K46: =COUNTIF(Music_Data[Playlist_name],"Melodic Rap") -> 28
A47: 46 | B47: =PROPER(Subgenero[[#This Row],[playlist_subgenre]]) -> Spanish | C47: =COUNTIF(G30:G1687,"spanish") -> 20 | G47: mainstream | I47: 46 | J47: Metal Essentials | K47: =COUNTIF(Music_Data[Playlist_name],"Metal Essentials") -> 16
A48: 47 | B48: =PROPER(Subgenero[[#This Row],[playlist_subgenre]]) -> Techno | C48: =COUNTIF(G30:G1687,"techno") -> 39 | G48: mainstream | I48: 47 | J48: Minimalism | K48: =COUNTIF(Music_Data[Playlist_name],"Minimalism") -> 1
A49: 48 | B49: =PROPER(Subgenero[[#This Row],[playlist_subgenre]]) -> Throat Singing | C49: =COUNTIF(G30:G1687,"throat singing") -> 4 | G49: classic | I49: 48 | J49: Neo-Classical | K49: =COUNTIF(Music_Data[Playlist_name],"Neo-Classical") -> 6
A50: 49 | B50: =PROPER(Subgenero[[#This Row],[playlist_subgenre]]) -> Throwback | C50: =COUNTIF(G30:G1687,"throwback") -> 150 | G50: classic | I50: 49 | J50: Nordic Folk | K50: =COUNTIF(Music_Data[Playlist_name],"Nordic Folk") -> 1
A51: 50 | B51: =PROPER(Subgenero[[#This Row],[playlist_subgenre]]) -> Trap | C51: =COUNTIF(G30:G1687,"trap") -> 36 | G51: classic | I51: 50 | J51: Pop Punk Powerhouses | K51: =COUNTIF(Music_Data[Playlist_name],"Pop Punk Powerhouses") -> 50
A52: 51 | B52: =PROPER(Subgenero[[#This Row],[playlist_subgenre]]) -> Tropical | C52: =COUNTIF(G30:G1687,"tropical") -> 7 | G52: classic | I52: 51 | J52: R&B Hits | K52: =COUNTIF(Music_Data[Playlist_name],"R&B Hits") -> 50
A53: 52 | B53: =PROPER(Subgenero[[#This Row],[playlist_subgenre]]) -> Vaporwave | C53: =COUNTIF(G30:G1687,"vaporwave") -> 9 | G53: classic | I53: 52 | J53: RapCaviar | K53: =COUNTIF(Music_Data[Playlist_name],"RapCaviar") -> 37
A54: 53 | B54: =PROPER(Subgenero[[#This Row],[playlist_subgenre]]) -> Workout | C54: =COUNTIF(G30:G1687,"workout") -> 2 | G54: classic | I54: 53 | J54: Reggae Classics | K54: =COUNTIF(Music_Data[Playlist_name],"Reggae Classics") -> 4
G55: classic | I55: 54 | J55: Reggae Fusion | K55: =COUNTIF(Music_Data[Playlist_name],"Reggae Fusion") -> 1
G56: classic | I56: 55 | J56: Reggaeton Hits | K56: =COUNTIF(Music_Data[Playlist_name],"Reggaeton Hits") -> 101
G57: classic | I57: 56 | J57: Rock Classics | K57: =COUNTIF(Music_Data[Playlist_name],"Rock Classics") -> 91
G58: classic | I58: 57 | J58: Rock This | K58: =COUNTIF(Music_Data[Playlist_name],"Rock This") -> 4
G59: classic | I59: 58 | J59: Scandi Pop | K59: =COUNTIF(Music_Data[Playlist_name],"Scandi Pop") -> 1
G60: classic | I60: 59 | J60: Soft Pop Hits | K60: =COUNTIF(Music_Data[Playlist_name],"Soft Pop Hits") -> 98
G61: classic | I61: 60 | J61: Soul Coffee | K61: =COUNTIF(Music_Data[Playlist_name],"Soul Coffee") -> 2
G62: classic | I62: 61 | J62: Southern Rock | K62: =COUNTIF(Music_Data[Playlist_name],"Southern Rock") -> 3
G63: classic | I63: 62 | J63: Spanish Rock Classics | K63: =COUNTIF(Music_Data[Playlist_name],"Spanish Rock Classics") -> 20
G64: classic | I64: 63 | J64: Techno Bunker | K64: =COUNTIF(Music_Data[Playlist_name],"Techno Bunker") -> 39
G65: classic | I65: 64 | J65: Throwback Party | K65: =COUNTIF(Music_Data[Playlist_name],"Throwback Party") -> 150
G66: classic | I66: 65 | J66: Today's Top Hits | K66: =COUNTIF(Music_Data[Playlist_name],"Today's Top Hits") -> 47
G67: classic | I67: 66 | J67: Top Gaming Tracks | K67: =COUNTIF(Music_Data[Playlist_name],"Top Gaming Tracks") -> 99
G68: classic | I68: 67 | J68: Trap | K68: =COUNTIF(Music_Data[Playlist_name],"Trap") -> 36
G69: classic | I69: 68 | J69: Tropical House | K69: =COUNTIF(Music_Data[Playlist_name],"Tropical House") -> 7
G70: classic | I70: 69 | J70: Turkish Pop | K70: =COUNTIF(Music_Data[Playlist_name],"Turkish Pop") -> 6
G71: classic | I71: 70 | J71: Tuvan Throat Singing | K71: =COUNTIF(Music_Data[Playlist_name],"Tuvan Throat Singing") -> 4
G72: classic | I72: 71 | J72: UK Drill | K72: =COUNTIF(Music_Data[Playlist_name],"UK Drill") -> 4
G73: classic | I73: 72 | J73: Vaporwave Essentials | K73: =COUNTIF(Music_Data[Playlist_name],"Vaporwave Essentials") -> 9
G74: classic | I74: 73 | J74: Viva Latino | K74: =COUNTIF(Music_Data[Playlist_name],"Viva Latino") -> 42
G75: classic
G76: classic
G77: classic
G78: classic
G79: classic
G80: classic
G81: classic
G82: classic
G83: classic
G84: classic
G85: classic
G86: classic
... G1687: scandi

Sheet TB_Playlist_Name
